Workbook
Name xxxxxxx: #REF!
Name qzqzqz30: #REF!
Name SSSSSSSSSSSSSS: #REF!
Name csSB_VISTA_LIBRE_Dim09: #REF!
Name corte: #REF!
Name _62_0Bcer: #REF!
Name __5_0Boro: #REF!
Name Total_Occidente: #REF!
Name _25: #REF!
Name _16___0Cons: #REF!
Name Merc: #REF!
Name TEST0: #REF!
Name anex: #REF!
Name _3_0Bcer: #REF!
Name FLUJO: #REF!
Name csBA_REP_MD_EDOSFINAnchor: #REF!
Name PEDESTALESB: #REF!
Name _SM8: #REF!
Name csSB_EDO_RES_PDCT_COLOC_2_Dim08: #REF!
Name csSB_VISTA_LIBRE_Dim04: #REF!
Name sdsd: #REF!
Name CUBES_X_DIMS: #REF!
Name SALUDO: #REF!
Name TOT: #REF!
Name VENTADEBREMS: #REF!
Name __8_0Boro: #REF!
Name Panama: #REF!
Name csSB_EDO_RES_PDCT_COLOC_2_Dim09: #REF!
Name _15_0Cafo: #REF!
Name TIENDASBR: #REF!
Name data33: #REF!
Name data65: #REF!
Name aan: #REF!
Name _DAT6: #REF!
Name AÑO94: #REF!
Name TIJUANA: #REF!
Name Ventas_nales._por_cte.3: #REF!
Name C_exportar_a_Excel: #REF!
Name _713_0Cons: #REF!
Name csSB_EDO_RES_PDCT_COMIS_2_Dim09: #REF!
Name MmExcelLinker_10E3A3B8_7658_4DCF_BA7C_F7F634B86C5F: #REF!
Name OTROSPRODTOS: #REF!
Name xxxxxxxxxx: #REF!
Name JUNIO: #REF!
Name AÑO84: #REF!
Name capita_lde_trabajo: #REF!
Name RESU2: #REF!
Name __1_0Bcer: #REF!
Name _128_0Cafo: #REF!
Name CANALTHEONE: #REF!
Name PCREDITOS: #REF!
Name _130_0Cafo: #REF!
Name _7: #REF!
Name Eigenvectores: #REF!
Name _712_0Cons: #REF!
Name FECH: #REF!
Name Ajuste3: #REF!
Name _195_0Bcer: #REF!
Name Resumen_Dlls1: #REF!
Name data19: #REF!

Sheet Resumen
B1: VARIACIONES FCST REALES A MARZO VS FCST REALES A FEBRERO
B3: CONTRIBUCIÓN NETA
B5: Unidad de Negocio | C5: Plan | D5: % | F5: Fcst Reales a Feb | G5: % | H5: Fcst Reales a Mar | I5: % | K5: Var Fcst Mar vs Fcst Feb | M5: Var Fcst Mar vs Plan
B6: Research Land | C6: =+#REF! -> #REF! | D6: 0.25328689 | F6: 33.039445 | G6: 0.16262001 | H6: =#REF! -> #REF! | I6: =#REF! -> #REF! | K6: =+H6-F6 -> #REF! | M6: =+H6-C6 -> #REF!
B7: Mkt United | C7: =+'MKT UNITED 26'!AG22 -> 107.2 | D7: 0.21367058 | F7: 96.456778 | G7: 0.19961294 | H7: ='MKT UNITED 26'!O22 -> #REF! | I7: =+'MKT UNITED 26'!AJ22 -> 0% | K7: =+H7-F7 -> #REF! | M7: =+H7-C7 -> #REF!
B8: Troader | C8: =+#REF! -> #REF! | D8: 0.17652298 | F8: 7.7767062 | G8: 0.14690027 | H8: =#REF! -> #REF! | I8: =#REF! -> #REF! | K8: =+H8-F8 -> #REF! | M8: =+H8-C8 -> #REF!
B9: Zeus | C9: =+#REF! -> #REF! | D9: =#REF! -> #REF! | F9: 40.859812 | G9: 0.28328755 | H9: =+#REF! -> #REF! | I9: =#REF! -> #REF! | K9: =+H9-F9 -> #REF! | M9: =+H9-C9 -> #REF!
B10: Promo Espacio | C10: =+#REF! -> #REF! | D10: =#REF! -> #REF! | F10: 50.897038 | G10: 0.13145145 | H10: =+#REF! -> #REF! | I10: =+#REF! -> #REF! | K10: =+H10-F10 -> #REF! | M10: =+H10-C10 -> #REF!
B11: Mexa | C11: =+#REF! -> #REF! | D11: =#REF! -> #REF! | F11: 38.018213 | G11: 0.17126882 | H11: =+#REF! -> #REF! | I11: =+#REF! -> #REF! | K11: =+H11-F11 -> #REF! | M11: =+H11-C11 -> #REF!
B12: House Of Films | C12: =+#REF! -> #REF! | D12: =+#REF! -> #REF! | F12: 44.241869 | G12: 0.21917813 | H12: =+#REF! -> #REF! | I12: =#REF! -> #REF! | K12: =+H12-F12 -> #REF! | M12: =+H12-C12 -> #REF!
B13: Nera Code | C13: =+#REF! -> #REF! | D13: =+#REF! -> #REF! | F13: 45.98408 | G13: 0.1830118 | H13: =+#REF! -> #REF! | I13: =+#REF! -> #REF! | K13: =+H13-F13 -> #REF! | M13: =+H13-C13 -> #REF!
B14: UiX | C14: =+#REF! -> #REF! | D14: =+#REF! -> #REF! | F14: 26.984561 | G14: 0.21793034 | H14: =+#REF! -> #REF! | I14: =+#REF! -> #REF! | K14: =+H14-F14 -> #REF! | M14: =+H14-C14 -> #REF!
B15: Staff - ND | C15: -70.602044 | F15: -77.286247 | H15: -75.83736 | K15: =+H15-F15 -> 1.4 | M15: =+H15-C15 -> (5.2)
B17: Total | C17: =SUM(C6:C15) -> #REF! | D17: =#REF! -> #REF! | F17: =SUM(F6:F15) -> 307.0 | G17: 0.14831924 | H17: =SUM(H6:H15) -> #REF! | I17: =#REF! -> #REF! | K17: =SUM(K6:K15) -> #REF! | M17: =SUM(M6:M15) -> #REF!

Sheet MKT UNITED 26
B1: MARKETING UNITED PRESUPUESTO 2026
AE2: Real 2025 | AG2: Plan 2026 | AI2: Fcst 2026 | AK2: Conceptos | AL2: Variaciones
C3: 2 | D3: 3 | E3: 4 | F3: 5 | G3: 6 | H3: 7 | I3: 8 | J3: 9 | K3: 10 | L3: 11 | M3: 12 | N3: 13 | AL3: Fcst 2026 vs Plan 2026 | AN3: Fcst 2026 vs Real 2025
B4: Proyección | C4: 46023 | D4: 46054 | E4: 46082 | F4: 46113 | G4: 46143 | H4: 46174 | I4: 46204 | J4: 46235 | K4: 46266 | L4: 46296 | M4: 46327 | N4: 46357 | O4: Total | AE4: $ | AF4: % | AG4: $ | AH4: % | AI4: $ | AJ4: % | AL4: $ | AM4: % | AN4: $ | AO4: %
B5: Ingresos Internos | C5: 12.383028 | D5: 29.264589 | E5: 24.061369 | F5: 37.738603 | G5: 39.871111 | H5: =VLOOKUP($B5,'[1]FCST MKT UNITED 26'!$B$4:$O$22,H$3,0) -> #REF! | I5: =VLOOKUP($B5,'[1]FCST MKT UNITED 26'!$B$4:$O$22,I$3,0) -> #REF! | J5: =VLOOKUP($B5,'[1]FCST MKT UNITED 26'!$B$4:$O$22,J$3,0) -> #REF! | K5: =VLOOKUP($B5,'[1]FCST MKT UNITED 26'!$B$4:$O$22,K$3,0) -> #REF! | L5: =VLOOKUP($B5,'[1]FCST MKT UNITED 26'!$B$4:$O$22,L$3,0) -> #REF! | M5: =VLOOKUP($B5,'[1]FCST MKT UNITED 26'!$B$4:$O$22,M$3,0) -> #REF! | N5: =VLOOKUP($B5,'[1]FCST MKT UNITED 26'!$B$4:$O$22,N$3,0) -> #REF! | O5: =+SUM(C5:N5) -> #REF! | AE5: 464.32805 | AF5: =IF((+IFERROR((AE5/$AE$7),0))<=-200%,"-200%",(+IFERROR((AE5/$AE$7),0))) -> 96% | AG5: =VLOOKUP(AK5,$B$27:$O$45,14,0) -> 436.5 | AH5: =IF((+IFERROR((AG5/$AG$7),0))<=-200%,"-200%",(+IFERROR((AG5/$AG$7),0))) -> 87% | AI5: =VLOOKUP(AK5,$B$4:$O$22,14,0) -> #REF! | AJ5: =IF((+IFERROR((AI5/$AI$7),0))<=-200%,"-200%",(+IFERROR((AI5/$AI$7),0))) -> 0% | AK5: Ingresos Internos | AL5: =+AI5-AG5 -> #REF! | AM5: =IF((IFERROR(IF(ABS(AL5/AG5)>=9.99,IF(AL5>0,9.99,-9.99),AL5/ABS(AG5)),IF(AL5=0,0,AL5/ABS(AL5))))<=-200%,"-200%",(IFERROR(IF(ABS(AL5/AG5)>=9.99,IF(AL5>0,9.99,-9.99),AL5/ABS(AG5)),IF(AL5=0,0,AL5/ABS(AL5))))) -> #REF! | AN5: =AI5-AE5 -> #REF! | AO5: =IF((IFERROR(IF(ABS(AN5/AE5)>=9.99,IF(AN5>0,9.99,-9.99),AN5/ABS(AE5)),IF(AN5=0,0,AN5/ABS(AN5))))<=-200%,"(200%)",(IFERROR(IF(ABS(AN5/AE5)>=9.99,IF(AN5>0,9.99,-9.99),AN5/ABS(AE5)),IF(AN5=0,0,AN5/ABS(AN5))))) -> #REF!
B6: Ingresos Externos | C6: 4.68591 | D6: 3.0455318 | E6: 0.654968 | F6: 2.256396 | G6: 1.765896 | H6: =VLOOKUP($B6,'[1]FCST MKT UNITED 26'!$B$4:$O$22,H$3,0) -> #REF! | I6: =VLOOKUP($B6,'[1]FCST MKT UNITED 26'!$B$4:$O$22,I$3,0) -> #REF! | J6: =VLOOKUP($B6,'[1]FCST MKT UNITED 26'!$B$4:$O$22,J$3,0) -> #REF! | K6: =VLOOKUP($B6,'[1]FCST MKT UNITED 26'!$B$4:$O$22,K$3,0) -> #REF! | L6: =VLOOKUP($B6,'[1]FCST MKT UNITED 26'!$B$4:$O$22,L$3,0) -> #REF! | M6: =VLOOKUP($B6,'[1]FCST MKT UNITED 26'!$B$4:$O$22,M$3,0) -> #REF! | N6: =VLOOKUP($B6,'[1]FCST MKT UNITED 26'!$B$4:$O$22,N$3,0) -> #REF! | O6: =+SUM(C6:N6) -> #REF! | AE6: 18.339807 | AF6: =IF((+IFERROR((AE6/$AE$7),0))<=-200%,"-200%",(+IFERROR((AE6/$AE$7),0))) -> 4% | AG6: =VLOOKUP(AK6,$B$27:$O$45,14,0) -> 65.0 | AH6: =IF((+IFERROR((AG6/$AG$7),0))<=-200%,"-200%",(+IFERROR((AG6/$AG$7),0))) -> 13% | AI6: =VLOOKUP(AK6,$B$4:$O$22,14,0) -> #REF! | AJ6: =IF((+IFERROR((AI6/$AI$7),0))<=-200%,"-200%",(+IFERROR((AI6/$AI$7),0))) -> 0% | AK6: Ingresos Externos | AL6: =+AI6-AG6 -> #REF! | AM6: =IF((IFERROR(IF(ABS(AL6/AG6)>=9.99,IF(AL6>0,9.99,-9.99),AL6/ABS(AG6)),IF(AL6=0,0,AL6/ABS(AL6))))<=-200%,"-200%",(IFERROR(IF(ABS(AL6/AG6)>=9.99,IF(AL6>0,9.99,-9.99),AL6/ABS(AG6)),IF(AL6=0,0,AL6/ABS(AL6))))) -> #REF! | AN6: =AI6-AE6 -> #REF! | AO6: =IF((IFERROR(IF(ABS(AN6/AE6)>=9.99,IF(AN6>0,9.99,-9.99),AN6/ABS(AE6)),IF(AN6=0,0,AN6/ABS(AN6))))<=-200%,"(200%)",(IFERROR(IF(ABS(AN6/AE6)>=9.99,IF(AN6>0,9.99,-9.99),AN6/ABS(AE6)),IF(AN6=0,0,AN6/ABS(AN6))))) -> #REF!
B7: Total Ingresos | C7: =C5+C6 -> 17.1 | D7: =D5+D6 -> 32.3 | E7: =E6+E5 -> 24.7 | F7: =F6+F5 -> 40.0 | G7: =G6+G5 -> 41.6 | H7: =H6+H5 -> #REF! | I7: =I6+I5 -> #REF! | J7: =J6+J5 -> #REF! | K7: =K6+K5 -> #REF! | L7: =L6+L5 -> #REF! | ... O7: =O6+O5 -> #REF! | AE7: =SUM(AE5:AE6) -> 482.7 | AF7: =IF((+IFERROR((AE7/$AE$7),0))<=-200%,"-200%",(+IFERROR((AE7/$AE$7),0))) -> 100% | AG7: =SUM(AG5:AG6) -> 501.5 | AH7: =IF((+IFERROR((AG7/$AG$7),0))<=-200%,"-200%",(+IFERROR((AG7/$AG$7),0))) -> 100% | AI7: =SUM(AI5:AI6) -> #REF! | AJ7: =IF((+IFERROR((AI7/$AI$7),0))<=-200%,"-200%",(+IFERROR((AI7/$AI$7),0))) -> 0% | AK7: Total Ingresos | AL7: =+AI7-AG7 -> #REF! | AM7: =IF((IFERROR(IF(ABS(AL7/AG7)>=9.99,IF(AL7>0,9.99,-9.99),AL7/ABS(AG7)),IF(AL7=0,0,AL7/ABS(AL7))))<=-200%,"-200%",(IFERROR(IF(ABS(AL7/AG7)>=9.99,IF(AL7>0,9.99,-9.99),AL7/ABS(AG7)),IF(AL7=0,0,AL7/ABS(AL7))))) -> #REF! | AN7: =AI7-AE7 -> #REF! | AO7: =IF((IFERROR(IF(ABS(AN7/AE7)>=9.99,IF(AN7>0,9.99,-9.99),AN7/ABS(AE7)),IF(AN7=0,0,AN7/ABS(AN7))))<=-200%,"(200%)",(IFERROR(IF(ABS(AN7/AE7)>=9.99,IF(AN7>0,9.99,-9.99),AN7/ABS(AE7)),IF(AN7=0,0,AN7/ABS(AN7))))) -> #REF!
A8: =#REF!/#REF! -> #REF! | B8: Activaciones | C8: -11.405566 | D8: -19.359604 | E8: -15.620091 | F8: -24.532327 | G8: -23.882503 | H8: =VLOOKUP($B8,'[1]FCST MKT UNITED 26'!$B$4:$O$22,H$3,0) -> #REF! | I8: =VLOOKUP($B8,'[1]FCST MKT UNITED 26'!$B$4:$O$22,I$3,0) -> #REF! | J8: =VLOOKUP($B8,'[1]FCST MKT UNITED 26'!$B$4:$O$22,J$3,0) -> #REF! | K8: =VLOOKUP($B8,'[1]FCST MKT UNITED 26'!$B$4:$O$22,K$3,0) -> #REF! | L8: =VLOOKUP($B8,'[1]FCST MKT UNITED 26'!$B$4:$O$22,L$3,0) -> #REF! | M8: =VLOOKUP($B8,'[1]FCST MKT UNITED 26'!$B$4:$O$22,M$3,0) -> #REF! | N8: =VLOOKUP($B8,'[1]FCST MKT UNITED 26'!$B$4:$O$22,N$3,0) -> #REF! | O8: =+SUM(C8:N8) -> #REF! | AE8: -336.06497 | AF8: =IF((+IFERROR((AE8/$AE$7),0))<=-200%,"-200%",(+IFERROR((AE8/$AE$7),0))) -> (70%) | AG8: =VLOOKUP(AK8,$B$27:$O$45,14,0) -> (300.9) | AH8: =IF((+IFERROR((AG8/$AG$7),0))<=-200%,"-200%",(+IFERROR((AG8/$AG$7),0))) -> (60%) | AI8: =VLOOKUP(AK8,$B$4:$O$22,14,0) -> #REF! | AJ8: =IF((+IFERROR((AI8/$AI$7),0))<=-200%,"-200%",(+IFERROR((AI8/$AI$7),0))) -> 0% | AK8: Activaciones | AL8: =+AI8-AG8 -> #REF! | AM8: =IF((IFERROR(IF(ABS(AL8/AG8)>=9.99,IF(AL8>0,9.99,-9.99),AL8/ABS(AG8)),IF(AL8=0,0,AL8/ABS(AL8))))<=-200%,"-200%",(IFERROR(IF(ABS(AL8/AG8)>=9.99,IF(AL8>0,9.99,-9.99),AL8/ABS(AG8)),IF(AL8=0,0,AL8/ABS(AL8))))) -> #REF! | AN8: =AI8-AE8 -> #REF! | AO8: =IF((IFERROR(IF(ABS(AN8/AE8)>=9.99,IF(AN8>0,9.99,-9.99),AN8/ABS(AE8)),IF(AN8=0,0,AN8/ABS(AN8))))<=-200%,"(200%)",(IFERROR(IF(ABS(AN8/AE8)>=9.99,IF(AN8>0,9.99,-9.99),AN8/ABS(AE8)),IF(AN8=0,0,AN8/ABS(AN8))))) -> #REF!
B9: Comisiones | C9: -0.0424585 | D9: -0.022924 | E9: -0.04886821 | F9: -0.04650403 | G9: -0.0137038 | H9: =VLOOKUP($B9,'[1]FCST MKT UNITED 26'!$B$4:$O$22,H$3,0) -> #REF! | I9: =VLOOKUP($B9,'[1]FCST MKT UNITED 26'!$B$4:$O$22,I$3,0) -> #REF! | J9: =VLOOKUP($B9,'[1]FCST MKT UNITED 26'!$B$4:$O$22,J$3,0) -> #REF! | K9: =VLOOKUP($B9,'[1]FCST MKT UNITED 26'!$B$4:$O$22,K$3,0) -> #REF! | L9: =VLOOKUP($B9,'[1]FCST MKT UNITED 26'!$B$4:$O$22,L$3,0) -> #REF! | M9: =VLOOKUP($B9,'[1]FCST MKT UNITED 26'!$B$4:$O$22,M$3,0) -> #REF! | N9: =VLOOKUP($B9,'[1]FCST MKT UNITED 26'!$B$4:$O$22,N$3,0) -> #REF! | O9: =+SUM(C9:N9) -> #REF! | P9: A partir de marzo, considerar promedio de alcance de enero y febrero | AE9: -0.44560217 | AF9: =IF((+IFERROR((AE9/$AE$7),0))<=-200%,"-200%",(+IFERROR((AE9/$AE$7),0))) -> (0%) | AG9: =VLOOKUP(AK9,$B$27:$O$45,14,0) -> (3.3) | AH9: =IF((+IFERROR((AG9/$AG$7),0))<=-200%,"-200%",(+IFERROR((AG9/$AG$7),0))) -> (1%) | AI9: =VLOOKUP(AK9,$B$4:$O$22,14,0) -> #REF! | AJ9: =IF((+IFERROR((AI9/$AI$7),0))<=-200%,"-200%",(+IFERROR((AI9/$AI$7),0))) -> 0% | AK9: Comisiones | AL9: =+AI9-AG9 -> #REF! | AM9: =IF((IFERROR(IF(ABS(AL9/AG9)>=9.99,IF(AL9>0,9.99,-9.99),AL9/ABS(AG9)),IF(AL9=0,0,AL9/ABS(AL9))))<=-200%,"-200%",(IFERROR(IF(ABS(AL9/AG9)>=9.99,IF(AL9>0,9.99,-9.99),AL9/ABS(AG9)),IF(AL9=0,0,AL9/ABS(AL9))))) -> #REF! | AN9: =AI9-AE9 -> #REF! | AO9: =IF((IFERROR(IF(ABS(AN9/AE9)>=9.99,IF(AN9>0,9.99,-9.99),AN9/ABS(AE9)),IF(AN9=0,0,AN9/ABS(AN9))))<=-200%,"(200%)",(IFERROR(IF(ABS(AN9/AE9)>=9.99,IF(AN9>0,9.99,-9.99),AN9/ABS(AE9)),IF(AN9=0,0,AN9/ABS(AN9))))) -> #REF!
B10: Participación Socios | C10: 0 | D10: 0 | E10: 0 | F10: 0 | G10: 0 | H10: =VLOOKUP($B10,'[1]FCST MKT UNITED 26'!$B$4:$O$22,H$3,0) -> #REF! | I10: =VLOOKUP($B10,'[1]FCST MKT UNITED 26'!$B$4:$O$22,I$3,0) -> #REF! | J10: =VLOOKUP($B10,'[1]FCST MKT UNITED 26'!$B$4:$O$22,J$3,0) -> #REF! | K10: =VLOOKUP($B10,'[1]FCST MKT UNITED 26'!$B$4:$O$22,K$3,0) -> #REF! | L10: =VLOOKUP($B10,'[1]FCST MKT UNITED 26'!$B$4:$O$22,L$3,0) -> #REF! | M10: =VLOOKUP($B10,'[1]FCST MKT UNITED 26'!$B$4:$O$22,M$3,0) -> #REF! | N10: =VLOOKUP($B10,'[1]FCST MKT UNITED 26'!$B$4:$O$22,N$3,0) -> #REF! | O10: =+SUM(C10:N10) -> #REF! | AE10: 0 | AF10: =IF((+IFERROR((AE10/$AE$7),0))<=-200%,"-200%",(+IFERROR((AE10/$AE$7),0))) -> 0% | AG10: =VLOOKUP(AK10,$B$27:$O$45,14,0) -> (2.3) | AH10: =IF((+IFERROR((AG10/$AG$7),0))<=-200%,"-200%",(+IFERROR((AG10/$AG$7),0))) -> (0%) | AI10: =VLOOKUP(AK10,$B$4:$O$22,14,0) -> #REF! | AJ10: =IF((+IFERROR((AI10/$AI$7),0))<=-200%,"-200%",(+IFERROR((AI10/$AI$7),0))) -> 0% | AK10: Participación Socios | AL10: =+AI10-AG10 -> #REF! | AM10: =IF((IFERROR(IF(ABS(AL10/AG10)>=9.99,IF(AL10>0,9.99,-9.99),AL10/ABS(AG10)),IF(AL10=0,0,AL10/ABS(AL10))))<=-200%,"-200%",(IFERROR(IF(ABS(AL10/AG10)>=9.99,IF(AL10>0,9.99,-9.99),AL10/ABS(AG10)),IF(AL10=0,0,AL10/ABS(AL10))))) -> #REF! | AN10: =AI10-AE10 -> #REF! | AO10: =IF((IFERROR(IF(ABS(AN10/AE10)>=9.99,IF(AN10>0,9.99,-9.99),AN10/ABS(AE10)),IF(AN10=0,0,AN10/ABS(AN10))))<=-200%,"(200%)",(IFERROR(IF(ABS(AN10/AE10)>=9.99,IF(AN10>0,9.99,-9.99),AN10/ABS(AE10)),IF(AN10=0,0,AN10/ABS(AN10))))) -> #REF!
B11: Costos Totales | C11: =SUM(C8:C10) -> (11.4) | D11: =SUM(D8:D10) -> (19.4) | E11: =SUM(E8:E10) -> (15.7) | F11: =SUM(F8:F10) -> (24.6) | G11: =SUM(G8:G10) -> (23.9) | H11: =SUM(H8:H10) -> #REF! | I11: =SUM(I8:I10) -> #REF! | J11: =SUM(J8:J10) -> #REF! | ... O11: =SUM(O8:O10) -> #REF! | AE11: =SUM(AE8:AE10) -> (336.5) | AF11: =IF((+IFERROR((AE11/$AE$7),0))<=-200%,"-200%",(+IFERROR((AE11/$AE$7),0))) -> (70%) | AG11: =SUM(AG8:AG10) -> (306.5) | AH11: =IF((+IFERROR((AG11/$AG$7),0))<=-200%,"-200%",(+IFERROR((AG11/$AG$7),0))) -> (61%) | AI11: =SUM(AI8:AI10) -> #REF! | AJ11: =IF((+IFERROR((AI11/$AI$7),0))<=-200%,"-200%",(+IFERROR((AI11/$AI$7),0))) -> 0% | AK11: Costos Totales | AL11: =+AI11-AG11 -> #REF! | AM11: =IF((IFERROR(IF(ABS(AL11/AG11)>=9.99,IF(AL11>0,9.99,-9.99),AL11/ABS(AG11)),IF(AL11=0,0,AL11/ABS(AL11))))<=-200%,"-200%",(IFERROR(IF(ABS(AL11/AG11)>=9.99,IF(AL11>0,9.99,-9.99),AL11/ABS(AG11)),IF(AL11=0,0,AL11/ABS(AL11))))) -> #REF! | AN11: =AI11-AE11 -> #REF! | AO11: =IF((IFERROR(IF(ABS(AN11/AE11)>=9.99,IF(AN11>0,9.99,-9.99),AN11/ABS(AE11)),IF(AN11=0,0,AN11/ABS(AN11))))<=-200%,"(200%)",(IFERROR(IF(ABS(AN11/AE11)>=9.99,IF(AN11>0,9.99,-9.99),AN11/ABS(AE11)),IF(AN11=0,0,AN11/ABS(AN11))))) -> #REF!
B12: Contribución Bruta | C12: =C7+C11 -> 5.6 | D12: =D7+D11 -> 12.9 | E12: =E7+E11 -> 9.0 | F12: =F7+F11 -> 15.4 | G12: =G7+G11 -> 17.7 | H12: =H7+H11 -> #REF! | I12: =I7+I11 -> #REF! | J12: =J7+J11 -> #REF! | ... O12: =O7+O11 -> #REF! | AE12: =AE11+AE7 -> 146.2 | AF12: =IF((+IFERROR((AE12/$AE$7),0))<=-200%,"-200%",(+IFERROR((AE12/$AE$7),0))) -> 30% | AG12: =AG7+AG11 -> 195.0 | AH12: =IF((+IFERROR((AG12/$AG$7),0))<=-200%,"-200%",(+IFERROR((AG12/$AG$7),0))) -> 39% | AI12: =AI7+AI11 -> #REF! | AJ12: =IF((+IFERROR((AI12/$AI$7),0))<=-200%,"-200%",(+IFERROR((AI12/$AI$7),0))) -> 0% | AK12: Contribución Bruta | AL12: =+AI12-AG12 -> #REF! | AM12: =IF((IFERROR(IF(ABS(AL12/AG12)>=9.99,IF(AL12>0,9.99,-9.99),AL12/ABS(AG12)),IF(AL12=0,0,AL12/ABS(AL12))))<=-200%,"-200%",(IFERROR(IF(ABS(AL12/AG12)>=9.99,IF(AL12>0,9.99,-9.99),AL12/ABS(AG12)),IF(AL12=0,0,AL12/ABS(AL12))))) -> #REF! | AN12: =AI12-AE12 -> #REF! | AO12: =IF((IFERROR(IF(ABS(AN12/AE12)>=9.99,IF(AN12>0,9.99,-9.99),AN12/ABS(AE12)),IF(AN12=0,0,AN12/ABS(AN12))))<=-200%,"(200%)",(IFERROR(IF(ABS(AN12/AE12)>=9.99,IF(AN12>0,9.99,-9.99),AN12/ABS(AE12)),IF(AN12=0,0,AN12/ABS(AN12))))) -> #REF!
B13: Personal | C13: -3.8888815 | D13: -3.6258446 | E13: -3.8910686 | F13: -3.8825815 | G13: -3.8703072 | H13: =VLOOKUP($B13,'[1]FCST MKT UNITED 26'!$B$4:$O$22,H$3,0) -> #REF! | I13: =VLOOKUP($B13,'[1]FCST MKT UNITED 26'!$B$4:$O$22,I$3,0) -> #REF! | J13: =VLOOKUP($B13,'[1]FCST MKT UNITED 26'!$B$4:$O$22,J$3,0) -> #REF! | K13: =VLOOKUP($B13,'[1]FCST MKT UNITED 26'!$B$4:$O$22,K$3,0) -> #REF! | L13: =VLOOKUP($B13,'[1]FCST MKT UNITED 26'!$B$4:$O$22,L$3,0) -> #REF! | M13: =VLOOKUP($B13,'[1]FCST MKT UNITED 26'!$B$4:$O$22,M$3,0) -> #REF! | N13: =VLOOKUP($B13,'[1]FCST MKT UNITED 26'!$B$4:$O$22,N$3,0) -> #REF! | O13: =+SUM(C13:N13) -> #REF! | P13: A partir de marzo, se considera el mismo monto de febrero | AE13: -39.818126 | AF13: =IF((+IFERROR((AE13/$AE$7),0))<=-200%,"-200%",(+IFERROR((AE13/$AE$7),0))) -> (8%) | AG13: =VLOOKUP(AK13,$B$27:$O$45,14,0) -> (49.6) | AH13: =IF((+IFERROR((AG13/$AG$7),0))<=-200%,"-200%",(+IFERROR((AG13/$AG$7),0))) -> (10%) | AI13: =VLOOKUP(AK13,$B$4:$O$22,14,0) -> #REF! | AJ13: =IF((+IFERROR((AI13/$AI$7),0))<=-200%,"-200%",(+IFERROR((AI13/$AI$7),0))) -> 0% | AK13: Personal | AL13: =+AI13-AG13 -> #REF! | AM13: =IF((IFERROR(IF(ABS(AL13/AG13)>=9.99,IF(AL13>0,9.99,-9.99),AL13/ABS(AG13)),IF(AL13=0,0,AL13/ABS(AL13))))<=-200%,"-200%",(IFERROR(IF(ABS(AL13/AG13)>=9.99,IF(AL13>0,9.99,-9.99),AL13/ABS(AG13)),IF(AL13=0,0,AL13/ABS(AL13))))) -> #REF! | AN13: =AI13-AE13 -> #REF! | AO13: =IF((IFERROR(IF(ABS(AN13/AE13)>=9.99,IF(AN13>0,9.99,-9.99),AN13/ABS(AE13)),IF(AN13=0,0,AN13/ABS(AN13))))<=-200%,"(200%)",(IFERROR(IF(ABS(AN13/AE13)>=9.99,IF(AN13>0,9.99,-9.99),AN13/ABS(AE13)),IF(AN13=0,0,AN13/ABS(AN13))))) -> #REF!
B14: Operación | C14: -0.52712119 | D14: -0.35311028 | E14: -0.09550295 | F14: -0.2450474 | G14: -0.24842095 | H14: =VLOOKUP($B14,'[1]FCST MKT UNITED 26'!$B$4:$O$22,H$3,0) -> #REF! | I14: =VLOOKUP($B14,'[1]FCST MKT UNITED 26'!$B$4:$O$22,I$3,0) -> #REF! | J14: =VLOOKUP($B14,'[1]FCST MKT UNITED 26'!$B$4:$O$22,J$3,0) -> #REF! | K14: =VLOOKUP($B14,'[1]FCST MKT UNITED 26'!$B$4:$O$22,K$3,0) -> #REF! | L14: =VLOOKUP($B14,'[1]FCST MKT UNITED 26'!$B$4:$O$22,L$3,0) -> #REF! | M14: =VLOOKUP($B14,'[1]FCST MKT UNITED 26'!$B$4:$O$22,M$3,0) -> #REF! | N14: =VLOOKUP($B14,'[1]FCST MKT UNITED 26'!$B$4:$O$22,N$3,0) -> #REF! | O14: =+SUM(C14:N14) -> #REF! | P14: Desde marzo queda igual que el plan en todos los meses | AE14: -4.5140742 | AF14: =IF((+IFERROR((AE14/$AE$7),0))<=-200%,"-200%",(+IFERROR((AE14/$AE$7),0))) -> (1%) | AG14: =VLOOKUP(AK14,$B$27:$O$45,14,0) -> (4.8) | AH14: =IF((+IFERROR((AG14/$AG$7),0))<=-200%,"-200%",(+IFERROR((AG14/$AG$7),0))) -> (1%) | AI14: =VLOOKUP(AK14,$B$4:$O$22,14,0) -> #REF! | AJ14: =IF((+IFERROR((AI14/$AI$7),0))<=-200%,"-200%",(+IFERROR((AI14/$AI$7),0))) -> 0% | AK14: Operación | AL14: =+AI14-AG14 -> #REF! | AM14: =IF((IFERROR(IF(ABS(AL14/AG14)>=9.99,IF(AL14>0,9.99,-9.99),AL14/ABS(AG14)),IF(AL14=0,0,AL14/ABS(AL14))))<=-200%,"-200%",(IFERROR(IF(ABS(AL14/AG14)>=9.99,IF(AL14>0,9.99,-9.99),AL14/ABS(AG14)),IF(AL14=0,0,AL14/ABS(AL14))))) -> #REF! | AN14: =AI14-AE14 -> #REF! | AO14: =IF((IFERROR(IF(ABS(AN14/AE14)>=9.99,IF(AN14>0,9.99,-9.99),AN14/ABS(AE14)),IF(AN14=0,0,AN14/ABS(AN14))))<=-200%,"(200%)",(IFERROR(IF(ABS(AN14/AE14)>=9.99,IF(AN14>0,9.99,-9.99),AN14/ABS(AE14)),IF(AN14=0,0,AN14/ABS(AN14))))) -> #REF!
B15: Mercadotecnia | C15: -0.07 | D15: -0.07403134 | E15: -0.08 | F15: -0.086 | G15: -0.08777841 | H15: =VLOOKUP($B15,'[1]FCST MKT UNITED 26'!$B$4:$O$22,H$3,0) -> #REF! | I15: =VLOOKUP($B15,'[1]FCST MKT UNITED 26'!$B$4:$O$22,I$3,0) -> #REF! | J15: =VLOOKUP($B15,'[1]FCST MKT UNITED 26'!$B$4:$O$22,J$3,0) -> #REF! | K15: =VLOOKUP($B15,'[1]FCST MKT UNITED 26'!$B$4:$O$22,K$3,0) -> #REF! | L15: =VLOOKUP($B15,'[1]FCST MKT UNITED 26'!$B$4:$O$22,L$3,0) -> #REF! | M15: =VLOOKUP($B15,'[1]FCST MKT UNITED 26'!$B$4:$O$22,M$3,0) -> #REF! | N15: =VLOOKUP($B15,'[1]FCST MKT UNITED 26'!$B$4:$O$22,N$3,0) -> #REF! | O15: =+SUM(C15:N15) -> #REF! | P15: Desde marzo queda igual que el plan en todos los meses | AE15: -2.1747093 | AF15: =IF((+IFERROR((AE15/$AE$7),0))<=-200%,"-200%",(+IFERROR((AE15/$AE$7),0))) -> (0%) | AG15: =VLOOKUP(AK15,$B$27:$O$45,14,0) -> (2.3) | AH15: =IF((+IFERROR((AG15/$AG$7),0))<=-200%,"-200%",(+IFERROR((AG15/$AG$7),0))) -> (0%) | AI15: =VLOOKUP(AK15,$B$4:$O$22,14,0) -> #REF! | AJ15: =IF((+IFERROR((AI15/$AI$7),0))<=-200%,"-200%",(+IFERROR((AI15/$AI$7),0))) -> 0% | AK15: Mercadotecnia | AL15: =+AI15-AG15 -> #REF! | AM15: =IF((IFERROR(IF(ABS(AL15/AG15)>=9.99,IF(AL15>0,9.99,-9.99),AL15/ABS(AG15)),IF(AL15=0,0,AL15/ABS(AL15))))<=-200%,"-200%",(IFERROR(IF(ABS(AL15/AG15)>=9.99,IF(AL15>0,9.99,-9.99),AL15/ABS(AG15)),IF(AL15=0,0,AL15/ABS(AL15))))) -> #REF! | AN15: =AI15-AE15 -> #REF! | AO15: =IF((IFERROR(IF(ABS(AN15/AE15)>=9.99,IF(AN15>0,9.99,-9.99),AN15/ABS(AE15)),IF(AN15=0,0,AN15/ABS(AN15))))<=-200%,"(200%)",(IFERROR(IF(ABS(AN15/AE15)>=9.99,IF(AN15>0,9.99,-9.99),AN15/ABS(AE15)),IF(AN15=0,0,AN15/ABS(AN15))))) -> #REF!
B16: Renta, Luz y Teléfono | C16: -0.39482286 | D16: -0.41314635 | E16: -0.42126174 | F16: -0.41080176 | G16: -0.4137786 | H16: =VLOOKUP($B16,'[1]FCST MKT UNITED 26'!$B$4:$O$22,H$3,0) -> #REF! | I16: =VLOOKUP($B16,'[1]FCST MKT UNITED 26'!$B$4:$O$22,I$3,0) -> #REF! | J16: =VLOOKUP($B16,'[1]FCST MKT UNITED 26'!$B$4:$O$22,J$3,0) -> #REF! | K16: =VLOOKUP($B16,'[1]FCST MKT UNITED 26'!$B$4:$O$22,K$3,0) -> #REF! | L16: =VLOOKUP($B16,'[1]FCST MKT UNITED 26'!$B$4:$O$22,L$3,0) -> #REF! | M16: =VLOOKUP($B16,'[1]FCST MKT UNITED 26'!$B$4:$O$22,M$3,0) -> #REF! | N16: =VLOOKUP($B16,'[1]FCST MKT UNITED 26'!$B$4:$O$22,N$3,0) -> #REF! | O16: =+SUM(C16:N16) -> #REF! | P16: A partir de marzo, se considera el mismo monto de febrero | AE16: -3.6057829 | AF16: =IF((+IFERROR((AE16/$AE$7),0))<=-200%,"-200%",(+IFERROR((AE16/$AE$7),0))) -> (1%) | AG16: =VLOOKUP(AK16,$B$27:$O$45,14,0) -> (4.4) | AH16: =IF((+IFERROR((AG16/$AG$7),0))<=-200%,"-200%",(+IFERROR((AG16/$AG$7),0))) -> (1%) | AI16: =VLOOKUP(AK16,$B$4:$O$22,14,0) -> #REF! | AJ16: =IF((+IFERROR((AI16/$AI$7),0))<=-200%,"-200%",(+IFERROR((AI16/$AI$7),0))) -> 0% | AK16: Renta, Luz y Teléfono | AL16: =+AI16-AG16 -> #REF! | AM16: =IF((IFERROR(IF(ABS(AL16/AG16)>=9.99,IF(AL16>0,9.99,-9.99),AL16/ABS(AG16)),IF(AL16=0,0,AL16/ABS(AL16))))<=-200%,"(200%)",(IFERROR(IF(ABS(AL16/AG16)>=9.99,IF(AL16>0,9.99,-9.99),AL16/ABS(AG16)),IF(AL16=0,0,AL16/ABS(AL16)))))*1 -> #REF! | AN16: =AI16-AE16 -> #REF! | AO16: =IF((IFERROR(IF(ABS(AN16/AE16)>=9.99,IF(AN16>0,9.99,-9.99),AN16/ABS(AE16)),IF(AN16=0,0,AN16/ABS(AN16))))<=-200%,"(200%)",(IFERROR(IF(ABS(AN16/AE16)>=9.99,IF(AN16>0,9.99,-9.99),AN16/ABS(AE16)),IF(AN16=0,0,AN16/ABS(AN16)))))*1 -> #REF!
B17: Gastos de despacho GS | C17: -0.28884766 | D17: -0.2803609 | E17: -0.27368624 | F17: -0.28761457 | G17: -0.29114064 | H17: =VLOOKUP($B17,'[1]FCST MKT UNITED 26'!$B$4:$O$22,H$3,0) -> #REF! | I17: =VLOOKUP($B17,'[1]FCST MKT UNITED 26'!$B$4:$O$22,I$3,0) -> #REF! | J17: =VLOOKUP($B17,'[1]FCST MKT UNITED 26'!$B$4:$O$22,J$3,0) -> #REF! | K17: =VLOOKUP($B17,'[1]FCST MKT UNITED 26'!$B$4:$O$22,K$3,0) -> #REF! | L17: =VLOOKUP($B17,'[1]FCST MKT UNITED 26'!$B$4:$O$22,L$3,0) -> #REF! | M17: =VLOOKUP($B17,'[1]FCST MKT UNITED 26'!$B$4:$O$22,M$3,0) -> #REF! | N17: =VLOOKUP($B17,'[1]FCST MKT UNITED 26'!$B$4:$O$22,N$3,0) -> #REF! | O17: =+SUM(C17:N17) -> #REF! | P17: A partir de marzo, se considera el mismo monto de febrero | AE17: -2.7181252 | AF17: =IF((+IFERROR((AE17/$AE$7),0))<=-200%,"-200%",(+IFERROR((AE17/$AE$7),0))) -> (1%) | AG17: =VLOOKUP(AK17,$B$27:$O$45,14,0) -> (2.6) | AH17: =IF((+IFERROR((AG17/$AG$7),0))<=-200%,"-200%",(+IFERROR((AG17/$AG$7),0))) -> (1%) | AI17: =VLOOKUP(AK17,$B$4:$O$22,14,0) -> #REF! | AJ17: =IF((+IFERROR((AI17/$AI$7),0))<=-200%,"-200%",(+IFERROR((AI17/$AI$7),0))) -> 0% | AK17: Gastos de despacho GS | AL17: =+AI17-AG17 -> #REF! | AM17: =IF((IFERROR(IF(ABS(AL17/AG17)>=9.99,IF(AL17>0,9.99,-9.99),AL17/ABS(AG17)),IF(AL17=0,0,AL17/ABS(AL17))))<=-200%,"-200%",(IFERROR(IF(ABS(AL17/AG17)>=9.99,IF(AL17>0,9.99,-9.99),AL17/ABS(AG17)),IF(AL17=0,0,AL17/ABS(AL17))))) -> #REF! | AN17: =AI17-AE17 -> #REF! | AO17: =IF((IFERROR(IF(ABS(AN17/AE17)>=9.99,IF(AN17>0,9.99,-9.99),AN17/ABS(AE17)),IF(AN17=0,0,AN17/ABS(AN17))))<=-200%,"(200%)",(IFERROR(IF(ABS(AN17/AE17)>=9.99,IF(AN17>0,9.99,-9.99),AN17/ABS(AE17)),IF(AN17=0,0,AN17/ABS(AN17))))) -> #REF!
B18: Costo de Activo | C18: -0.0001658 | D18: -0.0001688 | E18: -0.0001688 | F18: -0.0001688 | G18: -0.0001687 | H18: =VLOOKUP($B18,'[1]FCST MKT UNITED 26'!$B$4:$O$22,H$3,0) -> #REF! | I18: =VLOOKUP($B18,'[1]FCST MKT UNITED 26'!$B$4:$O$22,I$3,0) -> #REF! | J18: =VLOOKUP($B18,'[1]FCST MKT UNITED 26'!$B$4:$O$22,J$3,0) -> #REF! | K18: =VLOOKUP($B18,'[1]FCST MKT UNITED 26'!$B$4:$O$22,K$3,0) -> #REF! | L18: =VLOOKUP($B18,'[1]FCST MKT UNITED 26'!$B$4:$O$22,L$3,0) -> #REF! | M18: =VLOOKUP($B18,'[1]FCST MKT UNITED 26'!$B$4:$O$22,M$3,0) -> #REF! | N18: =VLOOKUP($B18,'[1]FCST MKT UNITED 26'!$B$4:$O$22,N$3,0) -> #REF! | O18: =+SUM(C18:N18) -> #REF! | P18: A partir de marzo, se considera el mismo monto de febrero | AE18: -0.003878325 | AF18: =IF((+IFERROR((AE18/$AE$7),0))<=-200%,"-200%",(+IFERROR((AE18/$AE$7),0))) -> (0%) | AG18: =VLOOKUP(AK18,$B$27:$O$45,14,0) -> (0.1) | AH18: =IF((+IFERROR((AG18/$AG$7),0))<=-200%,"-200%",(+IFERROR((AG18/$AG$7),0))) -> (0%) | AI18: =VLOOKUP(AK18,$B$4:$O$22,14,0) -> #REF! | AJ18: =IF((+IFERROR((AI18/$AI$7),0))<=-200%,"-200%",(+IFERROR((AI18/$AI$7),0))) -> 0% | AK18: Costo de Activo | AL18: =+AI18-AG18 -> #REF! | AM18: =IF((IFERROR(IF(ABS(AL18/AG18)>=9.99,IF(AL18>0,9.99,-9.99),AL18/ABS(AG18)),IF(AL18=0,0,AL18/ABS(AL18))))<=-200%,"-200%",(IFERROR(IF(ABS(AL18/AG18)>=9.99,IF(AL18>0,9.99,-9.99),AL18/ABS(AG18)),IF(AL18=0,0,AL18/ABS(AL18))))) -> #REF! | AN18: =AI18-AE18 -> #REF! | AO18: =IF((IFERROR(IF(ABS(AN18/AE18)>=9.99,IF(AN18>0,9.99,-9.99),AN18/ABS(AE18)),IF(AN18=0,0,AN18/ABS(AN18))))<=-200%,"(200%)",(IFERROR(IF(ABS(AN18/AE18)>=9.99,IF(AN18>0,9.99,-9.99),AN18/ABS(AE18)),IF(AN18=0,0,AN18/ABS(AN18))))) -> #REF!
B19: Gastos Ventas | C19: -0.5250295 | D19: -0.4645698 | E19: -0.3902149 | F19: -0.46456918 | G19: -0.41851421 | H19: =VLOOKUP($B19,'[1]FCST MKT UNITED 26'!$B$4:$O$22,H$3,0) -> #REF! | I19: =VLOOKUP($B19,'[1]FCST MKT UNITED 26'!$B$4:$O$22,I$3,0) -> #REF! | J19: =VLOOKUP($B19,'[1]FCST MKT UNITED 26'!$B$4:$O$22,J$3,0) -> #REF! | K19: =VLOOKUP($B19,'[1]FCST MKT UNITED 26'!$B$4:$O$22,K$3,0) -> #REF! | L19: =VLOOKUP($B19,'[1]FCST MKT UNITED 26'!$B$4:$O$22,L$3,0) -> #REF! | M19: =VLOOKUP($B19,'[1]FCST MKT UNITED 26'!$B$4:$O$22,M$3,0) -> #REF! | N19: =VLOOKUP($B19,'[1]FCST MKT UNITED 26'!$B$4:$O$22,N$3,0) -> #REF! | O19: =+SUM(C19:N19) -> #REF! | P19: A partir de marzo, se considera el mismo monto de febrero | AE19: -6.0321943 | AF19: =IF((+IFERROR((AE19/$AE$7),0))<=-200%,"-200%",(+IFERROR((AE19/$AE$7),0))) -> (1%) | AG19: =VLOOKUP(AK19,$B$27:$O$45,14,0) -> (6.1) | AH19: =IF((+IFERROR((AG19/$AG$7),0))<=-200%,"-200%",(+IFERROR((AG19/$AG$7),0))) -> (1%) | AI19: =VLOOKUP(AK19,$B$4:$O$22,14,0) -> #REF! | AJ19: =IF((+IFERROR((AI19/$AI$7),0))<=-200%,"-200%",(+IFERROR((AI19/$AI$7),0))) -> 0% | AK19: Gastos Ventas | AL19: =+AI19-AG19 -> #REF! | AM19: =IF((IFERROR(IF(ABS(AL19/AG19)>=9.99,IF(AL19>0,9.99,-9.99),AL19/ABS(AG19)),IF(AL19=0,0,AL19/ABS(AL19))))<=-200%,"-200%",(IFERROR(IF(ABS(AL19/AG19)>=9.99,IF(AL19>0,9.99,-9.99),AL19/ABS(AG19)),IF(AL19=0,0,AL19/ABS(AL19))))) -> #REF! | AN19: =AI19-AE19 -> #REF! | AO19: =IF((IFERROR(IF(ABS(AN19/AE19)>=9.99,IF(AN19>0,9.99,-9.99),AN19/ABS(AE19)),IF(AN19=0,0,AN19/ABS(AN19))))<=-200%,"(200%)",(IFERROR(IF(ABS(AN19/AE19)>=9.99,IF(AN19>0,9.99,-9.99),AN19/ABS(AE19)),IF(AN19=0,0,AN19/ABS(AN19))))) -> #REF!
B20: Gastos Staff | C20: -1.3179256 | D20: -1.4688517 | E20: -1.3427575 | F20: -1.287813 | G20: -1.3905488 | H20: =VLOOKUP($B20,'[1]FCST MKT UNITED 26'!$B$4:$O$22,H$3,0) -> #REF! | I20: =VLOOKUP($B20,'[1]FCST MKT UNITED 26'!$B$4:$O$22,I$3,0) -> #REF! | J20: =VLOOKUP($B20,'[1]FCST MKT UNITED 26'!$B$4:$O$22,J$3,0) -> #REF! | K20: =VLOOKUP($B20,'[1]FCST MKT UNITED 26'!$B$4:$O$22,K$3,0) -> #REF! | L20: =VLOOKUP($B20,'[1]FCST MKT UNITED 26'!$B$4:$O$22,L$3,0) -> #REF! | M20: =VLOOKUP($B20,'[1]FCST MKT UNITED 26'!$B$4:$O$22,M$3,0) -> #REF! | N20: =VLOOKUP($B20,'[1]FCST MKT UNITED 26'!$B$4:$O$22,N$3,0) -> #REF! | O20: =+SUM(C20:N20) -> #REF! | P20: Desde marzo queda igual que el plan en todos los meses | AE20: -17.246628 | AF20: =IF((+IFERROR((AE20/$AE$7),0))<=-200%,"-200%",(+IFERROR((AE20/$AE$7),0))) -> (4%) | AG20: =VLOOKUP(AK20,$B$27:$O$45,14,0) -> (17.8) | AH20: =IF((+IFERROR((AG20/$AG$7),0))<=-200%,"-200%",(+IFERROR((AG20/$AG$7),0))) -> (4%) | AI20: =VLOOKUP(AK20,$B$4:$O$22,14,0) -> #REF! | AJ20: =IF((+IFERROR((AI20/$AI$7),0))<=-200%,"-200%",(+IFERROR((AI20/$AI$7),0))) -> 0% | AK20: Gastos Staff | AL20: =+AI20-AG20 -> #REF! | AM20: =IF((IFERROR(IF(ABS(AL20/AG20)>=9.99,IF(AL20>0,9.99,-9.99),AL20/ABS(AG20)),IF(AL20=0,0,AL20/ABS(AL20))))<=-200%,"-200%",(IFERROR(IF(ABS(AL20/AG20)>=9.99,IF(AL20>0,9.99,-9.99),AL20/ABS(AG20)),IF(AL20=0,0,AL20/ABS(AL20))))) -> #REF! | AN20: =AI20-AE20 -> #REF! | AO20: =IF((IFERROR(IF(ABS(AN20/AE20)>=9.99,IF(AN20>0,9.99,-9.99),AN20/ABS(AE20)),IF(AN20=0,0,AN20/ABS(AN20))))<=-200%,"(200%)",(IFERROR(IF(ABS(AN20/AE20)>=9.99,IF(AN20>0,9.99,-9.99),AN20/ABS(AE20)),IF(AN20=0,0,AN20/ABS(AN20))))) -> #REF!
B21: Total Gastos | C21: =+SUM(C13:C20) -> (7.0) | D21: =+SUM(D13:D20) -> (6.7) | E21: =+SUM(E13:E20) -> (6.5) | F21: =+SUM(F13:F20) -> (6.7) | G21: =+SUM(G13:G20) -> (6.7) | H21: =+SUM(H13:H20) -> #REF! | I21: =+SUM(I13:I20) -> #REF! | J21: =+SUM(J13:J20) -> #REF! | ... O21: =+SUM(O13:O20) -> #REF! | AE21: =+SUM(AE13:AE20) -> (76.1) | AF21: =IF((+IFERROR((AE21/$AE$7),0))<=-200%,"-200%",(+IFERROR((AE21/$AE$7),0))) -> (16%) | AG21: =+SUM(AG13:AG20) -> (87.8) | AH21: =IF((+IFERROR((AG21/$AG$7),0))<=-200%,"-200%",(+IFERROR((AG21/$AG$7),0))) -> (18%) | AI21: =+SUM(AI13:AI20) -> #REF! | AJ21: =IF((+IFERROR((AI21/$AI$7),0))<=-200%,"-200%",(+IFERROR((AI21/$AI$7),0))) -> 0% | AK21: Total Gastos | AL21: =+AI21-AG21 -> #REF! | AM21: =IF((IFERROR(IF(ABS(AL21/AG21)>=9.99,IF(AL21>0,9.99,-9.99),AL21/ABS(AG21)),IF(AL21=0,0,AL21/ABS(AL21))))<=-200%,"-200%",(IFERROR(IF(ABS(AL21/AG21)>=9.99,IF(AL21>0,9.99,-9.99),AL21/ABS(AG21)),IF(AL21=0,0,AL21/ABS(AL21))))) -> #REF! | AN21: =AI21-AE21 -> #REF! | AO21: =IF((IFERROR(IF(ABS(AN21/AE21)>=9.99,IF(AN21>0,9.99,-9.99),AN21/ABS(AE21)),IF(AN21=0,0,AN21/ABS(AN21))))<=-200%,"(200%)",(IFERROR(IF(ABS(AN21/AE21)>=9.99,IF(AN21>0,9.99,-9.99),AN21/ABS(AE21)),IF(AN21=0,0,AN21/ABS(AN21))))) -> #REF!
B22: Contribución Neta $ | C22: =C12+C21 -> (1.4) | D22: =D12+D21 -> 6.2 | E22: =E12+E21 -> 2.6 | F22: =F12+F21 -> 8.8 | G22: =G12+G21 -> 11.0 | H22: =H12+H21 -> #REF! | I22: =I12+I21 -> #REF! | J22: =J12+J21 -> #REF! | ... O22: =O12+O21 -> #REF! | AE22: =+AE21+AE12 -> 70.0 | AF22: =IF((+IFERROR((AE22/$AE$7),0))<=-200%,"-200%",(+IFERROR((AE22/$AE$7),0))) -> 15% | AG22: =AG12+AG21 -> 107.2 | AH22: =IF((+IFERROR((AG22/$AG$7),0))<=-200%,"-200%",(+IFERROR((AG22/$AG$7),0))) -> 21% | AI22: =AI12+AI21 -> #REF! | AJ22: =IF((+IFERROR((AI22/$AI$7),0))<=-200%,"-200%",(+IFERROR((AI22/$AI$7),0))) -> 0% | AK22: Contribución Neta | AL22: =+AI22-AG22 -> #REF! | AM22: =IF((IFERROR(IF(ABS(AL22/AG22)>=9.99,IF(AL22>0,9.99,-9.99),AL22/ABS(AG22)),IF(AL22=0,0,AL22/ABS(AL22))))<=-200%,"-200%",(IFERROR(IF(ABS(AL22/AG22)>=9.99,IF(AL22>0,9.99,-9.99),AL22/ABS(AG22)),IF(AL22=0,0,AL22/ABS(AL22))))) -> #REF! | AN22: =AI22-AE22 -> #REF! | AO22: =IF((IFERROR(IF(ABS(AN22/AE22)>=9.99,IF(AN22>0,9.99,-9.99),AN22/ABS(AE22)),IF(AN22=0,0,AN22/ABS(AN22))))<=-200%,"(200%)",(IFERROR(IF(ABS(AN22/AE22)>=9.99,IF(AN22>0,9.99,-9.99),AN22/ABS(AE22)),IF(AN22=0,0,AN22/ABS(AN22))))) -> #REF!
B24: % Margen | C24: =C22/C7 -> (8%) | D24: =D22/D7 -> 19% | E24: =E22/E7 -> 10% | F24: =F22/F7 -> 22% | G24: =G22/G7 -> 26% | H24: =H22/H7 -> #REF! | I24: =I22/I7 -> #REF! | J24: =J22/J7 -> #REF! | ... O24: =O22/O7 -> #REF!
B27: Presupuesto 2026 | C27: 46023 | D27: 46054 | E27: 46082 | F27: 46113 | G27: 46143 | H27: 46174 | I27: 46204 | J27: 46235 | K27: 46266 | L27: 46296 | M27: 46327 | N27: 46357 | O27: Total
B28: Ingresos Internos | C28: 24.12836 | D28: 23.935514 | E28: 21.375945 | F28: 27.733583 | G28: 38.235001 | H28: 33.598168 | I28: 28.651672 | J28: 42.118013 | K28: 41.65958 | L28: 40.017488 | M28: 41.815298 | N28: 73.255224 | O28: =+SUM(C28:N28) -> 436.5 | R28: % | S28: 46023 | T28: 46054 | U28: 46082 | V28: 46113 | W28: 46143 | X28: 46174 | Y28: 46204 | Z28: 46235 | AA28: 46266 | AB28: 46296 | AC28: 46327 | AD28: 46357
B29: Ingresos Externos | C29: 1.0035979 | D29: 1.58533 | E29: 2.3324669 | F29: 2.7162186 | G29: 3.4036958 | H29: 2.6425153 | I29: 3.0059344 | J29: 4.1537398 | K29: 6.8141253 | L29: 10.714125 | M29: 13.314125 | N29: 13.314125 | O29: =+SUM(C29:N29) -> 65.0 | R29: Ingresos Internos | S29: =C5/C28 -> 51% | T29: =D5/D28 -> 122% | U29: =E5/E28 -> 113% | V29: =F5/F28 -> 136% | W29: =G5/G28 -> 104% | X29: =H5/H28 -> #REF! | Y29: =I5/I28 -> #REF! | Z29: =J5/J28 -> #REF! | ... AD29: =N5/N28 -> #REF!
B30: Total Ingresos | C30: =C28+C29 -> 25.1 | D30: =D28+D29 -> 25.5 | E30: =E29+E28 -> 23.7 | F30: =F29+F28 -> 30.4 | G30: =G29+G28 -> 41.6 | H30: =H29+H28 -> 36.2 | I30: =I29+I28 -> 31.7 | J30: =J29+J28 -> 46.3 | K30: =K29+K28 -> 48.5 | L30: =L29+L28 -> 50.7 | ... O30: =O29+O28 -> 501.5 | R30: Ingresos Externos | S30: =C6/C29 -> 467% | T30: =D6/D29 -> 192% | U30: =E6/E29 -> 28% | V30: 0.55 | W30: 0.55 | X30: 0.55 | Y30: 0.55 | Z30: 0.55 | AA30: 0.55 | AB30: 0.55 | AC30: 0.55 | AD30: 0.55
B31: Activaciones | C31: -15.079175 | D31: -15.312506 | E31: -14.225047 | F31: -18.269881 | G31: -24.983218 | H31: -21.74441 | I31: -18.994564 | J31: -27.763051 | K31: -29.084223 | L31: -30.438968 | M31: -33.077654 | N31: -51.941609 | O31: =+SUM(C31:N31) -> (300.9)
B32: Comisiones | C32: -0.051592962 | D32: -0.081498644 | E32: -0.11990746 | F32: -0.13963536 | G32: -0.17497719 | H32: -0.13584643 | I32: -0.15452907 | J32: -0.21353546 | K32: -0.35030056 | L32: -0.55079176 | M32: -0.68445256 | N32: -0.68445256 | O32: =+SUM(C32:N32) -> (3.3) | R32: Activaciones | U32: =E31/E30-6% -> -66.0% | V32: =U32 -> -66.0% | W32: =V32 -> -66.0% | X32: =W32 -> -66.0% | Y32: =X32 -> -66.0% | Z32: =Y32 -> -66.0% | AA32: =Z32 -> -66.0% | AB32: =AA32 -> -66.0% | AC32: =AB32 -> -66.0% | AD32: =AC32 -> -66.0%
B33: Participación Socios | C33: -0.035326647 | D33: -0.055803615 | E33: -0.082102834 | F33: -0.095610894 | G33: -0.11981009 | H33: -0.093016538 | I33: -0.10580889 | J33: -0.14621164 | K33: -0.23985721 | L33: -0.37713721 | M33: -0.46865721 | N33: -0.46865721 | O33: =+SUM(C33:N33) -> (2.3) | R33: Comisiones | S33: =C9/C32 -> 82% | T33: =D9/D32 -> 28% | U33: =AVERAGE(S33:T33) -> 55% | V33: =U33 -> 55% | W33: =V33 -> 55% | X33: =W33 -> 55% | Y33: =X33 -> 55% | Z33: =Y33 -> 55% | AA33: =Z33 -> 55% | AB33: =AA33 -> 55% | AC33: =AB33 -> 55% | AD33: =AC33 -> 55%
B34: Costos Totales | C34: =SUM(C31:C33) -> (15.2) | D34: =SUM(D31:D33) -> (15.4) | E34: =SUM(E31:E33) -> (14.4) | F34: =SUM(F31:F33) -> (18.5) | G34: =SUM(G31:G33) -> (25.3) | H34: =SUM(H31:H33) -> (22.0) | I34: =SUM(I31:I33) -> (19.3) | J34: =SUM(J31:J33) -> (28.1) | ... O34: =SUM(O31:O33) -> (306.5) | R34: Participación Socios
B35: Contribución Bruta | C35: =C30+C34 -> 10.0 | D35: =D30+D34 -> 10.1 | E35: =E30+E34 -> 9.3 | F35: =F30+F34 -> 11.9 | G35: =G30+G34 -> 16.4 | H35: =H30+H34 -> 14.3 | I35: =I30+I34 -> 12.4 | J35: =J30+J34 -> 18.1 | ... O35: =O30+O34 -> 195.0 | R35: Costos Totales
B36: Personal | C36: -4.1316957 | D36: -4.1316957 | E36: -4.1316957 | F36: -4.1316957 | G36: -4.1316957 | H36: -4.1316957 | I36: -4.1316957 | J36: -4.1316957 | K36: -4.1316957 | L36: -4.1316957 | M36: -4.1316957 | N36: -4.1316957 | O36: =+SUM(C36:N36) -> (49.6)
B37: Operación | C37: -0.667 | D37: -1.067 | E37: -0.167 | F37: -0.417 | G37: -0.424 | H37: -0.41763621 | I37: -0.267 | J37: -0.317 | K37: -0.267 | L37: -0.267 | M37: -0.274 | N37: -0.267 | O37: =+SUM(C37:N37) -> (4.8) | R37: Personal
B38: Mercadotecnia | C38: -0.151769 | D38: -0.18338 | E38: -0.59204677 | F38: -0.24869 | G38: -0.13869 | H38: -0.13869 | I38: -0.13869 | J38: -0.13869 | K38: -0.13869 | L38: -0.17369 | M38: -0.13869 | N38: -0.13869 | O38: =+SUM(C38:N38) -> (2.3) | R38: Operación
B39: Renta, Luz y Teléfono | C39: -0.3868168 | D39: -0.36747596 | E39: -0.36747596 | F39: -0.36747596 | G39: -0.36747596 | H39: -0.36747596 | I39: -0.36747596 | J39: -0.36747596 | K39: -0.36747596 | L39: -0.36747596 | M39: -0.36747596 | N39: -0.36747596 | O39: =+SUM(C39:N39) -> (4.4) | R39: Mercadotecnia
B40: Gastos de despacho GS | C40: -0.27331933 | D40: -0.234205 | E40: -0.20044467 | F40: -0.21160668 | G40: -0.20801397 | H40: -0.21403749 | I40: -0.21214275 | J40: -0.21182125 | K40: -0.20824344 | L40: -0.22866781 | M40: -0.20767621 | N40: -0.20767621 | O40: =+SUM(C40:N40) -> (2.6) | R40: Renta, Luz y Teléfono
B41: Costo de Activo | C41: -0.00016344563 | D41: -0.00016344563 | E41: -0.00016485 | F41: -0.0001638 | G41: -0.0001533 | H41: -0.00016065 | I41: -0.00067935 | J41: -0.00067935 | K41: -0.0021002625 | L41: -0.029884233 | M41: -0.029884233 | N41: -0.029884233 | O41: =+SUM(C41:N41) -> (0.1) | R41: Gastos de despacho GS
B42: Gastos Ventas | C42: -0.51010665 | D42: -0.51010665 | E42: -0.51010665 | F42: -0.51010665 | G42: -0.51010665 | H42: -0.51010665 | I42: -0.51010665 | J42: -0.51010665 | K42: -0.51010665 | L42: -0.51010665 | M42: -0.51010665 | N42: -0.51010665 | O42: =+SUM(C42:N42) -> (6.1) | R42: Costo de Activo
B43: Gastos Staff | C43: -1.3522168 | D43: -1.4532884 | E43: -1.4944164 | F43: -1.4322186 | G43: -1.440031 | H43: -1.4367408 | I43: -1.476321 | J43: -1.4611031 | K43: -1.55573 | L43: -1.527619 | M43: -1.6039685 | N43: -1.6038162 | O43: =+SUM(C43:N43) -> (17.8) | R43: Gastos Ventas | S43: =C19/C42 -> 103% | T43: =D19/D42 -> 91%
B44: Total Gastos | C44: =+SUM(C36:C43) -> (7.5) | D44: =+SUM(D36:D43) -> (7.9) | E44: =+SUM(E36:E43) -> (7.5) | F44: =+SUM(F36:F43) -> (7.3) | G44: =+SUM(G36:G43) -> (7.2) | H44: =+SUM(H36:H43) -> (7.2) | I44: =+SUM(I36:I43) -> (7.1) | J44: =+SUM(J36:J43) -> (7.1) | ... O44: =+SUM(O36:O43) -> (87.8) | R44: Gastos Staff
B45: Contribución Neta $ | C45: =C35+C44 -> 2.5 | D45: =D35+D44 -> 2.1 | E45: =E35+E44 -> 1.8 | F45: =F35+F44 -> 4.6 | G45: =G35+G44 -> 9.1 | H45: =H35+H44 -> 7.1 | I45: =I35+I44 -> 5.3 | J45: =J35+J44 -> 11.0 | ... O45: =O35+O44 -> 107.2
B47: % Margen | C47: =C45/C30 -> 10% | D47: =D45/D30 -> 8% | E47: =E45/E30 -> 8% | F47: =F45/F30 -> 15% | G47: =G45/G30 -> 22% | H47: =H45/H30 -> 19% | I47: =I45/I30 -> 17% | J47: =J45/J30 -> 24% | ... O47: =O45/O30 -> 21%
B51: Real 2025 | C51: 45658 | D51: 45689 | E51: 45717 | F51: 45748 | G51: 45778 | H51: 45809 | I51: 45839 | J51: 45870 | K51: 45901 | L51: 45931 | M51: 45962 | N51: 45992 | O51: Total
B52: Ingresos Internos | C52: 22.643869 | D52: 28.208033 | E52: 29.083078 | F52: 28.452118 | G52: 28.814173 | H52: 31.90132 | I52: 24.978855 | J52: 38.062659 | K52: 42.616382 | L52: 45.365613 | M52: 77.95618 | N52: 66.245772 | O52: =+SUM(C52:N52) -> 464.3
B53: Ingresos Externos | C53: 0.4249346 | D53: 0.272071 | E53: 3.2036794 | F53: 2.4794217 | G53: 2.531593 | H53: 1.585664 | I53: 1.6333018 | J53: 1.1760014 | K53: 0.662047 | L53: 0.580231 | M53: 1.5443169 | N53: 2.246545 | O53: =+SUM(C53:N53) -> 18.3
B54: Total Ingresos | C54: =C52+C53 -> 23.1 | D54: =D52+D53 -> 28.5 | E54: =E53+E52 -> 32.3 | F54: =F53+F52 -> 30.9 | G54: =G53+G52 -> 31.3 | H54: =H53+H52 -> 33.5 | I54: =I53+I52 -> 26.6 | J54: =J53+J52 -> 39.2 | K54: =K53+K52 -> 43.3 | L54: =L53+L52 -> 45.9 | ... O54: =O53+O52 -> 482.7
B55: Activaciones | C55: -15.623309 | D55: -19.2677 | E55: -20.981773 | F55: -18.517456 | G55: -21.491496 | H55: -20.066272 | I55: -17.437937 | J55: -24.291808 | K55: -27.329529 | L55: -29.569436 | M55: -48.587899 | N55: -72.900352 | O55: =+SUM(C55:N55) -> (336.1)
B56: Comisiones | C56: 0 | D56: 0 | E56: -0.108584 | F56: -0.03939952 | G56: -0.01 | H56: -0.01 | I56: -0.00999999 | J56: -0.001 | K56: -0.17125075 | L56: -0.02015062 | M56: -0.02483109 | N56: -0.0503862 | O56: =+SUM(C56:N56) -> (0.4)
B57: Costos Totales | C57: =SUM(C55:C56) -> (15.6) | D57: =SUM(D55:D56) -> (19.3) | E57: =SUM(E55:E56) -> (21.1) | F57: =SUM(F55:F56) -> (18.6) | G57: =SUM(G55:G56) -> (21.5) | H57: =SUM(H55:H56) -> (20.1) | I57: =SUM(I55:I56) -> (17.4) | J57: =SUM(J55:J56) -> (24.3) | ... O57: =SUM(O55:O56) -> (336.5)
B58: Contribución Bruta | C58: =C54+C57 -> 7.4 | D58: =D54+D57 -> 9.2 | E58: =E54+E57 -> 11.2 | F58: =F54+F57 -> 12.4 | G58: =G54+G57 -> 9.8 | H58: =H54+H57 -> 13.4 | I58: =I54+I57 -> 9.2 | J58: =J54+J57 -> 14.9 | ... O58: =O54+O57 -> 146.2
B59: Personal | C59: -2.9179817 | D59: -3.0693088 | E59: -3.0654749 | F59: -3.1979989 | G59: -3.065671 | H59: -3.247113 | I59: -3.1307781 | J59: -3.2574269 | K59: -3.5140876 | L59: -3.3482371 | M59: -3.8723525 | N59: -4.1316957 | O59: =+SUM(C59:N59) -> (39.8)
B60: Operación | C60: -0.05238614 | D60: -0.611535 | E60: -0.56056 | F60: -0.32415381 | G60: -0.70048418 | H60: -0.43238965 | I60: -0.00504263 | J60: -0.26336602 | K60: -0.39803395 | L60: -0.24991186 | M60: -0.36565492 | N60: -0.550556 | O60: =+SUM(C60:N60) -> (4.5)
B61: Mercadotecnia | C61: -0.176593 | D61: -0.347 | E61: -0.32491937 | F61: -0.28726233 | G61: -0.12399314 | H61: -0.066 | I61: -0.07 | J61: -0.241672 | K61: -0.22256736 | L61: -0.08156736 | M61: -0.07 | N61: -0.16313472 | O61: =+SUM(C61:N61) -> (2.2)
B62: Renta, Luz y Teléfono | C62: -0.32817754 | D62: -0.33778506 | E62: -0.2717744 | F62: -0.26889551 | G62: -0.2879567 | H62: -0.271482 | I62: -0.260071 | J62: -0.31683111 | K62: -0.31528931 | L62: -0.31651476 | M62: -0.314982 | N62: -0.31602355 | O62: =+SUM(C62:N62) -> (3.6)
B63: Gastos de despacho GS | C63: -0.112415 | D63: -0.19004148 | E63: -0.265314 | F63: -0.2131 | G63: -0.220684 | H63: -0.217887 | I63: -0.299068 | J63: -0.241672 | K63: -0.22960848 | L63: -0.22686802 | M63: -0.27129468 | N63: -0.2301725 | O63: =+SUM(C63:N63) -> (2.7)
B64: Costo de Activo | C64: -0.0001556625 | D64: -0.0001556625 | E64: -0.000157 | F64: -0.000156 | G64: -0.000146 | H64: -0.000553 | I64: -0.000648 | J64: -0.000647 | K64: -0.00068 | L64: -0.00018 | M64: -0.0002 | N64: -0.0002 | O64: =+SUM(C64:N64) -> (0.0)
B65: Gastos Ventas | C65: -0.43258951 | D65: -0.3879871 | E65: -0.38034272 | F65: -0.358139 | G65: -0.44243435 | H65: -0.496775 | I65: -0.53370306 | J65: -0.50577813 | K65: -0.5597212 | L65: -0.459092 | M65: -0.51010665 | N65: -0.96552554 | O65: =+SUM(C65:N65) -> (6.0)
B66: Gastos Staff | C66: -1.188505 | D66: -1.1842202 | E66: -1.2767439 | F66: -1.395286 | G66: -1.5148678 | H66: -1.613472 | I66: -1.4512437 | J66: -1.4439356 | K66: -1.3697778 | L66: -1.6029217 | M66: -1.461873 | N66: -1.7437807 | O66: =+SUM(C66:N66) -> (17.2)
B67: Total Gastos | C67: =+SUM(C59:C66) -> (5.2) | D67: =+SUM(D59:D66) -> (6.1) | E67: =+SUM(E59:E66) -> (6.1) | F67: =+SUM(F59:F66) -> (6.0) | G67: =+SUM(G59:G66) -> (6.4) | H67: =+SUM(H59:H66) -> (6.3) | I67: =+SUM(I59:I66) -> (5.8) | J67: =+SUM(J59:J66) -> (6.3) | ... O67: =+SUM(O59:O66) -> (76.1)
B68: Contribución Neta $ | C68: =C58+C67 -> 2.2 | D68: =D58+D67 -> 3.1 | E68: =E58+E67 -> 5.1 | F68: =F58+F67 -> 6.3 | G68: =G58+G67 -> 3.5 | H68: =H58+H67 -> 7.1 | I68: =I58+I67 -> 3.4 | J68: =J58+J67 -> 8.7 | ... O68: =O58+O67 -> 70.0
B71: Plan 2025 | C71: 45658 | D71: 45689 | E71: 45717 | F71: 45748 | G71: 45778 | H71: 45809 | I71: 45839 | J71: 45870 | K71: 45901 | L71: 45931 | M71: 45962 | N71: 45992 | O71: Total | R71: % | S71: 46023 | T71: 46054 | U71: 46082 | V71: 46113 | W71: 46143 | X71: 46174 | Y71: 46204 | Z71: 46235 | AA71: 46266 | AB71: 46296 | AC71: 46327 | AD71: 46357
B72: Ingresos Internos | C72: 18.424488 | D72: 25.520871 | E72: 28.538883 | F72: 28.652001 | G72: 29.754648 | H72: 31.157334 | I72: 34.514141 | J72: 33.605742 | K72: 38.898336 | L72: 37.279382 | M72: 38.197676 | N72: 75.456497 | O72: =+SUM(C72:N72) -> 420.0 | R72: Ingresos Internos | S72: =C52/C72 -> 123% | T72: =D52/D72 -> 111% | U72: =E52/E72 -> 102% | V72: =F52/F72 -> 99% | W72: =G52/G72 -> 97% | X72: =H52/H72 -> 102% | Y72: =I52/I72 -> 72% | Z72: =J52/J72 -> 113% | ... AB72: =L52/L72 -> 122% | AC72: =AVERAGE(Y72:AB72) -> 104% | AD72: =N52/N72 -> 88%
B73: Ingresos Externos | C73: 5.0592858 | D73: 3.8336327 | E73: 3.530855 | F73: 7.8643994 | G73: 6.6681884 | H73: 5.8532418 | I73: 4.4273841 | J73: 4.717548 | K73: 4.5672549 | L73: 8.4021147 | M73: 7.8272959 | N73: 12.248799 | O73: =+SUM(C73:N73) -> 75.0 | R73: Ingresos Externos | S73: =C53/C73 -> 8% | T73: =D53/D73 -> 7% | U73: =E53/E73 -> 91% | V73: =F53/F73 -> 32% | W73: =G53/G73 -> 38% | X73: =H53/H73 -> 27% | Y73: =I53/I73 -> 37% | Z73: =J53/J73 -> 25% | ... AD73: =N53/N73 -> 18%
B74: Total Ingresos | C74: =C72+C73 -> 23.5 | D74: =D72+D73 -> 29.4 | E74: =E73+E72 -> 32.1 | F74: =F73+F72 -> 36.5 | G74: =G73+G72 -> 36.4 | H74: =H73+H72 -> 37.0 | I74: =I73+I72 -> 38.9 | J74: =J73+J72 -> 38.3 | K74: =K73+K72 -> 43.5 | L74: =L73+L72 -> 45.7 | ... O74: =O73+O72 -> 495.0 | R74: Total Ingresos
B75: Activaciones | C75: -14.860046 | D75: -18.681512 | E75: -20.437651 | F75: -23.106933 | G75: -23.098062 | H75: -23.510271 | I75: -24.810967 | J75: -24.401641 | K75: -27.709431 | L75: -28.96791 | M75: -29.213024 | N75: -55.782552 | O75: =+SUM(C75:N75) -> (314.6) | R75: Activaciones
B76: Comisiones | C76: -0.22480196 | D76: -0.21658131 | E76: -0.2196104 | F76: -0.3494914 | G76: -0.31817515 | H76: -0.29944616 | I76: -0.27028777 | J76: -0.2753204 | K76: -0.29200202 | L76: -0.40006069 | M76: -0.38656594 | N76: -0.6676568 | O76: =+SUM(C76:N76) -> (3.9) | R76: Comisiones
B77: Costos Totales | C77: =SUM(C75:C76) -> (15.1) | D77: =SUM(D75:D76) -> (18.9) | E77: =SUM(E75:E76) -> (20.7) | F77: =SUM(F75:F76) -> (23.5) | G77: =SUM(G75:G76) -> (23.4) | H77: =SUM(H75:H76) -> (23.8) | I77: =SUM(I75:I76) -> (25.1) | J77: =SUM(J75:J76) -> (24.7) | ... O77: =SUM(O75:O76) -> (318.5) | R77: Costos Totales
B78: Contribución Bruta | C78: =C74+C77 -> 8.4 | D78: =D74+D77 -> 10.5 | E78: =E74+E77 -> 11.4 | F78: =F74+F77 -> 13.1 | G78: =G74+G77 -> 13.0 | H78: =H74+H77 -> 13.2 | I78: =I74+I77 -> 13.9 | J78: =J74+J77 -> 13.6 | ... O78: =O74+O77 -> 176.5 | R78: Contribución Bruta
B79: Personal | C79: -2.9476059 | D79: -2.9476059 | E79: -2.9476059 | F79: -2.9476059 | G79: -3.6568771 | H79: -3.6568771 | I79: -3.6568771 | J79: -3.6568771 | K79: -3.6568771 | L79: -3.6568771 | M79: -3.6568771 | N79: -3.6568771 | O79: =+SUM(C79:N79) -> (41.0) | R79: Personal
B80: Operación | C80: -0.74517835 | D80: -0.69517835 | E80: -0.95517835 | F80: -0.59517835 | G80: -0.34517835 | H80: -0.52517835 | I80: -0.56517835 | J80: -0.34517835 | K80: -0.50517835 | L80: -0.34517835 | M80: -0.34517835 | N80: -0.50517835 | O80: =+SUM(C80:N80) -> (6.5) | R80: Operación
B81: Mercadotecnia | C81: -0.17610793 | D81: -0.25706793 | E81: -0.90006793 | F81: -0.70506793 | G81: -0.44456793 | H81: -0.14806793 | I81: -0.18306793 | J81: -0.11806793 | K81: -0.18806793 | L81: -0.30506793 | M81: -0.18006793 | N81: -0.088067928 | O81: =+SUM(C81:N81) -> (3.7) | R81: Mercadotecnia
B82: Renta, Luz y Teléfono | C82: -0.33778552 | D82: -0.33778552 | E82: -0.33778552 | F82: -0.33778552 | G82: -0.33778552 | H82: -0.33778552 | I82: -0.33778552 | J82: -0.33778552 | K82: -0.33778552 | L82: -0.33778552 | M82: -0.33778552 | N82: -0.33778552 | O82: =+SUM(C82:N82) -> (4.1) | R82: Renta, Luz y Teléfono
B83: Gastos de despacho GS | C83: -0.11926408 | D83: -0.11878024 | E83: -0.12397104 | F83: -0.13701096 | G83: -0.13387685 | H83: -0.1355508 | I83: -0.13860288 | J83: -0.15176036 | K83: -0.13159044 | L83: -0.18110952 | M83: -0.18110952 | N83: -0.18110952 | O83: =+SUM(C83:N83) -> (1.7) | R83: Gastos de despacho GS
B84: Costo de Activo | C84: -0.00066904472 | D84: -0.0153804 | E84: -0.023077965 | F84: -0.021170025 | G84: -0.021170025 | H84: -0.021168098 | I84: -0.020013098 | J84: -0.0200025 | K84: -0.00200025 | L84: -0.028461174 | M84: -0.028461174 | N84: -0.028461174 | O84: =+SUM(C84:N84) -> (0.2) | R84: Costo de Activo
B85: Gastos Ventas | C85: -0.44714745 | D85: -0.44714745 | E85: -0.44714745 | F85: -0.44714745 | G85: -0.44714745 | H85: -0.44714745 | I85: -0.44714745 | J85: -0.44714745 | K85: -0.44714745 | L85: -0.44714745 | M85: -0.44714745 | N85: -0.44714745 | O85: =+SUM(C85:N85) -> (5.4) | R85: Gastos Ventas
B86: Gastos Staff | C86: -1.1887699 | D86: -1.1849542 | E86: -1.2767442 | F86: -1.3327869 | G86: -1.4265934 | H86: -1.4394657 | I86: -1.6396965 | J86: -1.36614 | K86: -2.0101214 | L86: -1.868954 | M86: -2.252356 | N86: -2.2515914 | O86: =+SUM(C86:N86) -> (19.2) | R86: Gastos Staff
B87: Total Gastos | C87: =+SUM(C79:C86) -> (6.0) | D87: =+SUM(D79:D86) -> (6.0) | E87: =+SUM(E79:E86) -> (7.0) | F87: =+SUM(F79:F86) -> (6.5) | G87: =+SUM(G79:G86) -> (6.8) | H87: =+SUM(H79:H86) -> (6.7) | I87: =+SUM(I79:I86) -> (7.0) | J87: =+SUM(J79:J86) -> (6.4) | ... O87: =+SUM(O79:O86) -> (81.8)
B88: Contribución Neta $ | C88: =C78+C87 -> 2.4 | D88: =D78+D87 -> 4.5 | E88: =E78+E87 -> 4.4 | F88: =F78+F87 -> 6.5 | G88: =G78+G87 -> 6.2 | H88: =H78+H87 -> 6.5 | I88: =I78+I87 -> 6.9 | J88: =J78+J87 -> 7.2 | ... O88: =O78+O87 -> 94.7

Sheet Mkt United + Troader 26
B1: MARKETING UNITED + TROADER REAL 2024 | Q1: MARKETING UNITED + TROADER REAL 2025 | AF1: MARKETING UNITED + TROADER PRESUPUESTO 2026 | AU1: MARKETING UNITED + TROADER FORECAST 2026 | BK1: MARKETING UNITED + TROADER
BK3: Real 2025 | BM3: Plan 2026 | BO3: Fcst 2026 | BQ3: Conceptos | BR3: Variaciones
BR4: Fcst 2026 vs Ppto 2026 | BT4: Fcst 2026 vs Real 2025
B5: Real 2024 | C5: 45292 | D5: 45323 | E5: 45352 | F5: 45383 | G5: 45413 | H5: 45444 | I5: 45474 | J5: 45505 | K5: 45536 | L5: 45566 | M5: 45597 | N5: 45627 | O5: Total | Q5: Real 2025 | R5: 46023 | S5: 46054 | T5: 46082 | U5: 46113 | V5: 46143 | W5: 46174 | X5: 46204 | Y5: 46235 | Z5: 46266 | AA5: 46296 | AB5: 46327 | AC5: 46357 | AD5: Total | AF5: Presupuesto 2026 | AG5: 46023 | AH5: 46054 | AI5: 46082 | AJ5: 46113 | AK5: 46143 | AL5: 46174 | AM5: 46204 | AN5: 46235 | AO5: 46266 | AP5: 46296 | AQ5: 46327 | AR5: 46357 | AS5: Total | AU5: Forecast 2026 | AV5: 46023 | AW5: 46054 | AX5: 46082 | AY5: 46113 | AZ5: 46143 | BA5: 46174 | BB5: 46204 | BC5: 46235 | BD5: 46266 | BE5: 46296 | BF5: 46327 | BG5: 46357 | BH5: Total | BK5: $ | BL5: % | BM5: $ | BN5: % | BO5: $ | BP5: % | BR5: $ | BS5: % | BT5: $ | BU5: %
B6: Ingresos Internos | C6: =SUMIF($B$38:$B$86,$B6,C$38:C$86) -> 35.8 | D6: =SUMIF($B$38:$B$86,$B6,D$38:D$86) -> 39.6 | E6: =SUMIF($B$38:$B$86,$B6,E$38:E$86) -> 48.7 | F6: =SUMIF($B$38:$B$86,$B6,F$38:F$86) -> 68.7 | G6: =SUMIF($B$38:$B$86,$B6,G$38:G$86) -> 63.1 | H6: =SUMIF($B$38:$B$86,$B6,H$38:H$86) -> 73.1 | I6: =SUMIF($B$38:$B$86,$B6,I$38:I$86) -> 63.3 | J6: =SUMIF($B$38:$B$86,$B6,J$38:J$86) -> 70.9 | ... N6: =SUMIF($B$38:$B$86,$B6,N$38:N$86) -> 89.6 | O6: =+SUM(C6:N6) -> 810.4 | Q6: Ingresos Internos | R6: =SUMIF($Q$38:$Q$86,$Q6,R$38:R$86) -> 51.2 | S6: =SUMIF($Q$38:$Q$86,$Q6,S$38:S$86) -> 59.5 | T6: =SUMIF($Q$38:$Q$86,$Q6,T$38:T$86) -> 58.3 | U6: =SUMIF($Q$38:$Q$86,$Q6,U$38:U$86) -> 65.3 | V6: =SUMIF($Q$38:$Q$86,$Q6,V$38:V$86) -> 62.5 | W6: =SUMIF($Q$38:$Q$86,$Q6,W$38:W$86) -> 66.1 | X6: =SUMIF($Q$38:$Q$86,$Q6,X$38:X$86) -> 70.7 | Y6: =SUMIF($Q$38:$Q$86,$Q6,Y$38:Y$86) -> 75.1 | ... AC6: =SUMIF($Q$38:$Q$86,$Q6,AC$38:AC$86) -> 72.3 | AD6: =+SUM(R6:AC6) -> 809.3 | AF6: Ingresos Internos | AG6: =SUMIF($AF$38:$AF$86,$AF6,AG$38:AG$86) -> 28.5 | AH6: =SUMIF($AF$38:$AF$86,$AF6,AH$38:AH$86) -> 27.7 | AI6: =SUMIF($AF$38:$AF$86,$AF6,AI$38:AI$86) -> 25.7 | AJ6: =SUMIF($AF$38:$AF$86,$AF6,AJ$38:AJ$86) -> 31.8 | AK6: =SUMIF($AF$38:$AF$86,$AF6,AK$38:AK$86) -> 42.3 | AL6: =SUMIF($AF$38:$AF$86,$AF6,AL$38:AL$86) -> 38.3 | AM6: =SUMIF($AF$38:$AF$86,$AF6,AM$38:AM$86) -> 32.9 | AN6: =SUMIF($AF$38:$AF$86,$AF6,AN$38:AN$86) -> 46.4 | ... AR6: =SUMIF($AF$38:$AF$86,$AF6,AR$38:AR$86) -> 78.0 | AS6: =+SUM(AG6:AR6) -> 489.0 | AU6: Ingresos Internos | AV6: =SUMIF($AU$38:$AU$86,$AU6,AV$38:AV$86) -> #REF! | AW6: =SUMIF($AU$38:$AU$86,$AU6,AW$38:AW$86) -> #REF! | AX6: =SUMIF($AU$38:$AU$86,$AU6,AX$38:AX$86) -> #REF! | AY6: =SUMIF($AU$38:$AU$86,$AU6,AY$38:AY$86) -> #REF! | AZ6: =SUMIF($AU$38:$AU$86,$AU6,AZ$38:AZ$86) -> 40.8 | BA6: =SUMIF($AU$38:$AU$86,$AU6,BA$38:BA$86) -> 33.5 | BB6: =SUMIF($AU$38:$AU$86,$AU6,BB$38:BB$86) -> 30.3 | BC6: =SUMIF($AU$38:$AU$86,$AU6,BC$38:BC$86) -> 44.0 | ... BG6: =SUMIF($AU$38:$AU$86,$AU6,BG$38:BG$86) -> 70.5 | BH6: =+SUM(AV6:BG6) -> #REF! | BK6: =VLOOKUP(BQ6,$Q$5:$AD$29,14,0) -> 809.3 | BL6: =IF((+IFERROR((BK6/$BK$8),0))<=-200%,"-200%",(+IFERROR((BK6/$BK$8),0))) -> 98% | BM6: =VLOOKUP(BQ6,$AF$5:$AS$29,14,0) -> 489.0 | BN6: =IF((+IFERROR((BM6/$BM$8),0))<=-200%,"-200%",(+IFERROR((BM6/$BM$8),0))) -> 87% | BO6: =VLOOKUP(BQ6,$AU$5:$BH$29,14,0) -> #REF! | BP6: =IF((+IFERROR((BO6/$BO$8),0))<=-200%,"-200%",(+IFERROR((BO6/$BO$8),0))) -> 0% | BQ6: Ingresos Internos | BR6: =+BO6-BM6 -> #REF! | BS6: =IF((IFERROR(IF(ABS(BR6/BM6)>=9.99,IF(BR6>0,9.99,-9.99),BR6/ABS(BM6)),IF(BR6=0,0,BR6/ABS(BR6))))<=-200%,"-200%",(IFERROR(IF(ABS(BR6/BM6)>=9.99,IF(BR6>0,9.99,-9.99),BR6/ABS(BM6)),IF(BR6=0,0,BR6/ABS(BR6))))) -> #REF! | BT6: =+BO6-BK6 -> #REF! | BU6: =IF((IFERROR(IF(ABS(BT6/BK6)>=9.99,IF(BT6>0,9.99,-9.99),BT6/ABS(BK6)),IF(BT6=0,0,BT6/ABS(BT6))))<=-200%,"-200%",(IFERROR(IF(ABS(BT6/BK6)>=9.99,IF(BT6>0,9.99,-9.99),BT6/ABS(BK6)),IF(BT6=0,0,BT6/ABS(BT6))))) -> #REF!
B7: Ingresos Externos | C7: =SUMIF($B$38:$B$86,$B7,C$38:C$86) -> 3.4 | D7: =SUMIF($B$38:$B$86,$B7,D$38:D$86) -> 3.7 | E7: =SUMIF($B$38:$B$86,$B7,E$38:E$86) -> 2.3 | F7: =SUMIF($B$38:$B$86,$B7,F$38:F$86) -> 0.5 | G7: =SUMIF($B$38:$B$86,$B7,G$38:G$86) -> 1.3 | H7: =SUMIF($B$38:$B$86,$B7,H$38:H$86) -> 1.1 | I7: =SUMIF($B$38:$B$86,$B7,I$38:I$86) -> 0.2 | J7: =SUMIF($B$38:$B$86,$B7,J$38:J$86) -> 0.7 | ... N7: =SUMIF($B$38:$B$86,$B7,N$38:N$86) -> 0.1 | O7: =+SUM(C7:N7) -> 17.2 | Q7: Ingresos Externos | R7: =SUMIF($Q$38:$Q$86,$Q7,R$38:R$86) -> 0.4 | S7: =SUMIF($Q$38:$Q$86,$Q7,S$38:S$86) -> 0.3 | T7: =SUMIF($Q$38:$Q$86,$Q7,T$38:T$86) -> 3.2 | U7: =SUMIF($Q$38:$Q$86,$Q7,U$38:U$86) -> 2.5 | V7: =SUMIF($Q$38:$Q$86,$Q7,V$38:V$86) -> 2.5 | W7: =SUMIF($Q$38:$Q$86,$Q7,W$38:W$86) -> 1.6 | X7: =SUMIF($Q$38:$Q$86,$Q7,X$38:X$86) -> 1.6 | Y7: =SUMIF($Q$38:$Q$86,$Q7,Y$38:Y$86) -> 1.2 | ... AC7: =SUMIF($Q$38:$Q$86,$Q7,AC$38:AC$86) -> 2.2 | AD7: =+SUM(R7:AC7) -> 18.3 | AF7: Ingresos Externos | AG7: =SUMIF($AF$38:$AF$86,$AF7,AG$38:AG$86) -> 1.0 | AH7: =SUMIF($AF$38:$AF$86,$AF7,AH$38:AH$86) -> 1.6 | AI7: =SUMIF($AF$38:$AF$86,$AF7,AI$38:AI$86) -> 2.3 | AJ7: =SUMIF($AF$38:$AF$86,$AF7,AJ$38:AJ$86) -> 2.7 | AK7: =SUMIF($AF$38:$AF$86,$AF7,AK$38:AK$86) -> 3.4 | AL7: =SUMIF($AF$38:$AF$86,$AF7,AL$38:AL$86) -> 3.5 | AM7: =SUMIF($AF$38:$AF$86,$AF7,AM$38:AM$86) -> 3.9 | AN7: =SUMIF($AF$38:$AF$86,$AF7,AN$38:AN$86) -> 5.1 | ... AR7: =SUMIF($AF$38:$AF$86,$AF7,AR$38:AR$86) -> 14.3 | AS7: =+SUM(AG7:AR7) -> 71.7 | AU7: Ingresos Externos | AV7: =SUMIF($AU$38:$AU$86,$AU7,AV$38:AV$86) -> #REF! | AW7: =SUMIF($AU$38:$AU$86,$AU7,AW$38:AW$86) -> #REF! | AX7: =SUMIF($AU$38:$AU$86,$AU7,AX$38:AX$86) -> #REF! | AY7: =SUMIF($AU$38:$AU$86,$AU7,AY$38:AY$86) -> #REF! | AZ7: =SUMIF($AU$38:$AU$86,$AU7,AZ$38:AZ$86) -> 4.6 | BA7: =SUMIF($AU$38:$AU$86,$AU7,BA$38:BA$86) -> 7.8 | BB7: =SUMIF($AU$38:$AU$86,$AU7,BB$38:BB$86) -> 4.1 | BC7: =SUMIF($AU$38:$AU$86,$AU7,BC$38:BC$86) -> 0.1 | ... BG7: =SUMIF($AU$38:$AU$86,$AU7,BG$38:BG$86) -> 1.1 | BH7: =+SUM(AV7:BG7) -> #REF! | BK7: =VLOOKUP(BQ7,$Q$5:$AD$29,14,0) -> 18.3 | BL7: =IF((+IFERROR((BK7/$BK$8),0))<=-200%,"-200%",(+IFERROR((BK7/$BK$8),0))) -> 2% | BM7: =VLOOKUP(BQ7,$AF$5:$AS$29,14,0) -> 71.7 | BN7: =IF((+IFERROR((BM7/$BM$8),0))<=-200%,"-200%",(+IFERROR((BM7/$BM$8),0))) -> 13% | BO7: =VLOOKUP(BQ7,$AU$5:$BH$29,14,0) -> #REF! | BP7: =IF((+IFERROR((BO7/$BO$8),0))<=-200%,"-200%",(+IFERROR((BO7/$BO$8),0))) -> 0% | BQ7: Ingresos Externos | BR7: =+BO7-BM7 -> #REF! | BS7: =IF((IFERROR(IF(ABS(BR7/BM7)>=9.99,IF(BR7>0,9.99,-9.99),BR7/ABS(BM7)),IF(BR7=0,0,BR7/ABS(BR7))))<=-200%,"-200%",(IFERROR(IF(ABS(BR7/BM7)>=9.99,IF(BR7>0,9.99,-9.99),BR7/ABS(BM7)),IF(BR7=0,0,BR7/ABS(BR7))))) -> #REF! | BT7: =+BO7-BK7 -> #REF! | BU7: =IF((IFERROR(IF(ABS(BT7/BK7)>=9.99,IF(BT7>0,9.99,-9.99),BT7/ABS(BK7)),IF(BT7=0,0,BT7/ABS(BT7))))<=-200%,"-200%",(IFERROR(IF(ABS(BT7/BK7)>=9.99,IF(BT7>0,9.99,-9.99),BT7/ABS(BK7)),IF(BT7=0,0,BT7/ABS(BT7))))) -> #REF!
B8: Total Ingresos | C8: =C6+C7 -> 39.2 | D8: =D6+D7 -> 43.3 | E8: =E7+E6 -> 51.0 | F8: =F7+F6 -> 69.2 | G8: =G7+G6 -> 64.4 | H8: =H7+H6 -> 74.2 | I8: =I7+I6 -> 63.5 | J8: =J7+J6 -> 71.5 | K8: =K7+K6 -> 62.4 | L8: =L7+L6 -> 85.7 | ... O8: =O7+O6 -> 827.6 | Q8: Total Ingresos | R8: =R6+R7 -> 51.6 | S8: =S6+S7 -> 59.8 | T8: =T7+T6 -> 61.5 | U8: =U7+U6 -> 67.8 | V8: =V7+V6 -> 65.0 | W8: =W7+W6 -> 67.7 | X8: =X7+X6 -> 72.4 | Y8: =Y7+Y6 -> 76.2 | Z8: =Z7+Z6 -> 81.1 | AA8: =AA7+AA6 -> 63.3 | ... AD8: =AD7+AD6 -> 827.6 | AF8: Total Ingresos | AG8: =AG6+AG7 -> 29.5 | AH8: =AH6+AH7 -> 29.3 | AI8: =AI7+AI6 -> 28.1 | AJ8: =AJ7+AJ6 -> 34.5 | AK8: =AK7+AK6 -> 45.7 | AL8: =AL7+AL6 -> 41.8 | AM8: =AM7+AM6 -> 36.8 | AN8: =AN7+AN6 -> 51.5 | AO8: =AO7+AO6 -> 54.4 | AP8: =AP7+AP6 -> 56.1 | ... AS8: =AS7+AS6 -> 560.7 | AU8: Total Ingresos | AV8: =AV6+AV7 -> #REF! | AW8: =AW6+AW7 -> #REF! | AX8: =AX7+AX6 -> #REF! | AY8: =AY7+AY6 -> #REF! | AZ8: =AZ7+AZ6 -> 45.4 | BA8: =BA7+BA6 -> 41.2 | BB8: =BB7+BB6 -> 34.4 | BC8: =BC7+BC6 -> 44.2 | BD8: =BD7+BD6 -> 49.1 | BE8: =BE7+BE6 -> 48.9 | ... BH8: =BH7+BH6 -> #REF! | BK8: =SUM(BK6:BK7) -> 827.6 | BL8: =IF((+IFERROR((BK8/$BK$8),0))<=-200%,"-200%",(+IFERROR((BK8/$BK$8),0))) -> 100% | BM8: =SUM(BM6:BM7) -> 560.7 | BN8: =IF((+IFERROR((BM8/$BM$8),0))<=-200%,"-200%",(+IFERROR((BM8/$BM$8),0))) -> 100% | BO8: =SUM(BO6:BO7) -> #REF! | BP8: =IF((+IFERROR((BO8/$BO$8),0))<=-200%,"-200%",(+IFERROR((BO8/$BO$8),0))) -> 0% | BQ8: Total Ingresos | BR8: =+BO8-BM8 -> #REF! | BS8: =IF((IFERROR(IF(ABS(BR8/BM8)>=9.99,IF(BR8>0,9.99,-9.99),BR8/ABS(BM8)),IF(BR8=0,0,BR8/ABS(BR8))))<=-200%,"-200%",(IFERROR(IF(ABS(BR8/BM8)>=9.99,IF(BR8>0,9.99,-9.99),BR8/ABS(BM8)),IF(BR8=0,0,BR8/ABS(BR8))))) -> #REF! | BT8: =+BO8-BK8 -> #REF! | BU8: =IF((IFERROR(IF(ABS(BT8/BK8)>=9.99,IF(BT8>0,9.99,-9.99),BT8/ABS(BK8)),IF(BT8=0,0,BT8/ABS(BT8))))<=-200%,"-200%",(IFERROR(IF(ABS(BT8/BK8)>=9.99,IF(BT8>0,9.99,-9.99),BT8/ABS(BK8)),IF(BT8=0,0,BT8/ABS(BT8))))) -> #REF!
B9: Costo | C9: =SUMIF($B$38:$B$86,$B9,C$38:C$86) -> (18.1) | D9: =SUMIF($B$38:$B$86,$B9,D$38:D$86) -> (15.0) | E9: =SUMIF($B$38:$B$86,$B9,E$38:E$86) -> (16.9) | F9: =SUMIF($B$38:$B$86,$B9,F$38:F$86) -> (22.9) | G9: =SUMIF($B$38:$B$86,$B9,G$38:G$86) -> (22.5) | H9: =SUMIF($B$38:$B$86,$B9,H$38:H$86) -> (22.0) | I9: =SUMIF($B$38:$B$86,$B9,I$38:I$86) -> (27.1) | J9: =SUMIF($B$38:$B$86,$B9,J$38:J$86) -> (24.1) | ... N9: =SUMIF($B$38:$B$86,$B9,N$38:N$86) -> (32.2) | O9: =+SUM(C9:N9) -> (286.3) | Q9: Costo | R9: =SUMIF($Q$38:$Q$86,$Q9,R$38:R$86) -> (23.4) | S9: =SUMIF($Q$38:$Q$86,$Q9,S$38:S$86) -> (21.4) | T9: =SUMIF($Q$38:$Q$86,$Q9,T$38:T$86) -> (22.3) | U9: =SUMIF($Q$38:$Q$86,$Q9,U$38:U$86) -> (26.8) | V9: =SUMIF($Q$38:$Q$86,$Q9,V$38:V$86) -> (26.6) | W9: =SUMIF($Q$38:$Q$86,$Q9,W$38:W$86) -> (26.1) | X9: =SUMIF($Q$38:$Q$86,$Q9,X$38:X$86) -> (34.3) | Y9: =SUMIF($Q$38:$Q$86,$Q9,Y$38:Y$86) -> (28.3) | ... AC9: =SUMIF($Q$38:$Q$86,$Q9,AC$38:AC$86) -> (0.9) | AD9: =+SUM(R9:AC9) -> (251.9) | AF9: Costo | AG9: =SUMIF($AF$38:$AF$86,$AF9,AG$38:AG$86) -> (0.8) | AH9: =SUMIF($AF$38:$AF$86,$AF9,AH$38:AH$86) -> (1.3) | AI9: =SUMIF($AF$38:$AF$86,$AF9,AI$38:AI$86) -> (1.3) | AJ9: =SUMIF($AF$38:$AF$86,$AF9,AJ$38:AJ$86) -> (1.4) | AK9: =SUMIF($AF$38:$AF$86,$AF9,AK$38:AK$86) -> (1.4) | AL9: =SUMIF($AF$38:$AF$86,$AF9,AL$38:AL$86) -> (1.4) | AM9: =SUMIF($AF$38:$AF$86,$AF9,AM$38:AM$86) -> (1.4) | AN9: =SUMIF($AF$38:$AF$86,$AF9,AN$38:AN$86) -> (1.4) | ... AR9: =SUMIF($AF$38:$AF$86,$AF9,AR$38:AR$86) -> (1.6) | AS9: =+SUM(AG9:AR9) -> (16.6) | AU9: Costo | AV9: =SUMIF($AU$38:$AU$86,$AU9,AV$38:AV$86) -> #REF! | AW9: =SUMIF($AU$38:$AU$86,$AU9,AW$38:AW$86) -> #REF! | AX9: =SUMIF($AU$38:$AU$86,$AU9,AX$38:AX$86) -> #REF! | AY9: =SUMIF($AU$38:$AU$86,$AU9,AY$38:AY$86) -> #REF! | AZ9: =SUMIF($AU$38:$AU$86,$AU9,AZ$38:AZ$86) -> (1.0) | BA9: =SUMIF($AU$38:$AU$86,$AU9,BA$38:BA$86) -> (1.0) | BB9: =SUMIF($AU$38:$AU$86,$AU9,BB$38:BB$86) -> (1.0) | BC9: =SUMIF($AU$38:$AU$86,$AU9,BC$38:BC$86) -> (1.0) | ... BG9: =SUMIF($AU$38:$AU$86,$AU9,BG$38:BG$86) -> (1.0) | BH9: =+SUM(AV9:BG9) -> #REF! | BK9: =VLOOKUP(BQ9,$Q$5:$AD$29,14,0) -> (251.9) | BL9: =IF((+IFERROR((BK9/$BK$8),0))<=-200%,"-200%",(+IFERROR((BK9/$BK$8),0))) -> (30%) | BM9: =VLOOKUP(BQ9,$AF$5:$AS$29,14,0) -> (16.6) | BN9: =IF((+IFERROR((BM9/$BM$8),0))<=-200%,"-200%",(+IFERROR((BM9/$BM$8),0))) -> (3%) | BO9: =VLOOKUP(BQ9,$AU$5:$BH$29,14,0) -> #REF! | BP9: =IF((+IFERROR((BO9/$BO$8),0))<=-200%,"-200%",(+IFERROR((BO9/$BO$8),0))) -> 0% | BQ9: Costo | BR9: =+BO9-BM9 -> #REF! | BS9: =IF((IFERROR(IF(ABS(BR9/BM9)>=9.99,IF(BR9>0,9.99,-9.99),BR9/ABS(BM9)),IF(BR9=0,0,BR9/ABS(BR9))))<=-200%,"-200%",(IFERROR(IF(ABS(BR9/BM9)>=9.99,IF(BR9>0,9.99,-9.99),BR9/ABS(BM9)),IF(BR9=0,0,BR9/ABS(BR9))))) -> #REF! | BT9: =+BO9-BK9 -> #REF! | BU9: =IF((IFERROR(IF(ABS(BT9/BK9)>=9.99,IF(BT9>0,9.99,-9.99),BT9/ABS(BK9)),IF(BT9=0,0,BT9/ABS(BT9))))<=-200%,"-200%",(IFERROR(IF(ABS(BT9/BK9)>=9.99,IF(BT9>0,9.99,-9.99),BT9/ABS(BK9)),IF(BT9=0,0,BT9/ABS(BT9))))) -> #REF!
B10: Costo de nube | C10: =SUMIF($B$38:$B$86,$B10,C$38:C$86) -> - | D10: =SUMIF($B$38:$B$86,$B10,D$38:D$86) -> - | E10: =SUMIF($B$38:$B$86,$B10,E$38:E$86) -> - | F10: =SUMIF($B$38:$B$86,$B10,F$38:F$86) -> - | G10: =SUMIF($B$38:$B$86,$B10,G$38:G$86) -> - | H10: =SUMIF($B$38:$B$86,$B10,H$38:H$86) -> - | I10: =SUMIF($B$38:$B$86,$B10,I$38:I$86) -> - | J10: =SUMIF($B$38:$B$86,$B10,J$38:J$86) -> - | ... N10: =SUMIF($B$38:$B$86,$B10,N$38:N$86) -> - | O10: =+SUM(C10:N10) -> - | Q10: Costo de nube | R10: =SUMIF($Q$38:$Q$86,$Q10,R$38:R$86) -> (0.2) | S10: =SUMIF($Q$38:$Q$86,$Q10,S$38:S$86) -> (0.2) | T10: =SUMIF($Q$38:$Q$86,$Q10,T$38:T$86) -> (0.2) | U10: =SUMIF($Q$38:$Q$86,$Q10,U$38:U$86) -> (0.2) | V10: =SUMIF($Q$38:$Q$86,$Q10,V$38:V$86) -> (0.2) | W10: =SUMIF($Q$38:$Q$86,$Q10,W$38:W$86) -> (0.2) | X10: =SUMIF($Q$38:$Q$86,$Q10,X$38:X$86) -> (0.1) | Y10: =SUMIF($Q$38:$Q$86,$Q10,Y$38:Y$86) -> (0.2) | ... AC10: =SUMIF($Q$38:$Q$86,$Q10,AC$38:AC$86) -> - | AD10: =+SUM(R10:AC10) -> (1.5) | AF10: Costo de nube | AG10: =SUMIF($AF$38:$AF$86,$AF10,AG$38:AG$86) -> (0.1) | AH10: =SUMIF($AF$38:$AF$86,$AF10,AH$38:AH$86) -> (0.1) | AI10: =SUMIF($AF$38:$AF$86,$AF10,AI$38:AI$86) -> (0.1) | AJ10: =SUMIF($AF$38:$AF$86,$AF10,AJ$38:AJ$86) -> (0.1) | AK10: =SUMIF($AF$38:$AF$86,$AF10,AK$38:AK$86) -> (0.1) | AL10: =SUMIF($AF$38:$AF$86,$AF10,AL$38:AL$86) -> (0.1) | AM10: =SUMIF($AF$38:$AF$86,$AF10,AM$38:AM$86) -> (0.1) | AN10: =SUMIF($AF$38:$AF$86,$AF10,AN$38:AN$86) -> (0.1) | ... AR10: =SUMIF($AF$38:$AF$86,$AF10,AR$38:AR$86) -> (0.1) | AS10: =+SUM(AG10:AR10) -> (1.2) | AU10: Costo de nube | AV10: =SUMIF($AU$38:$AU$86,$AU10,AV$38:AV$86) -> #REF! | AW10: =SUMIF($AU$38:$AU$86,$AU10,AW$38:AW$86) -> #REF! | AX10: =SUMIF($AU$38:$AU$86,$AU10,AX$38:AX$86) -> #REF! | AY10: =SUMIF($AU$38:$AU$86,$AU10,AY$38:AY$86) -> #REF! | AZ10: =SUMIF($AU$38:$AU$86,$AU10,AZ$38:AZ$86) -> (0.1) | BA10: =SUMIF($AU$38:$AU$86,$AU10,BA$38:BA$86) -> (0.1) | BB10: =SUMIF($AU$38:$AU$86,$AU10,BB$38:BB$86) -> (0.1) | BC10: =SUMIF($AU$38:$AU$86,$AU10,BC$38:BC$86) -> (0.1) | ... BG10: =SUMIF($AU$38:$AU$86,$AU10,BG$38:BG$86) -> (0.1) | BH10: =+SUM(AV10:BG10) -> #REF! | BK10: =VLOOKUP(BQ10,$Q$5:$AD$29,14,0) -> (1.5) | BL10: =IF((+IFERROR((BK10/$BK$8),0))<=-200%,"-200%",(+IFERROR((BK10/$BK$8),0))) -> (0%) | BM10: =VLOOKUP(BQ10,$AF$5:$AS$29,14,0) -> (1.2) | BN10: =IF((+IFERROR((BM10/$BM$8),0))<=-200%,"-200%",(+IFERROR((BM10/$BM$8),0))) -> (0%) | BO10: =VLOOKUP(BQ10,$AU$5:$BH$29,14,0) -> #REF! | BP10: =IF((+IFERROR((BO10/$BO$8),0))<=-200%,"-200%",(+IFERROR((BO10/$BO$8),0))) -> 0% | BQ10: Costo de nube | BR10: =+BO10-BM10 -> #REF! | BS10: =IF((IFERROR(IF(ABS(BR10/BM10)>=9.99,IF(BR10>0,9.99,-9.99),BR10/ABS(BM10)),IF(BR10=0,0,BR10/ABS(BR10))))<=-200%,"-200%",(IFERROR(IF(ABS(BR10/BM10)>=9.99,IF(BR10>0,9.99,-9.99),BR10/ABS(BM10)),IF(BR10=0,0,BR10/ABS(BR10))))) -> #REF! | BT10: =+BO10-BK10 -> #REF! | BU10: =IF((IFERROR(IF(ABS(BT10/BK10)>=9.99,IF(BT10>0,9.99,-9.99),BT10/ABS(BK10)),IF(BT10=0,0,BT10/ABS(BT10))))<=-200%,"-200%",(IFERROR(IF(ABS(BT10/BK10)>=9.99,IF(BT10>0,9.99,-9.99),BT10/ABS(BK10)),IF(BT10=0,0,BT10/ABS(BT10))))) -> #REF!
B11: Activaciones | C11: =SUMIF($B$38:$B$86,$B11,C$38:C$86) -> (10.7) | D11: =SUMIF($B$38:$B$86,$B11,D$38:D$86) -> (17.4) | E11: =SUMIF($B$38:$B$86,$B11,E$38:E$86) -> (18.0) | F11: =SUMIF($B$38:$B$86,$B11,F$38:F$86) -> (37.9) | G11: =SUMIF($B$38:$B$86,$B11,G$38:G$86) -> (19.0) | H11: =SUMIF($B$38:$B$86,$B11,H$38:H$86) -> (38.3) | I11: =SUMIF($B$38:$B$86,$B11,I$38:I$86) -> (17.9) | J11: =SUMIF($B$38:$B$86,$B11,J$38:J$86) -> (27.3) | ... N11: =SUMIF($B$38:$B$86,$B11,N$38:N$86) -> (28.8) | O11: =+SUM(C11:N11) -> (324.3) | Q11: Activaciones | R11: =SUMIF($Q$38:$Q$86,$Q11,R$38:R$86) -> (15.6) | S11: =SUMIF($Q$38:$Q$86,$Q11,S$38:S$86) -> (19.3) | T11: =SUMIF($Q$38:$Q$86,$Q11,T$38:T$86) -> (21.0) | U11: =SUMIF($Q$38:$Q$86,$Q11,U$38:U$86) -> (18.5) | V11: =SUMIF($Q$38:$Q$86,$Q11,V$38:V$86) -> (21.5) | W11: =SUMIF($Q$38:$Q$86,$Q11,W$38:W$86) -> (20.1) | X11: =SUMIF($Q$38:$Q$86,$Q11,X$38:X$86) -> (17.4) | Y11: =SUMIF($Q$38:$Q$86,$Q11,Y$38:Y$86) -> (24.3) | ... AC11: =SUMIF($Q$38:$Q$86,$Q11,AC$38:AC$86) -> (72.9) | AD11: =+SUM(R11:AC11) -> (336.1) | AF11: Activaciones | AG11: =SUMIF($AF$38:$AF$86,$AF11,AG$38:AG$86) -> (15.1) | AH11: =SUMIF($AF$38:$AF$86,$AF11,AH$38:AH$86) -> (15.3) | AI11: =SUMIF($AF$38:$AF$86,$AF11,AI$38:AI$86) -> (14.2) | AJ11: =SUMIF($AF$38:$AF$86,$AF11,AJ$38:AJ$86) -> (18.3) | AK11: =SUMIF($AF$38:$AF$86,$AF11,AK$38:AK$86) -> (25.0) | AL11: =SUMIF($AF$38:$AF$86,$AF11,AL$38:AL$86) -> (21.7) | AM11: =SUMIF($AF$38:$AF$86,$AF11,AM$38:AM$86) -> (19.0) | AN11: =SUMIF($AF$38:$AF$86,$AF11,AN$38:AN$86) -> (27.8) | ... AR11: =SUMIF($AF$38:$AF$86,$AF11,AR$38:AR$86) -> (51.9) | AS11: =+SUM(AG11:AR11) -> (300.9) | AU11: Activaciones | AV11: =SUMIF($AU$38:$AU$86,$AU11,AV$38:AV$86) -> (11.4) | AW11: =SUMIF($AU$38:$AU$86,$AU11,AW$38:AW$86) -> (19.4) | AX11: =SUMIF($AU$38:$AU$86,$AU11,AX$38:AX$86) -> (15.6) | AY11: =SUMIF($AU$38:$AU$86,$AU11,AY$38:AY$86) -> (24.5) | AZ11: =SUMIF($AU$38:$AU$86,$AU11,AZ$38:AZ$86) -> (26.2) | BA11: =SUMIF($AU$38:$AU$86,$AU11,BA$38:BA$86) -> (23.2) | BB11: =SUMIF($AU$38:$AU$86,$AU11,BB$38:BB$86) -> (19.1) | BC11: =SUMIF($AU$38:$AU$86,$AU11,BC$38:BC$86) -> (25.3) | ... BG11: =SUMIF($AU$38:$AU$86,$AU11,BG$38:BG$86) -> (41.7) | BH11: =+SUM(AV11:BG11) -> (309.4) | BK11: =VLOOKUP(BQ11,$Q$5:$AD$29,14,0) -> (336.1) | BL11: =IF((+IFERROR((BK11/$BK$8),0))<=-200%,"-200%",(+IFERROR((BK11/$BK$8),0))) -> (41%) | BM11: =VLOOKUP(BQ11,$AF$5:$AS$29,14,0) -> (300.9) | BN11: =IF((+IFERROR((BM11/$BM$8),0))<=-200%,"-200%",(+IFERROR((BM11/$BM$8),0))) -> (54%) | BO11: =VLOOKUP(BQ11,$AU$5:$BH$29,14,0) -> (309.4) | BP11: =IF((+IFERROR((BO11/$BO$8),0))<=-200%,"-200%",(+IFERROR((BO11/$BO$8),0))) -> 0% | BQ11: Activaciones | BR11: =+BO11-BM11 -> (8.5) | BS11: =IF((IFERROR(IF(ABS(BR11/BM11)>=9.99,IF(BR11>0,9.99,-9.99),BR11/ABS(BM11)),IF(BR11=0,0,BR11/ABS(BR11))))<=-200%,"-200%",(IFERROR(IF(ABS(BR11/BM11)>=9.99,IF(BR11>0,9.99,-9.99),BR11/ABS(BM11)),IF(BR11=0,0,BR11/ABS(BR11))))) -> (3%) | BT11: =+BO11-BK11 -> 26.6 | BU11: =IF((IFERROR(IF(ABS(BT11/BK11)>=9.99,IF(BT11>0,9.99,-9.99),BT11/ABS(BK11)),IF(BT11=0,0,BT11/ABS(BT11))))<=-200%,"-200%",(IFERROR(IF(ABS(BT11/BK11)>=9.99,IF(BT11>0,9.99,-9.99),BT11/ABS(BK11)),IF(BT11=0,0,BT11/ABS(BT11))))) -> 8%
B12: Comisiones | C12: =SUMIF($B$38:$B$86,$B12,C$38:C$86) -> (0.0) | D12: =SUMIF($B$38:$B$86,$B12,D$38:D$86) -> - | E12: =SUMIF($B$38:$B$86,$B12,E$38:E$86) -> (0.1) | F12: =SUMIF($B$38:$B$86,$B12,F$38:F$86) -> (0.1) | G12: =SUMIF($B$38:$B$86,$B12,G$38:G$86) -> (0.0) | H12: =SUMIF($B$38:$B$86,$B12,H$38:H$86) -> (0.0) | I12: =SUMIF($B$38:$B$86,$B12,I$38:I$86) -> (0.0) | J12: =SUMIF($B$38:$B$86,$B12,J$38:J$86) -> (0.0) | ... N12: =SUMIF($B$38:$B$86,$B12,N$38:N$86) -> - | O12: =+SUM(C12:N12) -> (0.3) | Q12: Comisiones | R12: =SUMIF($Q$38:$Q$86,$Q12,R$38:R$86) -> - | S12: =SUMIF($Q$38:$Q$86,$Q12,S$38:S$86) -> - | T12: =SUMIF($Q$38:$Q$86,$Q12,T$38:T$86) -> (0.1) | U12: =SUMIF($Q$38:$Q$86,$Q12,U$38:U$86) -> (0.0) | V12: =SUMIF($Q$38:$Q$86,$Q12,V$38:V$86) -> (0.0) | W12: =SUMIF($Q$38:$Q$86,$Q12,W$38:W$86) -> (0.0) | X12: =SUMIF($Q$38:$Q$86,$Q12,X$38:X$86) -> (0.0) | Y12: =SUMIF($Q$38:$Q$86,$Q12,Y$38:Y$86) -> (0.0) | ... AC12: =SUMIF($Q$38:$Q$86,$Q12,AC$38:AC$86) -> (0.1) | AD12: =+SUM(R12:AC12) -> (0.4) | AF12: Comisiones | AG12: =SUMIF($AF$38:$AF$86,$AF12,AG$38:AG$86) -> (0.1) | AH12: =SUMIF($AF$38:$AF$86,$AF12,AH$38:AH$86) -> (0.1) | AI12: =SUMIF($AF$38:$AF$86,$AF12,AI$38:AI$86) -> (0.1) | AJ12: =SUMIF($AF$38:$AF$86,$AF12,AJ$38:AJ$86) -> (0.1) | AK12: =SUMIF($AF$38:$AF$86,$AF12,AK$38:AK$86) -> (0.2) | AL12: =SUMIF($AF$38:$AF$86,$AF12,AL$38:AL$86) -> (0.1) | AM12: =SUMIF($AF$38:$AF$86,$AF12,AM$38:AM$86) -> (0.2) | AN12: =SUMIF($AF$38:$AF$86,$AF12,AN$38:AN$86) -> (0.2) | ... AR12: =SUMIF($AF$38:$AF$86,$AF12,AR$38:AR$86) -> (0.7) | AS12: =+SUM(AG12:AR12) -> (3.3) | AU12: Comisiones | AV12: =SUMIF($AU$38:$AU$86,$AU12,AV$38:AV$86) -> (0.0) | AW12: =SUMIF($AU$38:$AU$86,$AU12,AW$38:AW$86) -> (0.0) | AX12: =SUMIF($AU$38:$AU$86,$AU12,AX$38:AX$86) -> (0.0) | AY12: =SUMIF($AU$38:$AU$86,$AU12,AY$38:AY$86) -> (0.0) | AZ12: =SUMIF($AU$38:$AU$86,$AU12,AZ$38:AZ$86) -> (0.2) | BA12: =SUMIF($AU$38:$AU$86,$AU12,BA$38:BA$86) -> (0.2) | BB12: =SUMIF($AU$38:$AU$86,$AU12,BB$38:BB$86) -> (0.1) | BC12: =SUMIF($AU$38:$AU$86,$AU12,BC$38:BC$86) -> (0.0) | ... BG12: =SUMIF($AU$38:$AU$86,$AU12,BG$38:BG$86) -> (0.0) | BH12: =+SUM(AV12:BG12) -> (0.9) | BK12: =VLOOKUP(BQ12,$Q$5:$AD$29,14,0) -> (0.4) | BL12: =IF((+IFERROR((BK12/$BK$8),0))<=-200%,"-200%",(+IFERROR((BK12/$BK$8),0))) -> (0%) | BM12: =VLOOKUP(BQ12,$AF$5:$AS$29,14,0) -> (3.3) | BN12: =IF((+IFERROR((BM12/$BM$8),0))<=-200%,"-200%",(+IFERROR((BM12/$BM$8),0))) -> (1%) | BO12: =VLOOKUP(BQ12,$AU$5:$BH$29,14,0) -> (0.9) | BP12: =IF((+IFERROR((BO12/$BO$8),0))<=-200%,"-200%",(+IFERROR((BO12/$BO$8),0))) -> 0% | BQ12: Comisiones | BR12: =+BO12-BM12 -> 2.5 | BS12: =IF((IFERROR(IF(ABS(BR12/BM12)>=9.99,IF(BR12>0,9.99,-9.99),BR12/ABS(BM12)),IF(BR12=0,0,BR12/ABS(BR12))))<=-200%,"-200%",(IFERROR(IF(ABS(BR12/BM12)>=9.99,IF(BR12>0,9.99,-9.99),BR12/ABS(BM12)),IF(BR12=0,0,BR12/ABS(BR12))))) -> 74% | BT12: =+BO12-BK12 -> (0.4) | BU12: =IF((IFERROR(IF(ABS(BT12/BK12)>=9.99,IF(BT12>0,9.99,-9.99),BT12/ABS(BK12)),IF(BT12=0,0,BT12/ABS(BT12))))<=-200%,"-200%",(IFERROR(IF(ABS(BT12/BK12)>=9.99,IF(BT12>0,9.99,-9.99),BT12/ABS(BK12)),IF(BT12=0,0,BT12/ABS(BT12))))) -> (92%)
B13: Desarrollo de software | C13: =SUMIF($B$38:$B$86,$B13,C$38:C$86) -> (0.3) | D13: =SUMIF($B$38:$B$86,$B13,D$38:D$86) -> (0.3) | E13: =SUMIF($B$38:$B$86,$B13,E$38:E$86) -> (0.3) | F13: =SUMIF($B$38:$B$86,$B13,F$38:F$86) -> (0.3) | G13: =SUMIF($B$38:$B$86,$B13,G$38:G$86) -> (0.4) | H13: =SUMIF($B$38:$B$86,$B13,H$38:H$86) -> (0.3) | I13: =SUMIF($B$38:$B$86,$B13,I$38:I$86) -> (0.3) | J13: =SUMIF($B$38:$B$86,$B13,J$38:J$86) -> (0.3) | ... N13: =SUMIF($B$38:$B$86,$B13,N$38:N$86) -> (0.3) | O13: =+SUM(C13:N13) -> (3.7) | Q13: Desarrollo de software | R13: =SUMIF($Q$38:$Q$86,$Q13,R$38:R$86) -> (0.3) | S13: =SUMIF($Q$38:$Q$86,$Q13,S$38:S$86) -> (0.3) | T13: =SUMIF($Q$38:$Q$86,$Q13,T$38:T$86) -> (0.3) | U13: =SUMIF($Q$38:$Q$86,$Q13,U$38:U$86) -> (0.4) | V13: =SUMIF($Q$38:$Q$86,$Q13,V$38:V$86) -> (0.6) | W13: =SUMIF($Q$38:$Q$86,$Q13,W$38:W$86) -> (0.6) | X13: =SUMIF($Q$38:$Q$86,$Q13,X$38:X$86) -> (0.6) | Y13: =SUMIF($Q$38:$Q$86,$Q13,Y$38:Y$86) -> (0.6) | ... AC13: =SUMIF($Q$38:$Q$86,$Q13,AC$38:AC$86) -> (0.6) | AD13: =+SUM(R13:AC13) -> (6.1) | AF13: Desarrollo de software | AG13: =SUMIF($AF$38:$AF$86,$AF13,AG$38:AG$86) -> (0.9) | AH13: =SUMIF($AF$38:$AF$86,$AF13,AH$38:AH$86) -> (0.2) | AI13: =SUMIF($AF$38:$AF$86,$AF13,AI$38:AI$86) -> (0.2) | AJ13: =SUMIF($AF$38:$AF$86,$AF13,AJ$38:AJ$86) -> (0.2) | AK13: =SUMIF($AF$38:$AF$86,$AF13,AK$38:AK$86) -> (0.2) | AL13: =SUMIF($AF$38:$AF$86,$AF13,AL$38:AL$86) -> (0.2) | AM13: =SUMIF($AF$38:$AF$86,$AF13,AM$38:AM$86) -> (0.2) | AN13: =SUMIF($AF$38:$AF$86,$AF13,AN$38:AN$86) -> (0.1) | ... AR13: =SUMIF($AF$38:$AF$86,$AF13,AR$38:AR$86) -> (0.1) | AS13: =+SUM(AG13:AR13) -> (2.4) | AU13: Desarrollo de software | AV13: =SUMIF($AU$38:$AU$86,$AU13,AV$38:AV$86) -> #REF! | AW13: =SUMIF($AU$38:$AU$86,$AU13,AW$38:AW$86) -> #REF! | AX13: =SUMIF($AU$38:$AU$86,$AU13,AX$38:AX$86) -> #REF! | AY13: =SUMIF($AU$38:$AU$86,$AU13,AY$38:AY$86) -> #REF! | AZ13: =SUMIF($AU$38:$AU$86,$AU13,AZ$38:AZ$86) -> - | BA13: =SUMIF($AU$38:$AU$86,$AU13,BA$38:BA$86) -> - | BB13: =SUMIF($AU$38:$AU$86,$AU13,BB$38:BB$86) -> - | BC13: =SUMIF($AU$38:$AU$86,$AU13,BC$38:BC$86) -> - | ... BG13: =SUMIF($AU$38:$AU$86,$AU13,BG$38:BG$86) -> - | BH13: =+SUM(AV13:BG13) -> #REF! | BK13: =VLOOKUP(BQ13,$Q$5:$AD$29,14,0) -> (6.1) | BL13: =IF((+IFERROR((BK13/$BK$8),0))<=-200%,"-200%",(+IFERROR((BK13/$BK$8),0))) -> (1%) | BM13: =VLOOKUP(BQ13,$AF$5:$AS$29,14,0) -> (2.4) | BN13: =IF((+IFERROR((BM13/$BM$8),0))<=-200%,"-200%",(+IFERROR((BM13/$BM$8),0))) -> (0%) | BO13: =VLOOKUP(BQ13,$AU$5:$BH$29,14,0) -> #REF! | BP13: =IF((+IFERROR((BO13/$BO$8),0))<=-200%,"-200%",(+IFERROR((BO13/$BO$8),0))) -> 0% | BQ13: Desarrollo de software | BR13: =+BO13-BM13 -> #REF! | BS13: =IF((IFERROR(IF(ABS(BR13/BM13)>=9.99,IF(BR13>0,9.99,-9.99),BR13/ABS(BM13)),IF(BR13=0,0,BR13/ABS(BR13))))<=-200%,"-200%",(IFERROR(IF(ABS(BR13/BM13)>=9.99,IF(BR13>0,9.99,-9.99),BR13/ABS(BM13)),IF(BR13=0,0,BR13/ABS(BR13))))) -> #REF! | BT13: =+BO13-BK13 -> #REF! | BU13: =IF((IFERROR(IF(ABS(BT13/BK13)>=9.99,IF(BT13>0,9.99,-9.99),BT13/ABS(BK13)),IF(BT13=0,0,BT13/ABS(BT13))))<=-200%,"-200%",(IFERROR(IF(ABS(BT13/BK13)>=9.99,IF(BT13>0,9.99,-9.99),BT13/ABS(BK13)),IF(BT13=0,0,BT13/ABS(BT13))))) -> #REF!
B14: Participación Socios | C14: =SUMIF($B$38:$B$86,$B14,C$38:C$86) -> - | D14: =SUMIF($B$38:$B$86,$B14,D$38:D$86) -> - | E14: =SUMIF($B$38:$B$86,$B14,E$38:E$86) -> - | F14: =SUMIF($B$38:$B$86,$B14,F$38:F$86) -> - | G14: =SUMIF($B$38:$B$86,$B14,G$38:G$86) -> - | H14: =SUMIF($B$38:$B$86,$B14,H$38:H$86) -> - | I14: =SUMIF($B$38:$B$86,$B14,I$38:I$86) -> - | J14: =SUMIF($B$38:$B$86,$B14,J$38:J$86) -> - | ... N14: =SUMIF($B$38:$B$86,$B14,N$38:N$86) -> - | O14: =+SUM(C14:N14) -> - | Q14: Participación Socios | R14: =SUMIF($Q$38:$Q$86,$Q14,R$38:R$86) -> - | S14: =SUMIF($Q$38:$Q$86,$Q14,S$38:S$86) -> - | T14: =SUMIF($Q$38:$Q$86,$Q14,T$38:T$86) -> - | U14: =SUMIF($Q$38:$Q$86,$Q14,U$38:U$86) -> - | V14: =SUMIF($Q$38:$Q$86,$Q14,V$38:V$86) -> - | W14: =SUMIF($Q$38:$Q$86,$Q14,W$38:W$86) -> - | X14: =SUMIF($Q$38:$Q$86,$Q14,X$38:X$86) -> - | Y14: =SUMIF($Q$38:$Q$86,$Q14,Y$38:Y$86) -> - | ... AC14: =SUMIF($Q$38:$Q$86,$Q14,AC$38:AC$86) -> - | AD14: =+SUM(R14:AC14) -> - | AF14: Participación Socios | AG14: =SUMIF($AF$38:$AF$86,$AF14,AG$38:AG$86) -> (0.0) | AH14: =SUMIF($AF$38:$AF$86,$AF14,AH$38:AH$86) -> (0.1) | AI14: =SUMIF($AF$38:$AF$86,$AF14,AI$38:AI$86) -> (0.1) | AJ14: =SUMIF($AF$38:$AF$86,$AF14,AJ$38:AJ$86) -> (0.1) | AK14: =SUMIF($AF$38:$AF$86,$AF14,AK$38:AK$86) -> (0.1) | AL14: =SUMIF($AF$38:$AF$86,$AF14,AL$38:AL$86) -> (0.1) | AM14: =SUMIF($AF$38:$AF$86,$AF14,AM$38:AM$86) -> (0.1) | AN14: =SUMIF($AF$38:$AF$86,$AF14,AN$38:AN$86) -> (0.1) | ... AR14: =SUMIF($AF$38:$AF$86,$AF14,AR$38:AR$86) -> (0.5) | AS14: =+SUM(AG14:AR14) -> (2.3) | AU14: Participación Socios | AV14: =SUMIF($AU$38:$AU$86,$AU14,AV$38:AV$86) -> - | AW14: =SUMIF($AU$38:$AU$86,$AU14,AW$38:AW$86) -> - | AX14: =SUMIF($AU$38:$AU$86,$AU14,AX$38:AX$86) -> - | AY14: =SUMIF($AU$38:$AU$86,$AU14,AY$38:AY$86) -> - | AZ14: =SUMIF($AU$38:$AU$86,$AU14,AZ$38:AZ$86) -> - | BA14: =SUMIF($AU$38:$AU$86,$AU14,BA$38:BA$86) -> - | BB14: =SUMIF($AU$38:$AU$86,$AU14,BB$38:BB$86) -> - | BC14: =SUMIF($AU$38:$AU$86,$AU14,BC$38:BC$86) -> - | ... BG14: =SUMIF($AU$38:$AU$86,$AU14,BG$38:BG$86) -> - | BH14: =+SUM(AV14:BG14) -> - | BK14: =VLOOKUP(BQ14,$Q$5:$AD$29,14,0) -> - | BL14: =IF((+IFERROR((BK14/$BK$8),0))<=-200%,"-200%",(+IFERROR((BK14/$BK$8),0))) -> 0% | BM14: =VLOOKUP(BQ14,$AF$5:$AS$29,14,0) -> (2.3) | BN14: =IF((+IFERROR((BM14/$BM$8),0))<=-200%,"-200%",(+IFERROR((BM14/$BM$8),0))) -> (0%) | BO14: =VLOOKUP(BQ14,$AU$5:$BH$29,14,0) -> - | BP14: =IF((+IFERROR((BO14/$BO$8),0))<=-200%,"-200%",(+IFERROR((BO14/$BO$8),0))) -> 0% | BQ14: Participación Socios | BR14: =+BO14-BM14 -> 2.3 | BS14: =IF((IFERROR(IF(ABS(BR14/BM14)>=9.99,IF(BR14>0,9.99,-9.99),BR14/ABS(BM14)),IF(BR14=0,0,BR14/ABS(BR14))))<=-200%,"-200%",(IFERROR(IF(ABS(BR14/BM14)>=9.99,IF(BR14>0,9.99,-9.99),BR14/ABS(BM14)),IF(BR14=0,0,BR14/ABS(BR14))))) -> 100% | BT14: =+BO14-BK14 -> - | BU14: =IF((IFERROR(IF(ABS(BT14/BK14)>=9.99,IF(BT14>0,9.99,-9.99),BT14/ABS(BK14)),IF(BT14=0,0,BT14/ABS(BT14))))<=-200%,"-200%",(IFERROR(IF(ABS(BT14/BK14)>=9.99,IF(BT14>0,9.99,-9.99),BT14/ABS(BK14)),IF(BT14=0,0,BT14/ABS(BT14))))) -> 0%
B15: Costos Totales | C15: =SUM(C9:C14) -> (29.1) | D15: =SUM(D9:D14) -> (32.7) | E15: =SUM(E9:E14) -> (35.3) | F15: =SUM(F9:F14) -> (61.3) | G15: =SUM(G9:G14) -> (41.9) | H15: =SUM(H9:H14) -> (60.6) | I15: =SUM(I9:I14) -> (45.3) | J15: =SUM(J9:J14) -> (51.8) | ... O15: =SUM(O9:O14) -> (614.6) | Q15: Costos Totales | R15: =SUM(R9:R14) -> (39.5) | S15: =SUM(S9:S14) -> (41.1) | T15: =SUM(T9:T14) -> (43.8) | U15: =SUM(U9:U14) -> (46.0) | V15: =SUM(V9:V14) -> (48.9) | W15: =SUM(W9:W14) -> (46.9) | X15: =SUM(X9:X14) -> (52.5) | Y15: =SUM(Y9:Y14) -> (53.3) | ... AD15: =SUM(AD9:AD14) -> (596.1) | AF15: Costos Totales | AG15: =SUM(AG9:AG14) -> (16.9) | AH15: =SUM(AH9:AH14) -> (17.1) | AI15: =SUM(AI9:AI14) -> (16.0) | AJ15: =SUM(AJ9:AJ14) -> (20.2) | AK15: =SUM(AK9:AK14) -> (27.0) | AL15: =SUM(AL9:AL14) -> (23.7) | AM15: =SUM(AM9:AM14) -> (20.9) | AN15: =SUM(AN9:AN14) -> (29.7) | ... AS15: =SUM(AS9:AS14) -> (326.7) | AU15: Costos Totales | AV15: =SUM(AV9:AV14) -> #REF! | AW15: =SUM(AW9:AW14) -> #REF! | AX15: =SUM(AX9:AX14) -> #REF! | AY15: =SUM(AY9:AY14) -> #REF! | AZ15: =SUM(AZ9:AZ14) -> (27.5) | BA15: =SUM(BA9:BA14) -> (24.5) | BB15: =SUM(BB9:BB14) -> (20.3) | BC15: =SUM(BC9:BC14) -> (26.4) | ... BH15: =SUM(BH9:BH14) -> #REF! | BK15: =SUM(BK9:BK14) -> (596.1) | BL15: =IF((+IFERROR((BK15/$BK$8),0))<=-200%,"-200%",(+IFERROR((BK15/$BK$8),0))) -> (72%) | BM15: =SUM(BM9:BM14) -> (326.7) | BN15: =IF((+IFERROR((BM15/$BM$8),0))<=-200%,"-200%",(+IFERROR((BM15/$BM$8),0))) -> (58%) | BO15: =SUM(BO9:BO14) -> #REF! | BP15: =IF((+IFERROR((BO15/$BO$8),0))<=-200%,"-200%",(+IFERROR((BO15/$BO$8),0))) -> 0% | BQ15: Costos Totales | BR15: =+BO15-BM15 -> #REF! | BS15: =IF((IFERROR(IF(ABS(BR15/BM15)>=9.99,IF(BR15>0,9.99,-9.99),BR15/ABS(BM15)),IF(BR15=0,0,BR15/ABS(BR15))))<=-200%,"-200%",(IFERROR(IF(ABS(BR15/BM15)>=9.99,IF(BR15>0,9.99,-9.99),BR15/ABS(BM15)),IF(BR15=0,0,BR15/ABS(BR15))))) -> #REF! | BT15: =+BO15-BK15 -> #REF! | BU15: =IF((IFERROR(IF(ABS(BT15/BK15)>=9.99,IF(BT15>0,9.99,-9.99),BT15/ABS(BK15)),IF(BT15=0,0,BT15/ABS(BT15))))<=-200%,"-200%",(IFERROR(IF(ABS(BT15/BK15)>=9.99,IF(BT15>0,9.99,-9.99),BT15/ABS(BK15)),IF(BT15=0,0,BT15/ABS(BT15))))) -> #REF!
B16: Contribución Bruta | C16: =C8+C15 -> 10.0 | D16: =D8+D15 -> 10.6 | E16: =E8+E15 -> 15.7 | F16: =F8+F15 -> 7.9 | G16: =G8+G15 -> 22.5 | H16: =H8+H15 -> 13.6 | I16: =I8+I15 -> 18.2 | J16: =J8+J15 -> 19.8 | ... O16: =O8+O15 -> 213.1 | Q16: Contribución Bruta | R16: =R8+R15 -> 12.1 | S16: =S8+S15 -> 18.7 | T16: =T8+T15 -> 17.7 | U16: =U8+U15 -> 21.8 | V16: =V8+V15 -> 16.2 | W16: =W8+W15 -> 20.8 | X16: =X8+X15 -> 19.9 | Y16: =Y8+Y15 -> 22.9 | ... AD16: =AD8+AD15 -> 231.6 | AF16: Contribución Bruta | AG16: =AG8+AG15 -> 12.5 | AH16: =AH8+AH15 -> 12.2 | AI16: =AI8+AI15 -> 12.1 | AJ16: =AJ8+AJ15 -> 14.3 | AK16: =AK8+AK15 -> 18.7 | AL16: =AL8+AL15 -> 18.2 | AM16: =AM8+AM15 -> 15.9 | AN16: =AN8+AN15 -> 21.8 | ... AS16: =AS8+AS15 -> 234.0 | AU16: Contribución Bruta | AV16: =AV8+AV15 -> #REF! | AW16: =AW8+AW15 -> #REF! | AX16: =AX8+AX15 -> #REF! | AY16: =AY8+AY15 -> #REF! | AZ16: =AZ8+AZ15 -> 17.9 | BA16: =BA8+BA15 -> 16.7 | BB16: =BB8+BB15 -> 14.1 | BC16: =BC8+BC15 -> 17.8 | ... BH16: =BH8+BH15 -> #REF! | BK16: =BK8+BK15 -> 231.6 | BL16: =IF((+IFERROR((BK16/$BK$8),0))<=-200%,"-200%",(+IFERROR((BK16/$BK$8),0))) -> 28% | BM16: =BM8+BM15 -> 234.0 | BN16: =IF((+IFERROR((BM16/$BM$8),0))<=-200%,"-200%",(+IFERROR((BM16/$BM$8),0))) -> 42% | BO16: =BO8+BO15 -> #REF! | BP16: =IF((+IFERROR((BO16/$BO$8),0))<=-200%,"-200%",(+IFERROR((BO16/$BO$8),0))) -> 0% | BQ16: Contribución Bruta | BR16: =+BO16-BM16 -> #REF! | BS16: =IF((IFERROR(IF(ABS(BR16/BM16)>=9.99,IF(BR16>0,9.99,-9.99),BR16/ABS(BM16)),IF(BR16=0,0,BR16/ABS(BR16))))<=-200%,"-200%",(IFERROR(IF(ABS(BR16/BM16)>=9.99,IF(BR16>0,9.99,-9.99),BR16/ABS(BM16)),IF(BR16=0,0,BR16/ABS(BR16))))) -> #REF! | BT16: =+BO16-BK16 -> #REF! | BU16: =IF((IFERROR(IF(ABS(BT16/BK16)>=9.99,IF(BT16>0,9.99,-9.99),BT16/ABS(BK16)),IF(BT16=0,0,BT16/ABS(BT16))))<=-200%,"-200%",(IFERROR(IF(ABS(BT16/BK16)>=9.99,IF(BT16>0,9.99,-9.99),BT16/ABS(BK16)),IF(BT16=0,0,BT16/ABS(BT16))))) -> #REF!
B17: Personal | C17: =SUMIF($B$38:$B$86,$B17,C$38:C$86) -> (3.5) | D17: =SUMIF($B$38:$B$86,$B17,D$38:D$86) -> (3.1) | E17: =SUMIF($B$38:$B$86,$B17,E$38:E$86) -> (3.6) | F17: =SUMIF($B$38:$B$86,$B17,F$38:F$86) -> (3.4) | G17: =SUMIF($B$38:$B$86,$B17,G$38:G$86) -> (3.5) | H17: =SUMIF($B$38:$B$86,$B17,H$38:H$86) -> (3.8) | I17: =SUMIF($B$38:$B$86,$B17,I$38:I$86) -> (3.6) | J17: =SUMIF($B$38:$B$86,$B17,J$38:J$86) -> (3.8) | ... N17: =SUMIF($B$38:$B$86,$B17,N$38:N$86) -> (4.4) | O17: =+SUM(C17:N17) -> (44.8) | Q17: Personal | R17: =SUMIF($Q$38:$Q$86,$Q17,R$38:R$86) -> (4.6) | S17: =SUMIF($Q$38:$Q$86,$Q17,S$38:S$86) -> (4.5) | T17: =SUMIF($Q$38:$Q$86,$Q17,T$38:T$86) -> (4.5) | U17: =SUMIF($Q$38:$Q$86,$Q17,U$38:U$86) -> (4.7) | V17: =SUMIF($Q$38:$Q$86,$Q17,V$38:V$86) -> (4.5) | W17: =SUMIF($Q$38:$Q$86,$Q17,W$38:W$86) -> (4.8) | X17: =SUMIF($Q$38:$Q$86,$Q17,X$38:X$86) -> (4.5) | Y17: =SUMIF($Q$38:$Q$86,$Q17,Y$38:Y$86) -> (4.7) | ... AC17: =SUMIF($Q$38:$Q$86,$Q17,AC$38:AC$86) -> (5.0) | AD17: =+SUM(R17:AC17) -> (57.4) | AF17: Personal | AG17: =SUMIF($AF$38:$AF$86,$AF17,AG$38:AG$86) -> (5.0) | AH17: =SUMIF($AF$38:$AF$86,$AF17,AH$38:AH$86) -> (4.6) | AI17: =SUMIF($AF$38:$AF$86,$AF17,AI$38:AI$86) -> (4.7) | AJ17: =SUMIF($AF$38:$AF$86,$AF17,AJ$38:AJ$86) -> (4.6) | AK17: =SUMIF($AF$38:$AF$86,$AF17,AK$38:AK$86) -> (4.6) | AL17: =SUMIF($AF$38:$AF$86,$AF17,AL$38:AL$86) -> (4.6) | AM17: =SUMIF($AF$38:$AF$86,$AF17,AM$38:AM$86) -> (4.6) | AN17: =SUMIF($AF$38:$AF$86,$AF17,AN$38:AN$86) -> (4.6) | ... AR17: =SUMIF($AF$38:$AF$86,$AF17,AR$38:AR$86) -> (4.6) | AS17: =+SUM(AG17:AR17) -> (55.9) | AU17: Personal | AV17: =SUMIF($AU$38:$AU$86,$AU17,AV$38:AV$86) -> #REF! | AW17: =SUMIF($AU$38:$AU$86,$AU17,AW$38:AW$86) -> #REF! | AX17: =SUMIF($AU$38:$AU$86,$AU17,AX$38:AX$86) -> #REF! | AY17: =SUMIF($AU$38:$AU$86,$AU17,AY$38:AY$86) -> #REF! | AZ17: =SUMIF($AU$38:$AU$86,$AU17,AZ$38:AZ$86) -> (4.3) | BA17: =SUMIF($AU$38:$AU$86,$AU17,BA$38:BA$86) -> (4.3) | BB17: =SUMIF($AU$38:$AU$86,$AU17,BB$38:BB$86) -> (4.2) | BC17: =SUMIF($AU$38:$AU$86,$AU17,BC$38:BC$86) -> (4.2) | ... BG17: =SUMIF($AU$38:$AU$86,$AU17,BG$38:BG$86) -> (4.2) | BH17: =+SUM(AV17:BG17) -> #REF! | BK17: =VLOOKUP(BQ17,$Q$5:$AD$29,14,0) -> (57.4) | BL17: =IF((+IFERROR((BK17/$BK$8),0))<=-200%,"-200%",(+IFERROR((BK17/$BK$8),0))) -> (7%) | BM17: =VLOOKUP(BQ17,$AF$5:$AS$29,14,0) -> (55.9) | BN17: =IF((+IFERROR((BM17/$BM$8),0))<=-200%,"-200%",(+IFERROR((BM17/$BM$8),0))) -> (10%) | BO17: =VLOOKUP(BQ17,$AU$5:$BH$29,14,0) -> #REF! | BP17: =IF((+IFERROR((BO17/$BO$8),0))<=-200%,"-200%",(+IFERROR((BO17/$BO$8),0))) -> 0% | BQ17: Personal | BR17: =+BO17-BM17 -> #REF! | BS17: =IF((IFERROR(IF(ABS(BR17/BM17)>=9.99,IF(BR17>0,9.99,-9.99),BR17/ABS(BM17)),IF(BR17=0,0,BR17/ABS(BR17))))<=-200%,"-200%",(IFERROR(IF(ABS(BR17/BM17)>=9.99,IF(BR17>0,9.99,-9.99),BR17/ABS(BM17)),IF(BR17=0,0,BR17/ABS(BR17))))) -> #REF! | BT17: =+BO17-BK17 -> #REF! | BU17: =IF((IFERROR(IF(ABS(BT17/BK17)>=9.99,IF(BT17>0,9.99,-9.99),BT17/ABS(BK17)),IF(BT17=0,0,BT17/ABS(BT17))))<=-200%,"-200%",(IFERROR(IF(ABS(BT17/BK17)>=9.99,IF(BT17>0,9.99,-9.99),BT17/ABS(BK17)),IF(BT17=0,0,BT17/ABS(BT17))))) -> #REF!
B18: Gastos UX/UI | C18: =SUMIF($B$38:$B$86,$B18,C$38:C$86) -> (0.2) | D18: =SUMIF($B$38:$B$86,$B18,D$38:D$86) -> (0.2) | E18: =SUMIF($B$38:$B$86,$B18,E$38:E$86) -> (0.3) | F18: =SUMIF($B$38:$B$86,$B18,F$38:F$86) -> (0.3) | G18: =SUMIF($B$38:$B$86,$B18,G$38:G$86) -> (0.2) | H18: =SUMIF($B$38:$B$86,$B18,H$38:H$86) -> (0.2) | I18: =SUMIF($B$38:$B$86,$B18,I$38:I$86) -> (0.2) | J18: =SUMIF($B$38:$B$86,$B18,J$38:J$86) -> (0.2) | ... N18: =SUMIF($B$38:$B$86,$B18,N$38:N$86) -> (0.1) | O18: =+SUM(C18:N18) -> (2.5) | Q18: Gastos UX/UI | R18: =SUMIF($Q$38:$Q$86,$Q18,R$38:R$86) -> (0.3) | S18: =SUMIF($Q$38:$Q$86,$Q18,S$38:S$86) -> (0.2) | T18: =SUMIF($Q$38:$Q$86,$Q18,T$38:T$86) -> (0.3) | U18: =SUMIF($Q$38:$Q$86,$Q18,U$38:U$86) -> (0.2) | V18: =SUMIF($Q$38:$Q$86,$Q18,V$38:V$86) -> (0.3) | W18: =SUMIF($Q$38:$Q$86,$Q18,W$38:W$86) -> (0.2) | X18: =SUMIF($Q$38:$Q$86,$Q18,X$38:X$86) -> (0.2) | Y18: =SUMIF($Q$38:$Q$86,$Q18,Y$38:Y$86) -> (0.3) | ... AC18: =SUMIF($Q$38:$Q$86,$Q18,AC$38:AC$86) -> (0.2) | AD18: =+SUM(R18:AC18) -> (2.9) | AF18: Gastos UX/UI | AG18: =SUMIF($AF$38:$AF$86,$AF18,AG$38:AG$86) -> (0.2) | AH18: =SUMIF($AF$38:$AF$86,$AF18,AH$38:AH$86) -> (0.2) | AI18: =SUMIF($AF$38:$AF$86,$AF18,AI$38:AI$86) -> (0.2) | AJ18: =SUMIF($AF$38:$AF$86,$AF18,AJ$38:AJ$86) -> (0.2) | AK18: =SUMIF($AF$38:$AF$86,$AF18,AK$38:AK$86) -> (0.2) | AL18: =SUMIF($AF$38:$AF$86,$AF18,AL$38:AL$86) -> (0.2) | AM18: =SUMIF($AF$38:$AF$86,$AF18,AM$38:AM$86) -> (0.2) | AN18: =SUMIF($AF$38:$AF$86,$AF18,AN$38:AN$86) -> (0.2) | ... AR18: =SUMIF($AF$38:$AF$86,$AF18,AR$38:AR$86) -> (0.2) | AS18: =+SUM(AG18:AR18) -> (2.8) | AU18: Gastos UX/UI | AV18: =SUMIF($AU$38:$AU$86,$AU18,AV$38:AV$86) -> #REF! | AW18: =SUMIF($AU$38:$AU$86,$AU18,AW$38:AW$86) -> #REF! | AX18: =SUMIF($AU$38:$AU$86,$AU18,AX$38:AX$86) -> #REF! | AY18: =SUMIF($AU$38:$AU$86,$AU18,AY$38:AY$86) -> #REF! | AZ18: =SUMIF($AU$38:$AU$86,$AU18,AZ$38:AZ$86) -> - | BA18: =SUMIF($AU$38:$AU$86,$AU18,BA$38:BA$86) -> - | BB18: =SUMIF($AU$38:$AU$86,$AU18,BB$38:BB$86) -> - | BC18: =SUMIF($AU$38:$AU$86,$AU18,BC$38:BC$86) -> - | ... BG18: =SUMIF($AU$38:$AU$86,$AU18,BG$38:BG$86) -> - | BH18: =+SUM(AV18:BG18) -> #REF! | BK18: =VLOOKUP(BQ18,$Q$5:$AD$29,14,0) -> (2.9) | BL18: =IF((+IFERROR((BK18/$BK$8),0))<=-200%,"-200%",(+IFERROR((BK18/$BK$8),0))) -> (0%) | BM18: =VLOOKUP(BQ18,$AF$5:$AS$29,14,0) -> (2.8) | BN18: =IF((+IFERROR((BM18/$BM$8),0))<=-200%,"-200%",(+IFERROR((BM18/$BM$8),0))) -> (0%) | BO18: =VLOOKUP(BQ18,$AU$5:$BH$29,14,0) -> #REF! | BP18: =IF((+IFERROR((BO18/$BO$8),0))<=-200%,"-200%",(+IFERROR((BO18/$BO$8),0))) -> 0% | BQ18: Gastos UX/UI | BR18: =+BO18-BM18 -> #REF! | BS18: =IF((IFERROR(IF(ABS(BR18/BM18)>=9.99,IF(BR18>0,9.99,-9.99),BR18/ABS(BM18)),IF(BR18=0,0,BR18/ABS(BR18))))<=-200%,"-200%",(IFERROR(IF(ABS(BR18/BM18)>=9.99,IF(BR18>0,9.99,-9.99),BR18/ABS(BM18)),IF(BR18=0,0,BR18/ABS(BR18))))) -> #REF! | BT18: =+BO18-BK18 -> #REF! | BU18: =IF((IFERROR(IF(ABS(BT18/BK18)>=9.99,IF(BT18>0,9.99,-9.99),BT18/ABS(BK18)),IF(BT18=0,0,BT18/ABS(BT18))))<=-200%,"-200%",(IFERROR(IF(ABS(BT18/BK18)>=9.99,IF(BT18>0,9.99,-9.99),BT18/ABS(BK18)),IF(BT18=0,0,BT18/ABS(BT18))))) -> #REF!
B19: Operación | C19: =SUMIF($B$38:$B$86,$B19,C$38:C$86) -> (0.7) | D19: =SUMIF($B$38:$B$86,$B19,D$38:D$86) -> (0.7) | E19: =SUMIF($B$38:$B$86,$B19,E$38:E$86) -> (0.8) | F19: =SUMIF($B$38:$B$86,$B19,F$38:F$86) -> (1.1) | G19: =SUMIF($B$38:$B$86,$B19,G$38:G$86) -> (0.7) | H19: =SUMIF($B$38:$B$86,$B19,H$38:H$86) -> (0.7) | I19: =SUMIF($B$38:$B$86,$B19,I$38:I$86) -> (1.1) | J19: =SUMIF($B$38:$B$86,$B19,J$38:J$86) -> (0.9) | ... N19: =SUMIF($B$38:$B$86,$B19,N$38:N$86) -> (1.6) | O19: =+SUM(C19:N19) -> (12.7) | Q19: Operación | R19: =SUMIF($Q$38:$Q$86,$Q19,R$38:R$86) -> (0.9) | S19: =SUMIF($Q$38:$Q$86,$Q19,S$38:S$86) -> (1.5) | T19: =SUMIF($Q$38:$Q$86,$Q19,T$38:T$86) -> (1.4) | U19: =SUMIF($Q$38:$Q$86,$Q19,U$38:U$86) -> (1.4) | V19: =SUMIF($Q$38:$Q$86,$Q19,V$38:V$86) -> (1.5) | W19: =SUMIF($Q$38:$Q$86,$Q19,W$38:W$86) -> (1.5) | X19: =SUMIF($Q$38:$Q$86,$Q19,X$38:X$86) -> (1.0) | Y19: =SUMIF($Q$38:$Q$86,$Q19,Y$38:Y$86) -> (1.2) | ... AC19: =SUMIF($Q$38:$Q$86,$Q19,AC$38:AC$86) -> (1.0) | AD19: =+SUM(R19:AC19) -> (14.0) | AF19: Operación | AG19: =SUMIF($AF$38:$AF$86,$AF19,AG$38:AG$86) -> (0.7) | AH19: =SUMIF($AF$38:$AF$86,$AF19,AH$38:AH$86) -> (1.2) | AI19: =SUMIF($AF$38:$AF$86,$AF19,AI$38:AI$86) -> (0.2) | AJ19: =SUMIF($AF$38:$AF$86,$AF19,AJ$38:AJ$86) -> (0.5) | AK19: =SUMIF($AF$38:$AF$86,$AF19,AK$38:AK$86) -> (0.5) | AL19: =SUMIF($AF$38:$AF$86,$AF19,AL$38:AL$86) -> (0.5) | AM19: =SUMIF($AF$38:$AF$86,$AF19,AM$38:AM$86) -> (0.3) | AN19: =SUMIF($AF$38:$AF$86,$AF19,AN$38:AN$86) -> (0.4) | ... AR19: =SUMIF($AF$38:$AF$86,$AF19,AR$38:AR$86) -> (0.3) | AS19: =+SUM(AG19:AR19) -> (5.6) | AU19: Operación | AV19: =SUMIF($AU$38:$AU$86,$AU19,AV$38:AV$86) -> #REF! | AW19: =SUMIF($AU$38:$AU$86,$AU19,AW$38:AW$86) -> #REF! | AX19: =SUMIF($AU$38:$AU$86,$AU19,AX$38:AX$86) -> #REF! | AY19: =SUMIF($AU$38:$AU$86,$AU19,AY$38:AY$86) -> #REF! | AZ19: =SUMIF($AU$38:$AU$86,$AU19,AZ$38:AZ$86) -> (0.5) | BA19: =SUMIF($AU$38:$AU$86,$AU19,BA$38:BA$86) -> (0.5) | BB19: =SUMIF($AU$38:$AU$86,$AU19,BB$38:BB$86) -> (0.3) | BC19: =SUMIF($AU$38:$AU$86,$AU19,BC$38:BC$86) -> (0.4) | ... BG19: =SUMIF($AU$38:$AU$86,$AU19,BG$38:BG$86) -> (0.3) | BH19: =+SUM(AV19:BG19) -> #REF! | BK19: =VLOOKUP(BQ19,$Q$5:$AD$29,14,0) -> (14.0) | BL19: =IF((+IFERROR((BK19/$BK$8),0))<=-200%,"-200%",(+IFERROR((BK19/$BK$8),0))) -> (2%) | BM19: =VLOOKUP(BQ19,$AF$5:$AS$29,14,0) -> (5.6) | BN19: =IF((+IFERROR((BM19/$BM$8),0))<=-200%,"-200%",(+IFERROR((BM19/$BM$8),0))) -> (1%) | BO19: =VLOOKUP(BQ19,$AU$5:$BH$29,14,0) -> #REF! | BP19: =IF((+IFERROR((BO19/$BO$8),0))<=-200%,"-200%",(+IFERROR((BO19/$BO$8),0))) -> 0% | BQ19: Operación | BR19: =+BO19-BM19 -> #REF! | BS19: =IF((IFERROR(IF(ABS(BR19/BM19)>=9.99,IF(BR19>0,9.99,-9.99),BR19/ABS(BM19)),IF(BR19=0,0,BR19/ABS(BR19))))<=-200%,"-200%",(IFERROR(IF(ABS(BR19/BM19)>=9.99,IF(BR19>0,9.99,-9.99),BR19/ABS(BM19)),IF(BR19=0,0,BR19/ABS(BR19))))) -> #REF! | BT19: =+BO19-BK19 -> #REF! | BU19: =IF((IFERROR(IF(ABS(BT19/BK19)>=9.99,IF(BT19>0,9.99,-9.99),BT19/ABS(BK19)),IF(BT19=0,0,BT19/ABS(BT19))))<=-200%,"-200%",(IFERROR(IF(ABS(BT19/BK19)>=9.99,IF(BT19>0,9.99,-9.99),BT19/ABS(BK19)),IF(BT19=0,0,BT19/ABS(BT19))))) -> #REF!
B20: Mercadotecnia | C20: =SUMIF($B$38:$B$86,$B20,C$38:C$86) -> - | D20: =SUMIF($B$38:$B$86,$B20,D$38:D$86) -> - | E20: =SUMIF($B$38:$B$86,$B20,E$38:E$86) -> (0.2) | F20: =SUMIF($B$38:$B$86,$B20,F$38:F$86) -> (0.1) | G20: =SUMIF($B$38:$B$86,$B20,G$38:G$86) -> (0.0) | H20: =SUMIF($B$38:$B$86,$B20,H$38:H$86) -> (0.0) | I20: =SUMIF($B$38:$B$86,$B20,I$38:I$86) -> (0.1) | J20: =SUMIF($B$38:$B$86,$B20,J$38:J$86) -> (0.1) | ... N20: =SUMIF($B$38:$B$86,$B20,N$38:N$86) -> (0.0) | O20: =+SUM(C20:N20) -> (0.6) | Q20: Mercadotecnia | R20: =SUMIF($Q$38:$Q$86,$Q20,R$38:R$86) -> (0.2) | S20: =SUMIF($Q$38:$Q$86,$Q20,S$38:S$86) -> (0.3) | T20: =SUMIF($Q$38:$Q$86,$Q20,T$38:T$86) -> (0.3) | U20: =SUMIF($Q$38:$Q$86,$Q20,U$38:U$86) -> (0.3) | V20: =SUMIF($Q$38:$Q$86,$Q20,V$38:V$86) -> (0.1) | W20: =SUMIF($Q$38:$Q$86,$Q20,W$38:W$86) -> (0.1) | X20: =SUMIF($Q$38:$Q$86,$Q20,X$38:X$86) -> (0.1) | Y20: =SUMIF($Q$38:$Q$86,$Q20,Y$38:Y$86) -> (0.2) | ... AC20: =SUMIF($Q$38:$Q$86,$Q20,AC$38:AC$86) -> (0.2) | AD20: =+SUM(R20:AC20) -> (2.2) | AF20: Mercadotecnia | AG20: =SUMIF($AF$38:$AF$86,$AF20,AG$38:AG$86) -> (0.2) | AH20: =SUMIF($AF$38:$AF$86,$AF20,AH$38:AH$86) -> (0.2) | AI20: =SUMIF($AF$38:$AF$86,$AF20,AI$38:AI$86) -> (0.6) | AJ20: =SUMIF($AF$38:$AF$86,$AF20,AJ$38:AJ$86) -> (0.2) | AK20: =SUMIF($AF$38:$AF$86,$AF20,AK$38:AK$86) -> (0.1) | AL20: =SUMIF($AF$38:$AF$86,$AF20,AL$38:AL$86) -> (0.1) | AM20: =SUMIF($AF$38:$AF$86,$AF20,AM$38:AM$86) -> (0.1) | AN20: =SUMIF($AF$38:$AF$86,$AF20,AN$38:AN$86) -> (0.1) | ... AR20: =SUMIF($AF$38:$AF$86,$AF20,AR$38:AR$86) -> (0.1) | AS20: =+SUM(AG20:AR20) -> (2.3) | AU20: Mercadotecnia | AV20: =SUMIF($AU$38:$AU$86,$AU20,AV$38:AV$86) -> (0.1) | AW20: =SUMIF($AU$38:$AU$86,$AU20,AW$38:AW$86) -> (0.1) | AX20: =SUMIF($AU$38:$AU$86,$AU20,AX$38:AX$86) -> (0.1) | AY20: =SUMIF($AU$38:$AU$86,$AU20,AY$38:AY$86) -> (0.1) | AZ20: =SUMIF($AU$38:$AU$86,$AU20,AZ$38:AZ$86) -> (0.1) | BA20: =SUMIF($AU$38:$AU$86,$AU20,BA$38:BA$86) -> (0.1) | BB20: =SUMIF($AU$38:$AU$86,$AU20,BB$38:BB$86) -> (0.1) | BC20: =SUMIF($AU$38:$AU$86,$AU20,BC$38:BC$86) -> (0.1) | ... BG20: =SUMIF($AU$38:$AU$86,$AU20,BG$38:BG$86) -> (0.1) | BH20: =+SUM(AV20:BG20) -> (1.5) | BK20: =VLOOKUP(BQ20,$Q$5:$AD$29,14,0) -> (2.2) | BL20: =IF((+IFERROR((BK20/$BK$8),0))<=-200%,"-200%",(+IFERROR((BK20/$BK$8),0))) -> (0%) | BM20: =VLOOKUP(BQ20,$AF$5:$AS$29,14,0) -> (2.3) | BN20: =IF((+IFERROR((BM20/$BM$8),0))<=-200%,"-200%",(+IFERROR((BM20/$BM$8),0))) -> (0%) | BO20: =VLOOKUP(BQ20,$AU$5:$BH$29,14,0) -> (1.5) | BP20: =IF((+IFERROR((BO20/$BO$8),0))<=-200%,"-200%",(+IFERROR((BO20/$BO$8),0))) -> 0% | BQ20: Mercadotecnia | BR20: =+BO20-BM20 -> 0.9 | BS20: =IF((IFERROR(IF(ABS(BR20/BM20)>=9.99,IF(BR20>0,9.99,-9.99),BR20/ABS(BM20)),IF(BR20=0,0,BR20/ABS(BR20))))<=-200%,"-200%",(IFERROR(IF(ABS(BR20/BM20)>=9.99,IF(BR20>0,9.99,-9.99),BR20/ABS(BM20)),IF(BR20=0,0,BR20/ABS(BR20))))) -> 37% | BT20: =+BO20-BK20 -> 0.7 | BU20: =IF((IFERROR(IF(ABS(BT20/BK20)>=9.99,IF(BT20>0,9.99,-9.99),BT20/ABS(BK20)),IF(BT20=0,0,BT20/ABS(BT20))))<=-200%,"-200%",(IFERROR(IF(ABS(BT20/BK20)>=9.99,IF(BT20>0,9.99,-9.99),BT20/ABS(BK20)),IF(BT20=0,0,BT20/ABS(BT20))))) -> 33%
B21: Mantenimiento de software | C21: =SUMIF($B$38:$B$86,$B21,C$38:C$86) -> (0.3) | D21: =SUMIF($B$38:$B$86,$B21,D$38:D$86) -> (0.3) | E21: =SUMIF($B$38:$B$86,$B21,E$38:E$86) -> (0.3) | F21: =SUMIF($B$38:$B$86,$B21,F$38:F$86) -> (0.3) | G21: =SUMIF($B$38:$B$86,$B21,G$38:G$86) -> (0.3) | H21: =SUMIF($B$38:$B$86,$B21,H$38:H$86) -> (0.3) | I21: =SUMIF($B$38:$B$86,$B21,I$38:I$86) -> (0.3) | J21: =SUMIF($B$38:$B$86,$B21,J$38:J$86) -> (0.3) | ... N21: =SUMIF($B$38:$B$86,$B21,N$38:N$86) -> (0.4) | O21: =+SUM(C21:N21) -> (3.8) | Q21: Mantenimiento de software | R21: =SUMIF($Q$38:$Q$86,$Q21,R$38:R$86) -> (0.3) | S21: =SUMIF($Q$38:$Q$86,$Q21,S$38:S$86) -> (0.3) | T21: =SUMIF($Q$38:$Q$86,$Q21,T$38:T$86) -> (0.3) | U21: =SUMIF($Q$38:$Q$86,$Q21,U$38:U$86) -> (0.3) | V21: =SUMIF($Q$38:$Q$86,$Q21,V$38:V$86) -> (0.3) | W21: =SUMIF($Q$38:$Q$86,$Q21,W$38:W$86) -> (0.2) | X21: =SUMIF($Q$38:$Q$86,$Q21,X$38:X$86) -> (0.3) | Y21: =SUMIF($Q$38:$Q$86,$Q21,Y$38:Y$86) -> (0.3) | ... AC21: =SUMIF($Q$38:$Q$86,$Q21,AC$38:AC$86) -> (0.3) | AD21: =+SUM(R21:AC21) -> (3.1) | AF21: Mantenimiento de software | AG21: =SUMIF($AF$38:$AF$86,$AF21,AG$38:AG$86) -> (0.2) | AH21: =SUMIF($AF$38:$AF$86,$AF21,AH$38:AH$86) -> (0.1) | AI21: =SUMIF($AF$38:$AF$86,$AF21,AI$38:AI$86) -> (0.2) | AJ21: =SUMIF($AF$38:$AF$86,$AF21,AJ$38:AJ$86) -> (0.1) | AK21: =SUMIF($AF$38:$AF$86,$AF21,AK$38:AK$86) -> (0.1) | AL21: =SUMIF($AF$38:$AF$86,$AF21,AL$38:AL$86) -> (0.2) | AM21: =SUMIF($AF$38:$AF$86,$AF21,AM$38:AM$86) -> (0.2) | AN21: =SUMIF($AF$38:$AF$86,$AF21,AN$38:AN$86) -> (0.2) | ... AR21: =SUMIF($AF$38:$AF$86,$AF21,AR$38:AR$86) -> (0.3) | AS21: =+SUM(AG21:AR21) -> (2.4) | AU21: Mantenimiento de software | AV21: =SUMIF($AU$38:$AU$86,$AU21,AV$38:AV$86) -> #REF! | AW21: =SUMIF($AU$38:$AU$86,$AU21,AW$38:AW$86) -> #REF! | AX21: =SUMIF($AU$38:$AU$86,$AU21,AX$38:AX$86) -> #REF! | AY21: =SUMIF($AU$38:$AU$86,$AU21,AY$38:AY$86) -> #REF! | AZ21: =SUMIF($AU$38:$AU$86,$AU21,AZ$38:AZ$86) -> (0.3) | BA21: =SUMIF($AU$38:$AU$86,$AU21,BA$38:BA$86) -> (0.2) | BB21: =SUMIF($AU$38:$AU$86,$AU21,BB$38:BB$86) -> (0.2) | BC21: =SUMIF($AU$38:$AU$86,$AU21,BC$38:BC$86) -> (0.2) | ... BG21: =SUMIF($AU$38:$AU$86,$AU21,BG$38:BG$86) -> (0.2) | BH21: =+SUM(AV21:BG21) -> #REF! | BK21: =VLOOKUP(BQ21,$Q$5:$AD$29,14,0) -> (3.1) | BL21: =IF((+IFERROR((BK21/$BK$8),0))<=-200%,"-200%",(+IFERROR((BK21/$BK$8),0))) -> (0%) | BM21: =VLOOKUP(BQ21,$AF$5:$AS$29,14,0) -> (2.4) | BN21: =IF((+IFERROR((BM21/$BM$8),0))<=-200%,"-200%",(+IFERROR((BM21/$BM$8),0))) -> (0%) | BO21: =VLOOKUP(BQ21,$AU$5:$BH$29,14,0) -> #REF! | BP21: =IF((+IFERROR((BO21/$BO$8),0))<=-200%,"-200%",(+IFERROR((BO21/$BO$8),0))) -> 0% | BQ21: Mantenimiento de software | BR21: =+BO21-BM21 -> #REF! | BS21: =IF((IFERROR(IF(ABS(BR21/BM21)>=9.99,IF(BR21>0,9.99,-9.99),BR21/ABS(BM21)),IF(BR21=0,0,BR21/ABS(BR21))))<=-200%,"-200%",(IFERROR(IF(ABS(BR21/BM21)>=9.99,IF(BR21>0,9.99,-9.99),BR21/ABS(BM21)),IF(BR21=0,0,BR21/ABS(BR21))))) -> #REF! | BT21: =+BO21-BK21 -> #REF! | BU21: =IF((IFERROR(IF(ABS(BT21/BK21)>=9.99,IF(BT21>0,9.99,-9.99),BT21/ABS(BK21)),IF(BT21=0,0,BT21/ABS(BT21))))<=-200%,"-200%",(IFERROR(IF(ABS(BT21/BK21)>=9.99,IF(BT21>0,9.99,-9.99),BT21/ABS(BK21)),IF(BT21=0,0,BT21/ABS(BT21))))) -> #REF!
B22: Staff sistemas | C22: =SUMIF($B$38:$B$86,$B22,C$38:C$86) -> (0.2) | D22: =SUMIF($B$38:$B$86,$B22,D$38:D$86) -> (0.2) | E22: =SUMIF($B$38:$B$86,$B22,E$38:E$86) -> (0.2) | F22: =SUMIF($B$38:$B$86,$B22,F$38:F$86) -> (0.2) | G22: =SUMIF($B$38:$B$86,$B22,G$38:G$86) -> (0.2) | H22: =SUMIF($B$38:$B$86,$B22,H$38:H$86) -> (0.2) | I22: =SUMIF($B$38:$B$86,$B22,I$38:I$86) -> (0.1) | J22: =SUMIF($B$38:$B$86,$B22,J$38:J$86) -> (0.2) | ... N22: =SUMIF($B$38:$B$86,$B22,N$38:N$86) -> (0.1) | O22: =+SUM(C22:N22) -> (2.0) | Q22: Staff sistemas | R22: =SUMIF($Q$38:$Q$86,$Q22,R$38:R$86) -> (0.1) | S22: =SUMIF($Q$38:$Q$86,$Q22,S$38:S$86) -> (0.2) | T22: =SUMIF($Q$38:$Q$86,$Q22,T$38:T$86) -> (0.2) | U22: =SUMIF($Q$38:$Q$86,$Q22,U$38:U$86) -> (0.2) | V22: =SUMIF($Q$38:$Q$86,$Q22,V$38:V$86) -> (0.1) | W22: =SUMIF($Q$38:$Q$86,$Q22,W$38:W$86) -> (0.3) | X22: =SUMIF($Q$38:$Q$86,$Q22,X$38:X$86) -> (0.1) | Y22: =SUMIF($Q$38:$Q$86,$Q22,Y$38:Y$86) -> (0.3) | ... AC22: =SUMIF($Q$38:$Q$86,$Q22,AC$38:AC$86) -> (0.3) | AD22: =+SUM(R22:AC22) -> (2.4) | AF22: Staff sistemas | AG22: =SUMIF($AF$38:$AF$86,$AF22,AG$38:AG$86) -> (0.1) | AH22: =SUMIF($AF$38:$AF$86,$AF22,AH$38:AH$86) -> (0.1) | AI22: =SUMIF($AF$38:$AF$86,$AF22,AI$38:AI$86) -> (0.1) | AJ22: =SUMIF($AF$38:$AF$86,$AF22,AJ$38:AJ$86) -> (0.1) | AK22: =SUMIF($AF$38:$AF$86,$AF22,AK$38:AK$86) -> (0.1) | AL22: =SUMIF($AF$38:$AF$86,$AF22,AL$38:AL$86) -> (0.1) | AM22: =SUMIF($AF$38:$AF$86,$AF22,AM$38:AM$86) -> (0.1) | AN22: =SUMIF($AF$38:$AF$86,$AF22,AN$38:AN$86) -> (0.1) | ... AR22: =SUMIF($AF$38:$AF$86,$AF22,AR$38:AR$86) -> (0.1) | AS22: =+SUM(AG22:AR22) -> (1.2) | AU22: Staff sistemas | AV22: =SUMIF($AU$38:$AU$86,$AU22,AV$38:AV$86) -> #REF! | AW22: =SUMIF($AU$38:$AU$86,$AU22,AW$38:AW$86) -> #REF! | AX22: =SUMIF($AU$38:$AU$86,$AU22,AX$38:AX$86) -> #REF! | AY22: =SUMIF($AU$38:$AU$86,$AU22,AY$38:AY$86) -> #REF! | AZ22: =SUMIF($AU$38:$AU$86,$AU22,AZ$38:AZ$86) -> (0.0) | BA22: =SUMIF($AU$38:$AU$86,$AU22,BA$38:BA$86) -> (0.0) | BB22: =SUMIF($AU$38:$AU$86,$AU22,BB$38:BB$86) -> (0.0) | BC22: =SUMIF($AU$38:$AU$86,$AU22,BC$38:BC$86) -> (0.0) | ... BG22: =SUMIF($AU$38:$AU$86,$AU22,BG$38:BG$86) -> (0.0) | BH22: =+SUM(AV22:BG22) -> #REF! | BK22: =VLOOKUP(BQ22,$Q$5:$AD$29,14,0) -> (2.4) | BL22: =IF((+IFERROR((BK22/$BK$8),0))<=-200%,"-200%",(+IFERROR((BK22/$BK$8),0))) -> (0%) | BM22: =VLOOKUP(BQ22,$AF$5:$AS$29,14,0) -> (1.2) | BN22: =IF((+IFERROR((BM22/$BM$8),0))<=-200%,"-200%",(+IFERROR((BM22/$BM$8),0))) -> (0%) | BO22: =VLOOKUP(BQ22,$AU$5:$BH$29,14,0) -> #REF! | BP22: =IF((+IFERROR((BO22/$BO$8),0))<=-200%,"-200%",(+IFERROR((BO22/$BO$8),0))) -> 0% | BQ22: Staff sistemas | BR22: =+BO22-BM22 -> #REF! | BS22: =IF((IFERROR(IF(ABS(BR22/BM22)>=9.99,IF(BR22>0,9.99,-9.99),BR22/ABS(BM22)),IF(BR22=0,0,BR22/ABS(BR22))))<=-200%,"-200%",(IFERROR(IF(ABS(BR22/BM22)>=9.99,IF(BR22>0,9.99,-9.99),BR22/ABS(BM22)),IF(BR22=0,0,BR22/ABS(BR22))))) -> #REF! | BT22: =+BO22-BK22 -> #REF! | BU22: =IF((IFERROR(IF(ABS(BT22/BK22)>=9.99,IF(BT22>0,9.99,-9.99),BT22/ABS(BK22)),IF(BT22=0,0,BT22/ABS(BT22))))<=-200%,"-200%",(IFERROR(IF(ABS(BT22/BK22)>=9.99,IF(BT22>0,9.99,-9.99),BT22/ABS(BK22)),IF(BT22=0,0,BT22/ABS(BT22))))) -> #REF!
B23: Renta, Luz y Teléfono | C23: =SUMIF($B$38:$B$86,$B23,C$38:C$86) -> (0.5) | D23: =SUMIF($B$38:$B$86,$B23,D$38:D$86) -> (0.5) | E23: =SUMIF($B$38:$B$86,$B23,E$38:E$86) -> (0.5) | F23: =SUMIF($B$38:$B$86,$B23,F$38:F$86) -> (0.4) | G23: =SUMIF($B$38:$B$86,$B23,G$38:G$86) -> (0.4) | H23: =SUMIF($B$38:$B$86,$B23,H$38:H$86) -> (0.4) | I23: =SUMIF($B$38:$B$86,$B23,I$38:I$86) -> (0.4) | J23: =SUMIF($B$38:$B$86,$B23,J$38:J$86) -> (0.4) | ... N23: =SUMIF($B$38:$B$86,$B23,N$38:N$86) -> (0.5) | O23: =+SUM(C23:N23) -> (5.5) | Q23: Renta, Luz y Teléfono | R23: =SUMIF($Q$38:$Q$86,$Q23,R$38:R$86) -> (0.7) | S23: =SUMIF($Q$38:$Q$86,$Q23,S$38:S$86) -> (0.6) | T23: =SUMIF($Q$38:$Q$86,$Q23,T$38:T$86) -> (0.6) | U23: =SUMIF($Q$38:$Q$86,$Q23,U$38:U$86) -> (0.5) | V23: =SUMIF($Q$38:$Q$86,$Q23,V$38:V$86) -> (0.5) | W23: =SUMIF($Q$38:$Q$86,$Q23,W$38:W$86) -> (0.5) | X23: =SUMIF($Q$38:$Q$86,$Q23,X$38:X$86) -> (0.5) | Y23: =SUMIF($Q$38:$Q$86,$Q23,Y$38:Y$86) -> (0.6) | ... AC23: =SUMIF($Q$38:$Q$86,$Q23,AC$38:AC$86) -> (0.6) | AD23: =+SUM(R23:AC23) -> (6.8) | AF23: Renta, Luz y Teléfono | AG23: =SUMIF($AF$38:$AF$86,$AF23,AG$38:AG$86) -> (0.5) | AH23: =SUMIF($AF$38:$AF$86,$AF23,AH$38:AH$86) -> (0.5) | AI23: =SUMIF($AF$38:$AF$86,$AF23,AI$38:AI$86) -> (0.5) | AJ23: =SUMIF($AF$38:$AF$86,$AF23,AJ$38:AJ$86) -> (0.5) | AK23: =SUMIF($AF$38:$AF$86,$AF23,AK$38:AK$86) -> (0.5) | AL23: =SUMIF($AF$38:$AF$86,$AF23,AL$38:AL$86) -> (0.5) | AM23: =SUMIF($AF$38:$AF$86,$AF23,AM$38:AM$86) -> (0.5) | AN23: =SUMIF($AF$38:$AF$86,$AF23,AN$38:AN$86) -> (0.5) | ... AR23: =SUMIF($AF$38:$AF$86,$AF23,AR$38:AR$86) -> (0.5) | AS23: =+SUM(AG23:AR23) -> (5.9) | AU23: Renta, Luz y Teléfono | AV23: =SUMIF($AU$38:$AU$86,$AU23,AV$38:AV$86) -> #REF! | AW23: =SUMIF($AU$38:$AU$86,$AU23,AW$38:AW$86) -> #REF! | AX23: =SUMIF($AU$38:$AU$86,$AU23,AX$38:AX$86) -> #REF! | AY23: =SUMIF($AU$38:$AU$86,$AU23,AY$38:AY$86) -> #REF! | AZ23: =SUMIF($AU$38:$AU$86,$AU23,AZ$38:AZ$86) -> #ERROR! | BA23: =SUMIF($AU$38:$AU$86,$AU23,BA$38:BA$86) -> #ERROR! | BB23: =SUMIF($AU$38:$AU$86,$AU23,BB$38:BB$86) -> #ERROR! | BC23: =SUMIF($AU$38:$AU$86,$AU23,BC$38:BC$86) -> #ERROR! | ... BG23: =SUMIF($AU$38:$AU$86,$AU23,BG$38:BG$86) -> #ERROR! | BH23: =+SUM(AV23:BG23) -> #REF! | BK23: =VLOOKUP(BQ23,$Q$5:$AD$29,14,0) -> (6.8) | BL23: =IF((+IFERROR((BK23/$BK$8),0))<=-200%,"-200%",(+IFERROR((BK23/$BK$8),0))) -> (1%) | BM23: =VLOOKUP(BQ23,$AF$5:$AS$29,14,0) -> (5.9) | BN23: =IF((+IFERROR((BM23/$BM$8),0))<=-200%,"-200%",(+IFERROR((BM23/$BM$8),0))) -> (1%) | BO23: =VLOOKUP(BQ23,$AU$5:$BH$29,14,0) -> #REF! | BP23: =IF((+IFERROR((BO23/$BO$8),0))<=-200%,"-200%",(+IFERROR((BO23/$BO$8),0))) -> 0% | BQ23: Renta, Luz y Teléfono | BR23: =+BO23-BM23 -> #REF! | BS23: =IF((IFERROR(IF(ABS(BR23/BM23)>=9.99,IF(BR23>0,9.99,-9.99),BR23/ABS(BM23)),IF(BR23=0,0,BR23/ABS(BR23))))<=-200%,"-200%",(IFERROR(IF(ABS(BR23/BM23)>=9.99,IF(BR23>0,9.99,-9.99),BR23/ABS(BM23)),IF(BR23=0,0,BR23/ABS(BR23))))) -> #REF! | BT23: =+BO23-BK23 -> #REF! | BU23: =IF((IFERROR(IF(ABS(BT23/BK23)>=9.99,IF(BT23>0,9.99,-9.99),BT23/ABS(BK23)),IF(BT23=0,0,BT23/ABS(BT23))))<=-200%,"-200%",(IFERROR(IF(ABS(BT23/BK23)>=9.99,IF(BT23>0,9.99,-9.99),BT23/ABS(BK23)),IF(BT23=0,0,BT23/ABS(BT23))))) -> #REF!
B24: Gastos de despacho GS | C24: =SUMIF($B$38:$B$86,$B24,C$38:C$86) -> (0.2) | D24: =SUMIF($B$38:$B$86,$B24,D$38:D$86) -> (0.2) | E24: =SUMIF($B$38:$B$86,$B24,E$38:E$86) -> (0.2) | F24: =SUMIF($B$38:$B$86,$B24,F$38:F$86) -> (0.2) | G24: =SUMIF($B$38:$B$86,$B24,G$38:G$86) -> (0.2) | H24: =SUMIF($B$38:$B$86,$B24,H$38:H$86) -> (0.2) | I24: =SUMIF($B$38:$B$86,$B24,I$38:I$86) -> (0.2) | J24: =SUMIF($B$38:$B$86,$B24,J$38:J$86) -> (0.2) | ... N24: =SUMIF($B$38:$B$86,$B24,N$38:N$86) -> (0.2) | O24: =+SUM(C24:N24) -> (2.4) | Q24: Gastos de despacho GS | R24: =SUMIF($Q$38:$Q$86,$Q24,R$38:R$86) -> (0.2) | S24: =SUMIF($Q$38:$Q$86,$Q24,S$38:S$86) -> (0.3) | T24: =SUMIF($Q$38:$Q$86,$Q24,T$38:T$86) -> (0.3) | U24: =SUMIF($Q$38:$Q$86,$Q24,U$38:U$86) -> (0.3) | V24: =SUMIF($Q$38:$Q$86,$Q24,V$38:V$86) -> (0.3) | W24: =SUMIF($Q$38:$Q$86,$Q24,W$38:W$86) -> (0.3) | X24: =SUMIF($Q$38:$Q$86,$Q24,X$38:X$86) -> (0.4) | Y24: =SUMIF($Q$38:$Q$86,$Q24,Y$38:Y$86) -> (0.3) | ... AC24: =SUMIF($Q$38:$Q$86,$Q24,AC$38:AC$86) -> (0.3) | AD24: =+SUM(R24:AC24) -> (4.0) | AF24: Gastos de despacho GS | AG24: =SUMIF($AF$38:$AF$86,$AF24,AG$38:AG$86) -> (0.4) | AH24: =SUMIF($AF$38:$AF$86,$AF24,AH$38:AH$86) -> (0.3) | AI24: =SUMIF($AF$38:$AF$86,$AF24,AI$38:AI$86) -> (0.3) | AJ24: =SUMIF($AF$38:$AF$86,$AF24,AJ$38:AJ$86) -> (0.3) | AK24: =SUMIF($AF$38:$AF$86,$AF24,AK$38:AK$86) -> (0.3) | AL24: =SUMIF($AF$38:$AF$86,$AF24,AL$38:AL$86) -> (0.3) | AM24: =SUMIF($AF$38:$AF$86,$AF24,AM$38:AM$86) -> (0.3) | AN24: =SUMIF($AF$38:$AF$86,$AF24,AN$38:AN$86) -> (0.3) | ... AR24: =SUMIF($AF$38:$AF$86,$AF24,AR$38:AR$86) -> (0.3) | AS24: =+SUM(AG24:AR24) -> (3.8) | AU24: Gastos de despacho GS | AV24: =SUMIF($AU$38:$AU$86,$AU24,AV$38:AV$86) -> #REF! | AW24: =SUMIF($AU$38:$AU$86,$AU24,AW$38:AW$86) -> #REF! | AX24: =SUMIF($AU$38:$AU$86,$AU24,AX$38:AX$86) -> #REF! | AY24: =SUMIF($AU$38:$AU$86,$AU24,AY$38:AY$86) -> #REF! | AZ24: =SUMIF($AU$38:$AU$86,$AU24,AZ$38:AZ$86) -> #ERROR! | BA24: =SUMIF($AU$38:$AU$86,$AU24,BA$38:BA$86) -> #ERROR! | BB24: =SUMIF($AU$38:$AU$86,$AU24,BB$38:BB$86) -> #ERROR! | BC24: =SUMIF($AU$38:$AU$86,$AU24,BC$38:BC$86) -> #ERROR! | ... BG24: =SUMIF($AU$38:$AU$86,$AU24,BG$38:BG$86) -> #ERROR! | BH24: =+SUM(AV24:BG24) -> #REF! | BK24: =VLOOKUP(BQ24,$Q$5:$AD$29,14,0) -> (4.0) | BL24: =IF((+IFERROR((BK24/$BK$8),0))<=-200%,"-200%",(+IFERROR((BK24/$BK$8),0))) -> (0%) | BM24: =VLOOKUP(BQ24,$AF$5:$AS$29,14,0) -> (3.8) | BN24: =IF((+IFERROR((BM24/$BM$8),0))<=-200%,"-200%",(+IFERROR((BM24/$BM$8),0))) -> (1%) | BO24: =VLOOKUP(BQ24,$AU$5:$BH$29,14,0) -> #REF! | BP24: =IF((+IFERROR((BO24/$BO$8),0))<=-200%,"-200%",(+IFERROR((BO24/$BO$8),0))) -> 0% | BQ24: Gastos de despacho GS | BR24: =+BO24-BM24 -> #REF! | BS24: =IF((IFERROR(IF(ABS(BR24/BM24)>=9.99,IF(BR24>0,9.99,-9.99),BR24/ABS(BM24)),IF(BR24=0,0,BR24/ABS(BR24))))<=-200%,"-200%",(IFERROR(IF(ABS(BR24/BM24)>=9.99,IF(BR24>0,9.99,-9.99),BR24/ABS(BM24)),IF(BR24=0,0,BR24/ABS(BR24))))) -> #REF! | BT24: =+BO24-BK24 -> #REF! | BU24: =IF((IFERROR(IF(ABS(BT24/BK24)>=9.99,IF(BT24>0,9.99,-9.99),BT24/ABS(BK24)),IF(BT24=0,0,BT24/ABS(BT24))))<=-200%,"-200%",(IFERROR(IF(ABS(BT24/BK24)>=9.99,IF(BT24>0,9.99,-9.99),BT24/ABS(BK24)),IF(BT24=0,0,BT24/ABS(BT24))))) -> #REF!
B25: Costo de Activo | C25: =SUMIF($B$38:$B$86,$B25,C$38:C$86) -> (0.0) | D25: =SUMIF($B$38:$B$86,$B25,D$38:D$86) -> (0.0) | E25: =SUMIF($B$38:$B$86,$B25,E$38:E$86) -> (0.0) | F25: =SUMIF($B$38:$B$86,$B25,F$38:F$86) -> (0.0) | G25: =SUMIF($B$38:$B$86,$B25,G$38:G$86) -> (0.0) | H25: =SUMIF($B$38:$B$86,$B25,H$38:H$86) -> (0.0) | I25: =SUMIF($B$38:$B$86,$B25,I$38:I$86) -> (0.0) | J25: =SUMIF($B$38:$B$86,$B25,J$38:J$86) -> (0.0) | ... N25: =SUMIF($B$38:$B$86,$B25,N$38:N$86) -> (0.0) | O25: =+SUM(C25:N25) -> (0.1) | Q25: Costo de Activo | R25: =SUMIF($Q$38:$Q$86,$Q25,R$38:R$86) -> (0.0) | S25: =SUMIF($Q$38:$Q$86,$Q25,S$38:S$86) -> (0.0) | T25: =SUMIF($Q$38:$Q$86,$Q25,T$38:T$86) -> (0.0) | U25: =SUMIF($Q$38:$Q$86,$Q25,U$38:U$86) -> (0.0) | V25: =SUMIF($Q$38:$Q$86,$Q25,V$38:V$86) -> (0.0) | W25: =SUMIF($Q$38:$Q$86,$Q25,W$38:W$86) -> (0.0) | X25: =SUMIF($Q$38:$Q$86,$Q25,X$38:X$86) -> (0.0) | Y25: =SUMIF($Q$38:$Q$86,$Q25,Y$38:Y$86) -> (0.0) | ... AC25: =SUMIF($Q$38:$Q$86,$Q25,AC$38:AC$86) -> (0.0) | AD25: =+SUM(R25:AC25) -> (0.0) | AF25: Costo de Activo | AG25: =SUMIF($AF$38:$AF$86,$AF25,AG$38:AG$86) -> (0.0) | AH25: =SUMIF($AF$38:$AF$86,$AF25,AH$38:AH$86) -> (0.0) | AI25: =SUMIF($AF$38:$AF$86,$AF25,AI$38:AI$86) -> (0.0) | AJ25: =SUMIF($AF$38:$AF$86,$AF25,AJ$38:AJ$86) -> (0.0) | AK25: =SUMIF($AF$38:$AF$86,$AF25,AK$38:AK$86) -> (0.0) | AL25: =SUMIF($AF$38:$AF$86,$AF25,AL$38:AL$86) -> (0.0) | AM25: =SUMIF($AF$38:$AF$86,$AF25,AM$38:AM$86) -> (0.0) | AN25: =SUMIF($AF$38:$AF$86,$AF25,AN$38:AN$86) -> (0.0) | ... AR25: =SUMIF($AF$38:$AF$86,$AF25,AR$38:AR$86) -> (0.0) | AS25: =+SUM(AG25:AR25) -> (0.1) | AU25: Costo de Activo | AV25: =SUMIF($AU$38:$AU$86,$AU25,AV$38:AV$86) -> #REF! | AW25: =SUMIF($AU$38:$AU$86,$AU25,AW$38:AW$86) -> #REF! | AX25: =SUMIF($AU$38:$AU$86,$AU25,AX$38:AX$86) -> #REF! | AY25: =SUMIF($AU$38:$AU$86,$AU25,AY$38:AY$86) -> #REF! | AZ25: =SUMIF($AU$38:$AU$86,$AU25,AZ$38:AZ$86) -> (0.0) | BA25: =SUMIF($AU$38:$AU$86,$AU25,BA$38:BA$86) -> (0.0) | BB25: =SUMIF($AU$38:$AU$86,$AU25,BB$38:BB$86) -> (0.0) | BC25: =SUMIF($AU$38:$AU$86,$AU25,BC$38:BC$86) -> (0.0) | ... BG25: =SUMIF($AU$38:$AU$86,$AU25,BG$38:BG$86) -> (0.0) | BH25: =+SUM(AV25:BG25) -> #REF! | BK25: =VLOOKUP(BQ25,$Q$5:$AD$29,14,0) -> (0.0) | BL25: =IF((+IFERROR((BK25/$BK$8),0))<=-200%,"-200%",(+IFERROR((BK25/$BK$8),0))) -> (0%) | BM25: =VLOOKUP(BQ25,$AF$5:$AS$29,14,0) -> (0.1) | BN25: =IF((+IFERROR((BM25/$BM$8),0))<=-200%,"-200%",(+IFERROR((BM25/$BM$8),0))) -> (0%) | BO25: =VLOOKUP(BQ25,$AU$5:$BH$29,14,0) -> #REF! | BP25: =IF((+IFERROR((BO25/$BO$8),0))<=-200%,"-200%",(+IFERROR((BO25/$BO$8),0))) -> 0% | BQ25: Costo de Activo | BR25: =+BO25-BM25 -> #REF! | BS25: =IF((IFERROR(IF(ABS(BR25/BM25)>=9.99,IF(BR25>0,9.99,-9.99),BR25/ABS(BM25)),IF(BR25=0,0,BR25/ABS(BR25))))<=-200%,"-200%",(IFERROR(IF(ABS(BR25/BM25)>=9.99,IF(BR25>0,9.99,-9.99),BR25/ABS(BM25)),IF(BR25=0,0,BR25/ABS(BR25))))) -> #REF! | BT25: =+BO25-BK25 -> #REF! | BU25: =IF((IFERROR(IF(ABS(BT25/BK25)>=9.99,IF(BT25>0,9.99,-9.99),BT25/ABS(BK25)),IF(BT25=0,0,BT25/ABS(BT25))))<=-200%,"-200%",(IFERROR(IF(ABS(BT25/BK25)>=9.99,IF(BT25>0,9.99,-9.99),BT25/ABS(BK25)),IF(BT25=0,0,BT25/ABS(BT25))))) -> #REF!
B26: Gastos Ventas | C26: =SUMIF($B$38:$B$86,$B26,C$38:C$86) -> (0.2) | D26: =SUMIF($B$38:$B$86,$B26,D$38:D$86) -> (0.1) | E26: =SUMIF($B$38:$B$86,$B26,E$38:E$86) -> (0.2) | F26: =SUMIF($B$38:$B$86,$B26,F$38:F$86) -> (0.2) | G26: =SUMIF($B$38:$B$86,$B26,G$38:G$86) -> (0.2) | H26: =SUMIF($B$38:$B$86,$B26,H$38:H$86) -> (0.2) | I26: =SUMIF($B$38:$B$86,$B26,I$38:I$86) -> (0.3) | J26: =SUMIF($B$38:$B$86,$B26,J$38:J$86) -> (0.3) | ... N26: =SUMIF($B$38:$B$86,$B26,N$38:N$86) -> (0.3) | O26: =+SUM(C26:N26) -> (2.8) | Q26: Gastos Ventas | R26: =SUMIF($Q$38:$Q$86,$Q26,R$38:R$86) -> (0.4) | S26: =SUMIF($Q$38:$Q$86,$Q26,S$38:S$86) -> (0.4) | T26: =SUMIF($Q$38:$Q$86,$Q26,T$38:T$86) -> (0.4) | U26: =SUMIF($Q$38:$Q$86,$Q26,U$38:U$86) -> (0.4) | V26: =SUMIF($Q$38:$Q$86,$Q26,V$38:V$86) -> (0.4) | W26: =SUMIF($Q$38:$Q$86,$Q26,W$38:W$86) -> (0.5) | X26: =SUMIF($Q$38:$Q$86,$Q26,X$38:X$86) -> (0.5) | Y26: =SUMIF($Q$38:$Q$86,$Q26,Y$38:Y$86) -> (0.5) | ... AC26: =SUMIF($Q$38:$Q$86,$Q26,AC$38:AC$86) -> (1.0) | AD26: =+SUM(R26:AC26) -> (6.0) | AF26: Gastos Ventas | AG26: =SUMIF($AF$38:$AF$86,$AF26,AG$38:AG$86) -> (0.5) | AH26: =SUMIF($AF$38:$AF$86,$AF26,AH$38:AH$86) -> (0.5) | AI26: =SUMIF($AF$38:$AF$86,$AF26,AI$38:AI$86) -> (0.5) | AJ26: =SUMIF($AF$38:$AF$86,$AF26,AJ$38:AJ$86) -> (0.5) | AK26: =SUMIF($AF$38:$AF$86,$AF26,AK$38:AK$86) -> (0.5) | AL26: =SUMIF($AF$38:$AF$86,$AF26,AL$38:AL$86) -> (0.5) | AM26: =SUMIF($AF$38:$AF$86,$AF26,AM$38:AM$86) -> (0.5) | AN26: =SUMIF($AF$38:$AF$86,$AF26,AN$38:AN$86) -> (0.5) | ... AR26: =SUMIF($AF$38:$AF$86,$AF26,AR$38:AR$86) -> (0.5) | AS26: =+SUM(AG26:AR26) -> (6.1) | AU26: Gastos Ventas | AV26: =SUMIF($AU$38:$AU$86,$AU26,AV$38:AV$86) -> (0.5) | AW26: =SUMIF($AU$38:$AU$86,$AU26,AW$38:AW$86) -> (0.5) | AX26: =SUMIF($AU$38:$AU$86,$AU26,AX$38:AX$86) -> (0.4) | AY26: =SUMIF($AU$38:$AU$86,$AU26,AY$38:AY$86) -> (0.5) | AZ26: =SUMIF($AU$38:$AU$86,$AU26,AZ$38:AZ$86) -> (0.4) | BA26: =SUMIF($AU$38:$AU$86,$AU26,BA$38:BA$86) -> (0.4) | BB26: =SUMIF($AU$38:$AU$86,$AU26,BB$38:BB$86) -> (0.4) | BC26: =SUMIF($AU$38:$AU$86,$AU26,BC$38:BC$86) -> (0.4) | ... BG26: =SUMIF($AU$38:$AU$86,$AU26,BG$38:BG$86) -> (0.4) | BH26: =+SUM(AV26:BG26) -> (5.0) | BK26: =VLOOKUP(BQ26,$Q$5:$AD$29,14,0) -> (6.0) | BL26: =IF((+IFERROR((BK26/$BK$8),0))<=-200%,"-200%",(+IFERROR((BK26/$BK$8),0))) -> (1%) | BM26: =VLOOKUP(BQ26,$AF$5:$AS$29,14,0) -> (6.1) | BN26: =IF((+IFERROR((BM26/$BM$8),0))<=-200%,"-200%",(+IFERROR((BM26/$BM$8),0))) -> (1%) | BO26: =VLOOKUP(BQ26,$AU$5:$BH$29,14,0) -> (5.0) | BP26: =IF((+IFERROR((BO26/$BO$8),0))<=-200%,"-200%",(+IFERROR((BO26/$BO$8),0))) -> 0% | BQ26: Gastos Ventas | BR26: =+BO26-BM26 -> 1.2 | BS26: =IF((IFERROR(IF(ABS(BR26/BM26)>=9.99,IF(BR26>0,9.99,-9.99),BR26/ABS(BM26)),IF(BR26=0,0,BR26/ABS(BR26))))<=-200%,"-200%",(IFERROR(IF(ABS(BR26/BM26)>=9.99,IF(BR26>0,9.99,-9.99),BR26/ABS(BM26)),IF(BR26=0,0,BR26/ABS(BR26))))) -> 19% | BT26: =+BO26-BK26 -> 1.1 | BU26: =IF((IFERROR(IF(ABS(BT26/BK26)>=9.99,IF(BT26>0,9.99,-9.99),BT26/ABS(BK26)),IF(BT26=0,0,BT26/ABS(BT26))))<=-200%,"-200%",(IFERROR(IF(ABS(BT26/BK26)>=9.99,IF(BT26>0,9.99,-9.99),BT26/ABS(BK26)),IF(BT26=0,0,BT26/ABS(BT26))))) -> 18%
B27: Gastos Staff | C27: =SUMIF($B$38:$B$86,$B27,C$38:C$86) -> (2.0) | D27: =SUMIF($B$38:$B$86,$B27,D$38:D$86) -> (2.0) | E27: =SUMIF($B$38:$B$86,$B27,E$38:E$86) -> (2.2) | F27: =SUMIF($B$38:$B$86,$B27,F$38:F$86) -> (2.3) | G27: =SUMIF($B$38:$B$86,$B27,G$38:G$86) -> (2.4) | H27: =SUMIF($B$38:$B$86,$B27,H$38:H$86) -> (2.4) | I27: =SUMIF($B$38:$B$86,$B27,I$38:I$86) -> (2.7) | J27: =SUMIF($B$38:$B$86,$B27,J$38:J$86) -> (2.3) | ... N27: =SUMIF($B$38:$B$86,$B27,N$38:N$86) -> (4.0) | O27: =+SUM(C27:N27) -> (32.1) | Q27: Gastos Staff | R27: =SUMIF($Q$38:$Q$86,$Q27,R$38:R$86) -> (2.3) | S27: =SUMIF($Q$38:$Q$86,$Q27,S$38:S$86) -> (2.3) | T27: =SUMIF($Q$38:$Q$86,$Q27,T$38:T$86) -> (2.5) | U27: =SUMIF($Q$38:$Q$86,$Q27,U$38:U$86) -> (2.7) | V27: =SUMIF($Q$38:$Q$86,$Q27,V$38:V$86) -> (3.0) | W27: =SUMIF($Q$38:$Q$86,$Q27,W$38:W$86) -> (3.1) | X27: =SUMIF($Q$38:$Q$86,$Q27,X$38:X$86) -> (2.9) | Y27: =SUMIF($Q$38:$Q$86,$Q27,Y$38:Y$86) -> (2.9) | ... AC27: =SUMIF($Q$38:$Q$86,$Q27,AC$38:AC$86) -> (3.4) | AD27: =+SUM(R27:AC27) -> (33.7) | AF27: Gastos Staff | AG27: =SUMIF($AF$38:$AF$86,$AF27,AG$38:AG$86) -> (2.2) | AH27: =SUMIF($AF$38:$AF$86,$AF27,AH$38:AH$86) -> (2.3) | AI27: =SUMIF($AF$38:$AF$86,$AF27,AI$38:AI$86) -> (2.5) | AJ27: =SUMIF($AF$38:$AF$86,$AF27,AJ$38:AJ$86) -> (2.4) | AK27: =SUMIF($AF$38:$AF$86,$AF27,AK$38:AK$86) -> (2.5) | AL27: =SUMIF($AF$38:$AF$86,$AF27,AL$38:AL$86) -> (2.6) | AM27: =SUMIF($AF$38:$AF$86,$AF27,AM$38:AM$86) -> (2.5) | AN27: =SUMIF($AF$38:$AF$86,$AF27,AN$38:AN$86) -> (2.5) | ... AR27: =SUMIF($AF$38:$AF$86,$AF27,AR$38:AR$86) -> (2.8) | AS27: =+SUM(AG27:AR27) -> (30.3) | AU27: Gastos Staff | AV27: =SUMIF($AU$38:$AU$86,$AU27,AV$38:AV$86) -> #REF! | AW27: =SUMIF($AU$38:$AU$86,$AU27,AW$38:AW$86) -> #REF! | AX27: =SUMIF($AU$38:$AU$86,$AU27,AX$38:AX$86) -> #REF! | AY27: =SUMIF($AU$38:$AU$86,$AU27,AY$38:AY$86) -> #REF! | AZ27: =SUMIF($AU$38:$AU$86,$AU27,AZ$38:AZ$86) -> (2.5) | BA27: =SUMIF($AU$38:$AU$86,$AU27,BA$38:BA$86) -> (2.6) | BB27: =SUMIF($AU$38:$AU$86,$AU27,BB$38:BB$86) -> (2.5) | BC27: =SUMIF($AU$38:$AU$86,$AU27,BC$38:BC$86) -> (2.5) | ... BG27: =SUMIF($AU$38:$AU$86,$AU27,BG$38:BG$86) -> (2.8) | BH27: =+SUM(AV27:BG27) -> #REF! | BK27: =VLOOKUP(BQ27,$Q$5:$AD$29,14,0) -> (33.7) | BL27: =IF((+IFERROR((BK27/$BK$8),0))<=-200%,"-200%",(+IFERROR((BK27/$BK$8),0))) -> (4%) | BM27: =VLOOKUP(BQ27,$AF$5:$AS$29,14,0) -> (30.3) | BN27: =IF((+IFERROR((BM27/$BM$8),0))<=-200%,"-200%",(+IFERROR((BM27/$BM$8),0))) -> (5%) | BO27: =VLOOKUP(BQ27,$AU$5:$BH$29,14,0) -> #REF! | BP27: =IF((+IFERROR((BO27/$BO$8),0))<=-200%,"-200%",(+IFERROR((BO27/$BO$8),0))) -> 0% | BQ27: Gastos Staff | BR27: =+BO27-BM27 -> #REF! | BS27: =IF((IFERROR(IF(ABS(BR27/BM27)>=9.99,IF(BR27>0,9.99,-9.99),BR27/ABS(BM27)),IF(BR27=0,0,BR27/ABS(BR27))))<=-200%,"-200%",(IFERROR(IF(ABS(BR27/BM27)>=9.99,IF(BR27>0,9.99,-9.99),BR27/ABS(BM27)),IF(BR27=0,0,BR27/ABS(BR27))))) -> #REF! | BT27: =+BO27-BK27 -> #REF! | BU27: =IF((IFERROR(IF(ABS(BT27/BK27)>=9.99,IF(BT27>0,9.99,-9.99),BT27/ABS(BK27)),IF(BT27=0,0,BT27/ABS(BT27))))<=-200%,"-200%",(IFERROR(IF(ABS(BT27/BK27)>=9.99,IF(BT27>0,9.99,-9.99),BT27/ABS(BK27)),IF(BT27=0,0,BT27/ABS(BT27))))) -> #REF!
B28: Total Gastos | C28: =+SUM(C17:C27) -> (7.8) | D28: =+SUM(D17:D27) -> (7.4) | E28: =+SUM(E17:E27) -> (8.4) | F28: =+SUM(F17:F27) -> (8.4) | G28: =+SUM(G17:G27) -> (8.2) | H28: =+SUM(H17:H27) -> (8.6) | I28: =+SUM(I17:I27) -> (9.2) | J28: =+SUM(J17:J27) -> (8.7) | ... O28: =+SUM(O17:O27) -> (109.2) | Q28: Total Gastos | R28: =+SUM(R17:R27) -> (9.9) | S28: =+SUM(S17:S27) -> (10.6) | T28: =+SUM(T17:T27) -> (10.7) | U28: =+SUM(U17:U27) -> (10.9) | V28: =+SUM(V17:V27) -> (11.1) | W28: =+SUM(W17:W27) -> (11.5) | X28: =+SUM(X17:X27) -> (10.6) | Y28: =+SUM(Y17:Y27) -> (11.2) | ... AD28: =+SUM(AD17:AD27) -> (132.6) | AF28: Total Gastos | AG28: =+SUM(AG17:AG27) -> (10.0) | AH28: =+SUM(AH17:AH27) -> (10.0) | AI28: =+SUM(AI17:AI27) -> (9.8) | AJ28: =+SUM(AJ17:AJ27) -> (9.5) | AK28: =+SUM(AK17:AK27) -> (9.4) | AL28: =+SUM(AL17:AL27) -> (9.6) | AM28: =+SUM(AM17:AM27) -> (9.5) | AN28: =+SUM(AN17:AN27) -> (9.5) | ... AS28: =+SUM(AS17:AS27) -> (116.4) | AU28: Total Gastos | AV28: =+SUM(AV17:AV27) -> #REF! | AW28: =+SUM(AW17:AW27) -> #REF! | AX28: =+SUM(AX17:AX27) -> #REF! | AY28: =+SUM(AY17:AY27) -> #REF! | AZ28: =+SUM(AZ17:AZ27) -> #ERROR! | BA28: =+SUM(BA17:BA27) -> #ERROR! | BB28: =+SUM(BB17:BB27) -> #ERROR! | BC28: =+SUM(BC17:BC27) -> #ERROR! | ... BH28: =+SUM(BH17:BH27) -> #REF! | BK28: =+SUM(BK17:BK27) -> (132.6) | BL28: =IF((+IFERROR((BK28/$BK$8),0))<=-200%,"-200%",(+IFERROR((BK28/$BK$8),0))) -> (16%) | BM28: =+SUM(BM17:BM27) -> (116.4) | BN28: =IF((+IFERROR((BM28/$BM$8),0))<=-200%,"-200%",(+IFERROR((BM28/$BM$8),0))) -> (21%) | BO28: =+SUM(BO17:BO27) -> #REF! | BP28: =IF((+IFERROR((BO28/$BO$8),0))<=-200%,"-200%",(+IFERROR((BO28/$BO$8),0))) -> 0% | BQ28: Total Gastos | BR28: =+BO28-BM28 -> #REF! | BS28: =IF((IFERROR(IF(ABS(BR28/BM28)>=9.99,IF(BR28>0,9.99,-9.99),BR28/ABS(BM28)),IF(BR28=0,0,BR28/ABS(BR28))))<=-200%,"-200%",(IFERROR(IF(ABS(BR28/BM28)>=9.99,IF(BR28>0,9.99,-9.99),BR28/ABS(BM28)),IF(BR28=0,0,BR28/ABS(BR28))))) -> #REF! | BT28: =+BO28-BK28 -> #REF! | BU28: =IF((IFERROR(IF(ABS(BT28/BK28)>=9.99,IF(BT28>0,9.99,-9.99),BT28/ABS(BK28)),IF(BT28=0,0,BT28/ABS(BT28))))<=-200%,"-200%",(IFERROR(IF(ABS(BT28/BK28)>=9.99,IF(BT28>0,9.99,-9.99),BT28/ABS(BK28)),IF(BT28=0,0,BT28/ABS(BT28))))) -> #REF!
B29: Contribución Neta $ | C29: =C16+C28 -> 2.3 | D29: =D16+D28 -> 3.2 | E29: =E16+E28 -> 7.2 | F29: =F16+F28 -> (0.4) | G29: =G16+G28 -> 14.3 | H29: =H16+H28 -> 5.0 | I29: =I16+I28 -> 9.0 | J29: =J16+J28 -> 11.1 | ... O29: =O16+O28 -> 103.8 | Q29: Contribución Neta $ | R29: =R16+R28 -> 2.1 | S29: =S16+S28 -> 8.1 | T29: =T16+T28 -> 6.9 | U29: =U16+U28 -> 10.9 | V29: =V16+V28 -> 5.0 | W29: =W16+W28 -> 9.4 | X29: =X16+X28 -> 9.3 | Y29: =Y16+Y28 -> 11.7 | ... AD29: =AD16+AD28 -> 99.0 | AF29: Contribución Neta $ | AG29: =AG16+AG28 -> 2.5 | AH29: =AH16+AH28 -> 2.2 | AI29: =AI16+AI28 -> 2.2 | AJ29: =AJ16+AJ28 -> 4.7 | AK29: =AK16+AK28 -> 9.3 | AL29: =AL16+AL28 -> 8.5 | AM29: =AM16+AM28 -> 6.4 | AN29: =AN16+AN28 -> 12.3 | ... AS29: =AS16+AS28 -> 117.6 | AU29: Contribución Neta $ | AV29: =AV16+AV28 -> #REF! | AW29: =AW16+AW28 -> #REF! | AX29: =AX16+AX28 -> #REF! | AY29: =AY16+AY28 -> #REF! | AZ29: =AZ16+AZ28 -> #ERROR! | BA29: =BA16+BA28 -> #ERROR! | BB29: =BB16+BB28 -> #ERROR! | BC29: =BC16+BC28 -> #ERROR! | ... BH29: =BH16+BH28 -> #REF! | BK29: =BK16+BK28 -> 99.0 | BL29: =IF((+IFERROR((BK29/$BK$8),0))<=-200%,"-200%",(+IFERROR((BK29/$BK$8),0))) -> 12% | BM29: =BM16+BM28 -> 117.6 | BN29: =IF((+IFERROR((BM29/$BM$8),0))<=-200%,"-200%",(+IFERROR((BM29/$BM$8),0))) -> 21.0% | BO29: =BO16+BO28 -> #REF! | BP29: =IF((+IFERROR((BO29/$BO$8),0))<=-200%,"-200%",(+IFERROR((BO29/$BO$8),0))) -> 0.0% | BQ29: Contribución Neta | BR29: =+BO29-BM29 -> #REF! | BS29: =IF((IFERROR(IF(ABS(BR29/BM29)>=9.99,IF(BR29>0,9.99,-9.99),BR29/ABS(BM29)),IF(BR29=0,0,BR29/ABS(BR29))))<=-200%,"-200%",(IFERROR(IF(ABS(BR29/BM29)>=9.99,IF(BR29>0,9.99,-9.99),BR29/ABS(BM29)),IF(BR29=0,0,BR29/ABS(BR29))))) -> #REF! | BT29: =+BO29-BK29 -> #REF! | BU29: =IF((IFERROR(IF(ABS(BT29/BK29)>=9.99,IF(BT29>0,9.99,-9.99),BT29/ABS(BK29)),IF(BT29=0,0,BT29/ABS(BT29))))<=-200%,"-200%",(IFERROR(IF(ABS(BT29/BK29)>=9.99,IF(BT29>0,9.99,-9.99),BT29/ABS(BK29)),IF(BT29=0,0,BT29/ABS(BT29))))) -> #REF!
B31: % Margen | C31: =C29/C8 -> 6% | D31: =D29/D8 -> 7% | E31: =E29/E8 -> 14% | F31: =F29/F8 -> (1%) | G31: =G29/G8 -> 22% | H31: =H29/H8 -> 7% | I31: =I29/I8 -> 14% | J31: =J29/J8 -> 15% | ... O31: =O29/O8 -> 13% | Q31: % Margen | R31: =R29/R8 -> 4% | S31: =S29/S8 -> 13% | T31: =T29/T8 -> 11% | U31: =U29/U8 -> 16% | V31: =V29/V8 -> 8% | W31: =W29/W8 -> 14% | X31: =X29/X8 -> 13% | Y31: =Y29/Y8 -> 15% | ... AD31: =AD29/AD8 -> 12% | AF31: % Margen | AG31: =AG29/AG8 -> 8% | AH31: =AH29/AH8 -> 7% | AI31: =AI29/AI8 -> 8% | AJ31: =AJ29/AJ8 -> 14% | AK31: =AK29/AK8 -> 20% | AL31: =AL29/AL8 -> 20% | AM31: =AM29/AM8 -> 18% | AN31: =AN29/AN8 -> 24% | ... AS31: =AS29/AS8 -> 21% | AU31: % Margen | AV31: =AV29/AV8 -> #REF! | AW31: =AW29/AW8 -> #REF! | AX31: =AX29/AX8 -> #REF! | AY31: =AY29/AY8 -> #REF! | AZ31: =AZ29/AZ8 -> #ERROR! | BA31: =BA29/BA8 -> #ERROR! | BB31: =BB29/BB8 -> #ERROR! | BC31: =BC29/BC8 -> #ERROR! | ... BH31: =BH29/BH8 -> #REF!
O33: =+O56+O84 -> 103.82 | AD33: =+AD56+AD84 -> 98.99 | AS33: =+AS56+AS84 -> 117.60 | BH33: =+BH56+BH84 -> #REF!
N34: CHECK | O34: =+O29-O33 -> 0.00 | AC34: CHECK | AD34: =+AD29-AD33 -> - 0.00 | AR34: CHECK | AS34: =+AS29-AS33 -> - 0.00 | BG34: CHECK | BH34: =+BH29-BH33 -> #REF!
B35: MARKETING UNITED REAL 2024 | Q35: MARKETING UNITED REAL 2025 | AF35: MARKETING UNITED PRESUPUESTO 2026 | AU35: MARKETING UNITED FORECAST 2026
AV37: 2 | AW37: 3 | AX37: 4 | AY37: 5 | AZ37: 6 | BA37: 7 | BB37: 8 | BC37: 9 | BD37: 10 | BE37: 11 | BF37: 12 | BG37: 13
B38: Real 2024 | C38: 45292 | D38: 45323 | E38: 45352 | F38: 45383 | G38: 45413 | H38: 45444 | I38: 45474 | J38: 45505 | K38: 45536 | L38: 45566 | M38: 45597 | N38: 45627 | O38: Total | Q38: Real 2025 | R38: 45658 | S38: 45689 | T38: 45717 | U38: 45748 | V38: 45778 | W38: 45809 | X38: 45839 | Y38: 45870 | Z38: 45901 | AA38: 45931 | AB38: 45962 | AC38: 45992 | AD38: Total | AF38: Presupuesto 2026 | AG38: 46023 | AH38: 46054 | AI38: 46082 | AJ38: 46113 | AK38: 46143 | AL38: 46174 | AM38: 46204 | AN38: 46235 | AO38: 46266 | AP38: 46296 | AQ38: 46327 | AR38: 46357 | AS38: Total | AU38: Forecast 2026 | AV38: 46023 | AW38: 46054 | AX38: 46082 | AY38: 46113 | AZ38: 46143 | BA38: 46174 | BB38: 46204 | BC38: 46235 | BD38: 46266 | BE38: 46296 | BF38: 46327 | BG38: 46357 | BH38: Total
B39: Ingresos Internos | C39: 13.905133 | D39: 20.128183 | E39: 26.694362 | F39: 39.279291 | G39: 34.674105 | H39: 45.60117 | I39: 29.485042 | J39: 40.744091 | K39: 31.496351 | L39: 46.978771 | M39: 70.110273 | N39: 47.992743 | O39: =+SUM(C39:N39) -> 447.1 | Q39: Ingresos Internos | R39: 22.643869 | S39: 28.208033 | T39: 29.083078 | U39: 28.452118 | V39: 28.814173 | W39: 31.90132 | X39: 24.978855 | Y39: 38.062659 | Z39: 42.616382 | AA39: 45.365613 | AB39: 77.95618 | AC39: 66.245772 | AD39: =+SUM(R39:AC39) -> 464.3 | AF39: Ingresos Internos | AG39: 24.12836 | AH39: 23.935514 | AI39: 21.375945 | AJ39: 27.733583 | AK39: 38.235001 | AL39: 33.598168 | AM39: 28.651672 | AN39: 42.118013 | AO39: 41.65958 | AP39: 40.017488 | AQ39: 41.815298 | AR39: 73.255224 | AS39: =+SUM(AG39:AR39) -> 436.5 | AU39: Ingresos Internos | AV39: =VLOOKUP($AU39,'MKT UNITED 26'!$B$4:$O$22,'Mkt United + Troader 26'!AV$37,0) -> 12.4 | AW39: =VLOOKUP($AU39,'MKT UNITED 26'!$B$4:$O$22,'Mkt United + Troader 26'!AW$37,0) -> 29.3 | AX39: =VLOOKUP($AU39,'MKT UNITED 26'!$B$4:$O$22,'Mkt United + Troader 26'!AX$37,0) -> 24.1 | AY39: =VLOOKUP($AU39,'MKT UNITED 26'!$B$4:$O$22,'Mkt United + Troader 26'!AY$37,0) -> 37.7 | AZ39: 37 | BA39: 29 | BB39: 26.224051 | BC39: 39.960082 | BD39: 44.740809 | BE39: 40 | BF39: 75 | BG39: 66 | BH39: =+SUM(AV39:BG39) -> 461.4
B40: Ingresos Externos | C40: 3.3728572 | D40: 3.6802853 | E40: 2.3388693 | F40: 0.45106288 | G40: 1.3019607 | H40: 1.0775386 | I40: 0.1778911 | J40: 0.67767933 | K40: 1.0054299 | L40: 1.2071059 | M40: 1.7599089 | N40: 0.13401321 | O40: =+SUM(C40:N40) -> 17.2 | Q40: Ingresos Externos | R40: 0.4249346 | S40: 0.272071 | T40: 3.2036794 | U40: 2.4794217 | V40: 2.531593 | W40: 1.585664 | X40: 1.6333018 | Y40: 1.1760014 | Z40: 0.662047 | AA40: 0.580231 | AB40: 1.5443169 | AC40: 2.246545 | AD40: =+SUM(R40:AC40) -> 18.3 | AF40: Ingresos Externos | AG40: 1.0035979 | AH40: 1.58533 | AI40: 2.3324669 | AJ40: 2.7162186 | AK40: 3.4036958 | AL40: 2.6425153 | AM40: 3.0059344 | AN40: 4.1537398 | AO40: 6.8141253 | AP40: 10.714125 | AQ40: 13.314125 | AR40: 13.314125 | AS40: =+SUM(AG40:AR40) -> 65.0 | AU40: Ingresos Externos | AV40: =VLOOKUP($AU40,'MKT UNITED 26'!$B$4:$O$22,'Mkt United + Troader 26'!AV$37,0) -> 4.7 | AW40: =VLOOKUP($AU40,'MKT UNITED 26'!$B$4:$O$22,'Mkt United + Troader 26'!AW$37,0) -> 3.0 | AX40: =VLOOKUP($AU40,'MKT UNITED 26'!$B$4:$O$22,'Mkt United + Troader 26'!AX$37,0) -> 0.7 | AY40: =VLOOKUP($AU40,'MKT UNITED 26'!$B$4:$O$22,'Mkt United + Troader 26'!AY$37,0) -> 2.3 | AZ40: 4.5621289 | BA40: 7.766372 | BB40: 4.126372 | BC40: 0.126372 | BD40: 0.126372 | BE40: 3.726372 | BF40: 0.126372 | BG40: 0.126372 | BH40: =+SUM(AV40:BG40) -> 31.3
B41: Total Ingresos | C41: =C39+C40 -> 17.3 | D41: =D39+D40 -> 23.8 | E41: =E40+E39 -> 29.0 | F41: =F40+F39 -> 39.7 | G41: =G40+G39 -> 36.0 | H41: =H40+H39 -> 46.7 | I41: =I40+I39 -> 29.7 | J41: =J40+J39 -> 41.4 | K41: =K40+K39 -> 32.5 | L41: =L40+L39 -> 48.2 | ... O41: =O40+O39 -> 464.3 | Q41: Total Ingresos | R41: =R39+R40 -> 23.1 | S41: =S39+S40 -> 28.5 | T41: =T40+T39 -> 32.3 | U41: =U40+U39 -> 30.9 | V41: =V40+V39 -> 31.3 | W41: =W40+W39 -> 33.5 | X41: =X40+X39 -> 26.6 | Y41: =Y40+Y39 -> 39.2 | Z41: =Z40+Z39 -> 43.3 | AA41: =AA40+AA39 -> 45.9 | ... AD41: =AD40+AD39 -> 482.7 | AF41: Total Ingresos | AG41: =AG39+AG40 -> 25.1 | AH41: =AH39+AH40 -> 25.5 | AI41: =AI40+AI39 -> 23.7 | AJ41: =AJ40+AJ39 -> 30.4 | AK41: =AK40+AK39 -> 41.6 | AL41: =AL40+AL39 -> 36.2 | AM41: =AM40+AM39 -> 31.7 | AN41: =AN40+AN39 -> 46.3 | AO41: =AO40+AO39 -> 48.5 | AP41: =AP40+AP39 -> 50.7 | ... AS41: =AS40+AS39 -> 501.5 | AU41: Total Ingresos | AV41: =AV39+AV40 -> 17.1 | AW41: =AW39+AW40 -> 32.3 | AX41: =AX40+AX39 -> 24.7 | AY41: =AY40+AY39 -> 40.0 | AZ41: =AZ40+AZ39 -> 41.6 | BA41: =BA40+BA39 -> 36.8 | BB41: =BB40+BB39 -> 30.4 | BC41: =BC40+BC39 -> 40.1 | BD41: =BD40+BD39 -> 44.9 | BE41: =BE40+BE39 -> 43.7 | ... BH41: =BH40+BH39 -> 492.7
B42: Activaciones | C42: -10.74433 | D42: -17.355256 | E42: -18.005206 | F42: -37.900332 | G42: -19.039129 | H42: -38.294099 | I42: -17.896271 | J42: -27.326271 | K42: -21.28752 | L42: -34.121782 | M42: -53.477208 | N42: -28.838195 | O42: =+SUM(C42:N42) -> (324.3) | Q42: Activaciones | R42: -15.623309 | S42: -19.2677 | T42: -20.981773 | U42: -18.517456 | V42: -21.491496 | W42: -20.066272 | X42: -17.437937 | Y42: -24.291808 | Z42: -27.329529 | AA42: -29.569436 | AB42: -48.587899 | AC42: -72.900352 | AD42: =+SUM(R42:AC42) -> (336.1) | AF42: Activaciones | AG42: -15.079175 | AH42: -15.312506 | AI42: -14.225047 | AJ42: -18.269881 | AK42: -24.983218 | AL42: -21.74441 | AM42: -18.994564 | AN42: -27.763051 | AO42: -29.084223 | AP42: -30.438968 | AQ42: -33.077654 | AR42: -51.941609 | AS42: =+SUM(AG42:AR42) -> (300.9) | AU42: Activaciones | AV42: =VLOOKUP($AU42,'MKT UNITED 26'!$B$4:$O$22,'Mkt United + Troader 26'!AV$37,0) -> (11.4) | AW42: =VLOOKUP($AU42,'MKT UNITED 26'!$B$4:$O$22,'Mkt United + Troader 26'!AW$37,0) -> (19.4) | AX42: =VLOOKUP($AU42,'MKT UNITED 26'!$B$4:$O$22,'Mkt United + Troader 26'!AX$37,0) -> (15.6) | AY42: =VLOOKUP($AU42,'MKT UNITED 26'!$B$4:$O$22,'Mkt United + Troader 26'!AY$37,0) -> (24.5) | AZ42: -26.184141 | BA42: -23.162814 | BB42: -19.120766 | BC42: -25.254466 | BD42: -28.266324 | BE42: -27.547614 | BF42: -47.329614 | BG42: -41.659614 | BH42: =+SUM(AV42:BG42) -> (309.4)
B43: Comisiones | C43: -0.01478727 | D43: 0 | E43: -0.10061592 | F43: -0.117463 | G43: -0.015577 | H43: -0.03940326 | I43: -0.00769 | J43: -0.00441909 | K43: 0 | L43: 0 | M43: 0 | N43: 0 | O43: =+SUM(C43:N43) -> (0.3) | Q43: Comisiones | R43: 0 | S43: 0 | T43: -0.108584 | U43: -0.03939952 | V43: -0.01 | W43: -0.01 | X43: -0.00999999 | Y43: -0.001 | Z43: -0.17125075 | AA43: -0.02015062 | AB43: -0.02483109 | AC43: -0.0503862 | AD43: =+SUM(R43:AC43) -> (0.4) | AF43: Comisiones | AG43: -0.051592962 | AH43: -0.081498644 | AI43: -0.11990746 | AJ43: -0.13963536 | AK43: -0.17497719 | AL43: -0.13584643 | AM43: -0.15452907 | AN43: -0.21353546 | AO43: -0.35030056 | AP43: -0.55079176 | AQ43: -0.68445256 | AR43: -0.68445256 | AS43: =+SUM(AG43:AR43) -> (3.3) | AU43: Comisiones | AV43: =VLOOKUP($AU43,'MKT UNITED 26'!$B$4:$O$22,'Mkt United + Troader 26'!AV$37,0) -> (0.0) | AW43: =VLOOKUP($AU43,'MKT UNITED 26'!$B$4:$O$22,'Mkt United + Troader 26'!AW$37,0) -> (0.0) | AX43: =VLOOKUP($AU43,'MKT UNITED 26'!$B$4:$O$22,'Mkt United + Troader 26'!AX$37,0) -> (0.0) | AY43: =VLOOKUP($AU43,'MKT UNITED 26'!$B$4:$O$22,'Mkt United + Troader 26'!AY$37,0) -> (0.0) | AZ43: -0.20196 | BA43: -0.23765098 | BB43: -0.12626698 | BC43: -0.0038669832 | BD43: -0.0038669832 | BE43: -0.11402698 | BF43: -0.0038669832 | BG43: -0.0038669832 | BH43: =+SUM(AV43:BG43) -> (0.9)
B44: Participación Socios | C44: 0 | D44: 0 | E44: 0 | F44: 0 | G44: 0 | H44: 0 | I44: 0 | J44: 0 | K44: 0 | L44: 0 | M44: 0 | N44: 0 | O44: =+SUM(C44:N44) -> - | Q44: Participación Socios | R44: 0 | S44: 0 | T44: 0 | U44: 0 | V44: 0 | W44: 0 | X44: 0 | Y44: 0 | Z44: 0 | AA44: 0 | AB44: 0 | AC44: 0 | AD44: =+SUM(R44:AC44) -> - | AF44: Participación Socios | AG44: -0.035326647 | AH44: -0.055803615 | AI44: -0.082102834 | AJ44: -0.095610894 | AK44: -0.11981009 | AL44: -0.093016538 | AM44: -0.10580889 | AN44: -0.14621164 | AO44: -0.23985721 | AP44: -0.37713721 | AQ44: -0.46865721 | AR44: -0.46865721 | AS44: =+SUM(AG44:AR44) -> (2.3) | AU44: Participación Socios | AV44: =VLOOKUP($AU44,'MKT UNITED 26'!$B$4:$O$22,'Mkt United + Troader 26'!AV$37,0) -> - | AW44: =VLOOKUP($AU44,'MKT UNITED 26'!$B$4:$O$22,'Mkt United + Troader 26'!AW$37,0) -> - | AX44: =VLOOKUP($AU44,'MKT UNITED 26'!$B$4:$O$22,'Mkt United + Troader 26'!AX$37,0) -> - | AY44: =VLOOKUP($AU44,'MKT UNITED 26'!$B$4:$O$22,'Mkt United + Troader 26'!AY$37,0) -> - | AZ44: 0 | BA44: 0 | BB44: 0 | BC44: 0 | BD44: 0 | BE44: 0 | BF44: 0 | BG44: 0 | BH44: =+SUM(AV44:BG44) -> -
B45: Costos Totales | C45: =SUM(C42:C43) -> (10.8) | D45: =SUM(D42:D43) -> (17.4) | E45: =SUM(E42:E43) -> (18.1) | F45: =SUM(F42:F43) -> (38.0) | G45: =SUM(G42:G43) -> (19.1) | H45: =SUM(H42:H43) -> (38.3) | I45: =SUM(I42:I43) -> (17.9) | J45: =SUM(J42:J43) -> (27.3) | ... O45: =SUM(O42:O43) -> (324.6) | Q45: Costos Totales | R45: =SUM(R42:R43) -> (15.6) | S45: =SUM(S42:S43) -> (19.3) | T45: =SUM(T42:T43) -> (21.1) | U45: =SUM(U42:U43) -> (18.6) | V45: =SUM(V42:V43) -> (21.5) | W45: =SUM(W42:W43) -> (20.1) | X45: =SUM(X42:X43) -> (17.4) | Y45: =SUM(Y42:Y43) -> (24.3) | ... AD45: =SUM(AD42:AD43) -> (336.5) | AF45: Costos Totales | AG45: =SUM(AG42:AG44) -> (15.2) | AH45: =SUM(AH42:AH44) -> (15.4) | AI45: =SUM(AI42:AI44) -> (14.4) | AJ45: =SUM(AJ42:AJ44) -> (18.5) | AK45: =SUM(AK42:AK44) -> (25.3) | AL45: =SUM(AL42:AL44) -> (22.0) | AM45: =SUM(AM42:AM44) -> (19.3) | AN45: =SUM(AN42:AN44) -> (28.1) | ... AS45: =SUM(AS42:AS44) -> (306.5) | AU45: Costos Totales | AV45: =SUM(AV42:AV44) -> (11.4) | AW45: =SUM(AW42:AW44) -> (19.4) | AX45: =SUM(AX42:AX44) -> (15.7) | AY45: =SUM(AY42:AY44) -> (24.6) | AZ45: =SUM(AZ42:AZ44) -> (26.4) | BA45: =SUM(BA42:BA44) -> (23.4) | BB45: =SUM(BB42:BB44) -> (19.2) | BC45: =SUM(BC42:BC44) -> (25.3) | ... BH45: =SUM(BH42:BH44) -> (310.3)
B46: Contribución Bruta | C46: =C41+C45 -> 6.5 | D46: =D41+D45 -> 6.5 | E46: =E41+E45 -> 10.9 | F46: =F41+F45 -> 1.7 | G46: =G41+G45 -> 16.9 | H46: =H41+H45 -> 8.3 | I46: =I41+I45 -> 11.8 | J46: =J41+J45 -> 14.1 | ... O46: =O41+O45 -> 139.7 | Q46: Contribución Bruta | R46: =R41+R45 -> 7.4 | S46: =S41+S45 -> 9.2 | T46: =T41+T45 -> 11.2 | U46: =U41+U45 -> 12.4 | V46: =V41+V45 -> 9.8 | W46: =W41+W45 -> 13.4 | X46: =X41+X45 -> 9.2 | Y46: =Y41+Y45 -> 14.9 | ... AD46: =AD41+AD45 -> 146.2 | AF46: Contribución Bruta | AG46: =AG41+AG45 -> 10.0 | AH46: =AH41+AH45 -> 10.1 | AI46: =AI41+AI45 -> 9.3 | AJ46: =AJ41+AJ45 -> 11.9 | AK46: =AK41+AK45 -> 16.4 | AL46: =AL41+AL45 -> 14.3 | AM46: =AM41+AM45 -> 12.4 | AN46: =AN41+AN45 -> 18.1 | ... AS46: =AS41+AS45 -> 195.0 | AU46: Contribución Bruta | AV46: =AV41+AV45 -> 5.6 | AW46: =AW41+AW45 -> 12.9 | AX46: =AX41+AX45 -> 9.0 | AY46: =AY41+AY45 -> 15.4 | AZ46: =AZ41+AZ45 -> 15.2 | BA46: =BA41+BA45 -> 13.4 | BB46: =BB41+BB45 -> 11.1 | BC46: =BC41+BC45 -> 14.8 | ... BH46: =BH41+BH45 -> 182.4
B47: Personal | C47: -2.296358 | D47: -2.0569823 | E47: -2.3486783 | F47: -2.2244277 | G47: -2.35753 | H47: -2.44557 | I47: -2.3897928 | J47: -2.5236759 | K47: -2.8030143 | L47: -2.8376762 | M47: -3.0023939 | N47: -2.942367 | O47: =+SUM(C47:N47) -> (30.2) | Q47: Personal | R47: -2.9179817 | S47: -3.0693088 | T47: -3.0654749 | U47: -3.1979989 | V47: -3.065671 | W47: -3.247113 | X47: -3.1307781 | Y47: -3.2574269 | Z47: -3.5140876 | AA47: -3.3482371 | AB47: -3.8723525 | AC47: -4.1316957 | AD47: =+SUM(R47:AC47) -> (39.8) | AF47: Personal | AG47: -4.1316957 | AH47: -4.1316957 | AI47: -4.1316957 | AJ47: -4.1316957 | AK47: -4.1316957 | AL47: -4.1316957 | AM47: -4.1316957 | AN47: -4.1316957 | AO47: -4.1316957 | AP47: -4.1316957 | AQ47: -4.1316957 | AR47: -4.1316957 | AS47: =+SUM(AG47:AR47) -> (49.6) | AU47: Personal | AV47: =VLOOKUP($AU47,'MKT UNITED 26'!$B$4:$O$22,'Mkt United + Troader 26'!AV$37,0) -> (3.9) | AW47: =VLOOKUP($AU47,'MKT UNITED 26'!$B$4:$O$22,'Mkt United + Troader 26'!AW$37,0) -> (3.6) | AX47: =VLOOKUP($AU47,'MKT UNITED 26'!$B$4:$O$22,'Mkt United + Troader 26'!AX$37,0) -> (3.9) | AY47: =VLOOKUP($AU47,'MKT UNITED 26'!$B$4:$O$22,'Mkt United + Troader 26'!AY$37,0) -> (3.9) | AZ47: -3.8910686 | BA47: -3.8910686 | BB47: -3.8910686 | BC47: -3.8910686 | BD47: -3.8910686 | BE47: -3.8910686 | BF47: -3.8910686 | BG47: -3.8910686 | BH47: =+SUM(AV47:BG47) -> (46.4)
B48: Operación | C48: -0.15418236 | D48: -0.26743641 | E48: -0.25462354 | F48: -0.32504619 | G48: -0.19070222 | H48: -0.19070222 | I48: -0.25650657 | J48: -0.21124016 | K48: -0.16030741 | L48: -0.24937804 | M48: -0.31482796 | N48: -0.503331 | O48: =+SUM(C48:N48) -> (3.1) | Q48: Operación | R48: -0.05238614 | S48: -0.611535 | T48: -0.56056 | U48: -0.32415381 | V48: -0.70048418 | W48: -0.43238965 | X48: -0.00504263 | Y48: -0.26336602 | Z48: -0.39803395 | AA48: -0.24991186 | AB48: -0.36565492 | AC48: -0.550556 | AD48: =+SUM(R48:AC48) -> (4.5) | AF48: Operación | AG48: -0.667 | AH48: -1.067 | AI48: -0.167 | AJ48: -0.417 | AK48: -0.424 | AL48: -0.41763621 | AM48: -0.267 | AN48: -0.317 | AO48: -0.267 | AP48: -0.267 | AQ48: -0.274 | AR48: -0.267 | AS48: =+SUM(AG48:AR48) -> (4.8) | AU48: Operación | AV48: =VLOOKUP($AU48,'MKT UNITED 26'!$B$4:$O$22,'Mkt United + Troader 26'!AV$37,0) -> (0.5) | AW48: =VLOOKUP($AU48,'MKT UNITED 26'!$B$4:$O$22,'Mkt United + Troader 26'!AW$37,0) -> (0.4) | AX48: =VLOOKUP($AU48,'MKT UNITED 26'!$B$4:$O$22,'Mkt United + Troader 26'!AX$37,0) -> (0.1) | AY48: =VLOOKUP($AU48,'MKT UNITED 26'!$B$4:$O$22,'Mkt United + Troader 26'!AY$37,0) -> (0.2) | AZ48: -0.424 | BA48: -0.41763621 | BB48: -0.267 | BC48: -0.317 | BD48: -0.267 | BE48: -0.267 | BF48: -0.274 | BG48: -0.267 | BH48: =+SUM(AV48:BG48) -> (3.7)
B49: Mercadotecnia | C49: 0 | D49: 0 | E49: -0.15735576 | F49: -0.05 | G49: -0.021 | H49: -0.03 | I49: -0.087541837 | J49: -0.05 | K49: -0.05 | L49: -0.051 | M49: -0.051 | N49: -0.017 | O49: =+SUM(C49:N49) -> (0.6) | Q49: Mercadotecnia | R49: -0.176593 | S49: -0.347 | T49: -0.32491937 | U49: -0.28726233 | V49: -0.12399314 | W49: -0.066 | X49: -0.07 | Y49: -0.241672 | Z49: -0.22256736 | AA49: -0.08156736 | AB49: -0.07 | AC49: -0.16313472 | AD49: =+SUM(R49:AC49) -> (2.2) | AF49: Mercadotecnia | AG49: -0.151769 | AH49: -0.18338 | AI49: -0.59204677 | AJ49: -0.24869 | AK49: -0.13869 | AL49: -0.13869 | AM49: -0.13869 | AN49: -0.13869 | AO49: -0.13869 | AP49: -0.17369 | AQ49: -0.13869 | AR49: -0.13869 | AS49: =+SUM(AG49:AR49) -> (2.3) | AU49: Mercadotecnia | AV49: =VLOOKUP($AU49,'MKT UNITED 26'!$B$4:$O$22,'Mkt United + Troader 26'!AV$37,0) -> (0.1) | AW49: =VLOOKUP($AU49,'MKT UNITED 26'!$B$4:$O$22,'Mkt United + Troader 26'!AW$37,0) -> (0.1) | AX49: =VLOOKUP($AU49,'MKT UNITED 26'!$B$4:$O$22,'Mkt United + Troader 26'!AX$37,0) -> (0.1) | AY49: =VLOOKUP($AU49,'MKT UNITED 26'!$B$4:$O$22,'Mkt United + Troader 26'!AY$37,0) -> (0.1) | AZ49: -0.13869 | BA49: -0.13869 | BB49: -0.13869 | BC49: -0.13869 | BD49: -0.13869 | BE49: -0.17369 | BF49: -0.13869 | BG49: -0.13869 | BH49: =+SUM(AV49:BG49) -> (1.5)
B50: Renta, Luz y Teléfono | C50: -0.19545014 | D50: -0.31151981 | E50: -0.31951802 | F50: -0.227407 | G50: -0.22363572 | H50: -0.22545 | I50: -0.22740618 | J50: -0.22366495 | K50: -0.2235 | L50: -0.2265 | M50: -0.2265 | N50: -0.2265 | O50: =+SUM(C50:N50) -> (2.9) | Q50: Renta, Luz y Teléfono | R50: -0.32817754 | S50: -0.33778506 | T50: -0.2717744 | U50: -0.26889551 | V50: -0.2879567 | W50: -0.271482 | X50: -0.260071 | Y50: -0.31683111 | Z50: -0.31528931 | AA50: -0.31651476 | AB50: -0.314982 | AC50: -0.31602355 | AD50: =+SUM(R50:AC50) -> (3.6) | AF50: Renta, Luz y Teléfono | AG50: -0.3868168 | AH50: -0.36747596 | AI50: -0.36747596 | AJ50: -0.36747596 | AK50: -0.36747596 | AL50: -0.36747596 | AM50: -0.36747596 | AN50: -0.36747596 | AO50: -0.36747596 | AP50: -0.36747596 | AQ50: -0.36747596 | AR50: -0.36747596 | AS50: =+SUM(AG50:AR50) -> (4.4) | AU50: Renta, Luz y Teléfono | AV50: =VLOOKUP($AU50,'MKT UNITED 26'!$B$4:$O$22,'Mkt United + Troader 26'!AV$37,0) -> (0.4) | AW50: =VLOOKUP($AU50,'MKT UNITED 26'!$B$4:$O$22,'Mkt United + Troader 26'!AW$37,0) -> (0.4) | AX50: =VLOOKUP($AU50,'MKT UNITED 26'!$B$4:$O$22,'Mkt United + Troader 26'!AX$37,0) -> (0.4) | AY50: =VLOOKUP($AU50,'MKT UNITED 26'!$B$4:$O$22,'Mkt United + Troader 26'!AY$37,0) -> (0.4) | AZ50: -0.42126174 | BA50: -0.42126174 | BB50: -0.42126174 | BC50: -0.42126174 | BD50: -0.42126174 | BE50: -0.42126174 | BF50: -0.42126174 | BG50: -0.42126174 | BH50: =+SUM(AV50:BG50) -> (5.0)
B51: Gastos de despacho GS | C51: -0.1154297 | D51: -0.1149817 | E51: -0.119788 | F51: -0.131862 | G51: -0.12396005 | H51: -0.12551 | I51: -0.128336 | J51: -0.14051885 | K51: -0.121843 | L51: -0.119325 | M51: -0.119983 | N51: -0.130237 | O51: =+SUM(C51:N51) -> (1.5) | Q51: Gastos de despacho GS | R51: -0.112415 | S51: -0.19004148 | T51: -0.265314 | U51: -0.2131 | V51: -0.220684 | W51: -0.217887 | X51: -0.299068 | Y51: -0.241672 | Z51: -0.22960848 | AA51: -0.22686802 | AB51: -0.27129468 | AC51: -0.2301725 | AD51: =+SUM(R51:AC51) -> (2.7) | AF51: Gastos de despacho GS | AG51: -0.27331933 | AH51: -0.234205 | AI51: -0.20044467 | AJ51: -0.21160668 | AK51: -0.20801397 | AL51: -0.21403749 | AM51: -0.21214275 | AN51: -0.21182125 | AO51: -0.20824344 | AP51: -0.22866781 | AQ51: -0.20767621 | AR51: -0.20767621 | AS51: =+SUM(AG51:AR51) -> (2.6) | AU51: Gastos de despacho GS | AV51: =VLOOKUP($AU51,'MKT UNITED 26'!$B$4:$O$22,'Mkt United + Troader 26'!AV$37,0) -> (0.3) | AW51: =VLOOKUP($AU51,'MKT UNITED 26'!$B$4:$O$22,'Mkt United + Troader 26'!AW$37,0) -> (0.3) | AX51: =VLOOKUP($AU51,'MKT UNITED 26'!$B$4:$O$22,'Mkt United + Troader 26'!AX$37,0) -> (0.3) | AY51: =VLOOKUP($AU51,'MKT UNITED 26'!$B$4:$O$22,'Mkt United + Troader 26'!AY$37,0) -> (0.3) | AZ51: -0.27368624 | BA51: -0.27368624 | BB51: -0.27368624 | BC51: -0.27368624 | BD51: -0.27368624 | BE51: -0.27368624 | BF51: -0.27368624 | BG51: -0.27368624 | BH51: =+SUM(AV51:BG51) -> (3.3)
B52: Costo de Activo | C52: -0.0001591625 | D52: -0.0001591625 | E52: -0.0001605 | F52: -0.0001595 | G52: -0.020161929 | H52: -0.020160093 | I52: -0.019060093 | J52: -0.01905 | K52: -0.001905 | L52: -0.001905 | M52: -0.001903 | N52: -0.001902 | O52: =+SUM(C52:N52) -> (0.1) | Q52: Costo de Activo | R52: -0.0001556625 | S52: -0.0001556625 | T52: -0.000157 | U52: -0.000156 | V52: -0.000146 | W52: -0.000553 | X52: -0.000648 | Y52: -0.000647 | Z52: -0.00068 | AA52: -0.00018 | AB52: -0.0002 | AC52: -0.0002 | AD52: =+SUM(R52:AC52) -> (0.0) | AF52: Costo de Activo | AG52: -0.00016344563 | AH52: -0.00016344563 | AI52: -0.00016485 | AJ52: -0.0001638 | AK52: -0.0001533 | AL52: -0.00016065 | AM52: -0.00067935 | AN52: -0.00067935 | AO52: -0.0021002625 | AP52: -0.029884233 | AQ52: -0.029884233 | AR52: -0.029884233 | AS52: =+SUM(AG52:AR52) -> (0.1) | AU52: Costo de Activo | AV52: =VLOOKUP($AU52,'MKT UNITED 26'!$B$4:$O$22,'Mkt United + Troader 26'!AV$37,0) -> (0.0) | AW52: =VLOOKUP($AU52,'MKT UNITED 26'!$B$4:$O$22,'Mkt United + Troader 26'!AW$37,0) -> (0.0) | AX52: =VLOOKUP($AU52,'MKT UNITED 26'!$B$4:$O$22,'Mkt United + Troader 26'!AX$37,0) -> (0.0) | AY52: =VLOOKUP($AU52,'MKT UNITED 26'!$B$4:$O$22,'Mkt United + Troader 26'!AY$37,0) -> (0.0) | AZ52: -0.0001688 | BA52: -0.0001688 | BB52: -0.0001688 | BC52: -0.0001688 | BD52: -0.0001688 | BE52: -0.0001688 | BF52: -0.0001688 | BG52: -0.0001688 | BH52: =+SUM(AV52:BG52) -> (0.0)
B53: Gastos Ventas | C53: -0.189106 | D53: -0.090165706 | E53: -0.15660253 | F53: -0.19773679 | G53: -0.192954 | H53: -0.2070504 | I53: -0.33485293 | J53: -0.34829167 | K53: -0.2871411 | L53: -0.27746723 | M53: -0.280313 | N53: -0.252433 | O53: =+SUM(C53:N53) -> (2.8) | Q53: Gastos Ventas | R53: -0.43258951 | S53: -0.3879871 | T53: -0.38034272 | U53: -0.358139 | V53: -0.44243435 | W53: -0.496775 | X53: -0.53370306 | Y53: -0.50577813 | Z53: -0.5597212 | AA53: -0.459092 | AB53: -0.51010665 | AC53: -0.96552554 | AD53: =+SUM(R53:AC53) -> (6.0) | AF53: Gastos Ventas | AG53: -0.51010665 | AH53: -0.51010665 | AI53: -0.51010665 | AJ53: -0.51010665 | AK53: -0.51010665 | AL53: -0.51010665 | AM53: -0.51010665 | AN53: -0.51010665 | AO53: -0.51010665 | AP53: -0.51010665 | AQ53: -0.51010665 | AR53: -0.51010665 | AS53: =+SUM(AG53:AR53) -> (6.1) | AU53: Gastos Ventas | AV53: =VLOOKUP($AU53,'MKT UNITED 26'!$B$4:$O$22,'Mkt United + Troader 26'!AV$37,0) -> (0.5) | AW53: =VLOOKUP($AU53,'MKT UNITED 26'!$B$4:$O$22,'Mkt United + Troader 26'!AW$37,0) -> (0.5) | AX53: =VLOOKUP($AU53,'MKT UNITED 26'!$B$4:$O$22,'Mkt United + Troader 26'!AX$37,0) -> (0.4) | AY53: =VLOOKUP($AU53,'MKT UNITED 26'!$B$4:$O$22,'Mkt United + Troader 26'!AY$37,0) -> (0.5) | AZ53: -0.3902149 | BA53: -0.3902149 | BB53: -0.3902149 | BC53: -0.3902149 | BD53: -0.3902149 | BE53: -0.3902149 | BF53: -0.3902149 | BG53: -0.3902149 | BH53: =+SUM(AV53:BG53) -> (5.0)
B54: Gastos Staff | C54: -1.011614 | D54: -1.008367 | E54: -1.086478 | F54: -1.134169 | G54: -1.213996 | H54: -1.22495 | I54: -1.3953415 | J54: -1.1625516 | K54: -1.710564 | L54: -1.590434 | M54: -1.5297635 | N54: -2.009486 | O54: =+SUM(C54:N54) -> (16.1) | Q54: Gastos Staff | R54: -1.188505 | S54: -1.1842202 | T54: -1.2767439 | U54: -1.395286 | V54: -1.5148678 | W54: -1.613472 | X54: -1.4512437 | Y54: -1.4439356 | Z54: -1.3697778 | AA54: -1.6029217 | AB54: -1.461873 | AC54: -1.7437807 | AD54: =+SUM(R54:AC54) -> (17.2) | AF54: Gastos Staff | AG54: -1.3522168 | AH54: -1.4532884 | AI54: -1.4944164 | AJ54: -1.4322186 | AK54: -1.440031 | AL54: -1.4367408 | AM54: -1.476321 | AN54: -1.4611031 | AO54: -1.55573 | AP54: -1.527619 | AQ54: -1.6039685 | AR54: -1.6038162 | AS54: =+SUM(AG54:AR54) -> (17.8) | AU54: Gastos Staff | AV54: =VLOOKUP($AU54,'MKT UNITED 26'!$B$4:$O$22,'Mkt United + Troader 26'!AV$37,0) -> (1.3) | AW54: =VLOOKUP($AU54,'MKT UNITED 26'!$B$4:$O$22,'Mkt United + Troader 26'!AW$37,0) -> (1.5) | AX54: =VLOOKUP($AU54,'MKT UNITED 26'!$B$4:$O$22,'Mkt United + Troader 26'!AX$37,0) -> (1.3) | AY54: =VLOOKUP($AU54,'MKT UNITED 26'!$B$4:$O$22,'Mkt United + Troader 26'!AY$37,0) -> (1.3) | AZ54: -1.440031 | BA54: -1.4367408 | BB54: -1.476321 | BC54: -1.4611031 | BD54: -1.55573 | BE54: -1.527619 | BF54: -1.6039685 | BG54: -1.6038162 | BH54: =+SUM(AV54:BG54) -> (17.5)
B55: Total Gastos | C55: =+SUM(C47:C54) -> (4.0) | D55: =+SUM(D47:D54) -> (3.8) | E55: =+SUM(E47:E54) -> (4.4) | F55: =+SUM(F47:F54) -> (4.3) | G55: =+SUM(G47:G54) -> (4.3) | H55: =+SUM(H47:H54) -> (4.5) | I55: =+SUM(I47:I54) -> (4.8) | J55: =+SUM(J47:J54) -> (4.7) | ... O55: =+SUM(O47:O54) -> (57.2) | Q55: Total Gastos | R55: =+SUM(R47:R54) -> (5.2) | S55: =+SUM(S47:S54) -> (6.1) | T55: =+SUM(T47:T54) -> (6.1) | U55: =+SUM(U47:U54) -> (6.0) | V55: =+SUM(V47:V54) -> (6.4) | W55: =+SUM(W47:W54) -> (6.3) | X55: =+SUM(X47:X54) -> (5.8) | Y55: =+SUM(Y47:Y54) -> (6.3) | ... AD55: =+SUM(AD47:AD54) -> (76.1) | AF55: Total Gastos | AG55: =+SUM(AG47:AG54) -> (7.5) | AH55: =+SUM(AH47:AH54) -> (7.9) | AI55: =+SUM(AI47:AI54) -> (7.5) | AJ55: =+SUM(AJ47:AJ54) -> (7.3) | AK55: =+SUM(AK47:AK54) -> (7.2) | AL55: =+SUM(AL47:AL54) -> (7.2) | AM55: =+SUM(AM47:AM54) -> (7.1) | AN55: =+SUM(AN47:AN54) -> (7.1) | ... AS55: =+SUM(AS47:AS54) -> (87.8) | AU55: Total Gastos | AV55: =+SUM(AV47:AV54) -> (7.0) | AW55: =+SUM(AW47:AW54) -> (6.7) | AX55: =+SUM(AX47:AX54) -> (6.5) | AY55: =+SUM(AY47:AY54) -> (6.7) | AZ55: =+SUM(AZ47:AZ54) -> (7.0) | BA55: =+SUM(BA47:BA54) -> (7.0) | BB55: =+SUM(BB47:BB54) -> (6.9) | BC55: =+SUM(BC47:BC54) -> (6.9) | ... BH55: =+SUM(BH47:BH54) -> (82.4)
B56: Contribución Neta $ | C56: =C46+C55 -> 2.6 | D56: =D46+D55 -> 2.6 | E56: =E46+E55 -> 6.5 | F56: =F46+F55 -> (2.6) | G56: =G46+G55 -> 12.6 | H56: =H46+H55 -> 3.9 | I56: =I46+I55 -> 6.9 | J56: =J46+J55 -> 9.4 | ... O56: =O46+O55 -> 82.5 | Q56: Contribución Neta $ | R56: =R46+R55 -> 2.2 | S56: =S46+S55 -> 3.1 | T56: =T46+T55 -> 5.1 | U56: =U46+U55 -> 6.3 | V56: =V46+V55 -> 3.5 | W56: =W46+W55 -> 7.1 | X56: =X46+X55 -> 3.4 | Y56: =Y46+Y55 -> 8.7 | ... AD56: =AD46+AD55 -> 70.0 | AF56: Contribución Neta $ | AG56: =AG46+AG55 -> 2.5 | AH56: =AH46+AH55 -> 2.1 | AI56: =AI46+AI55 -> 1.8 | AJ56: =AJ46+AJ55 -> 4.6 | AK56: =AK46+AK55 -> 9.1 | AL56: =AL46+AL55 -> 7.1 | AM56: =AM46+AM55 -> 5.3 | AN56: =AN46+AN55 -> 11.0 | ... AS56: =AS46+AS55 -> 107.2 | AU56: Contribución Neta $ | AV56: =AV46+AV55 -> (1.4) | AW56: =AW46+AW55 -> 6.2 | AX56: =AX46+AX55 -> 2.6 | AY56: =AY46+AY55 -> 8.8 | AZ56: =AZ46+AZ55 -> 8.2 | BA56: =BA46+BA55 -> 6.4 | BB56: =BB46+BB55 -> 4.2 | BC56: =BC46+BC55 -> 7.9 | ... BH56: =BH46+BH55 -> 100.0
B58: % Margen | C58: =C56/C41 -> 15% | D58: =D56/D41 -> 11% | E58: =E56/E41 -> 22% | F58: =F56/F41 -> (6%) | G58: =G56/G41 -> 35% | H58: =H56/H41 -> 8% | I58: =I56/I41 -> 23% | J58: =J56/J41 -> 23% | ... O58: =O56/O41 -> 18% | Q58: % Margen | R58: =R56/R41 -> 10% | S58: =S56/S41 -> 11% | T58: =T56/T41 -> 16% | U58: =U56/U41 -> 20% | V58: =V56/V41 -> 11% | W58: =W56/W41 -> 21% | X58: =X56/X41 -> 13% | Y58: =Y56/Y41 -> 22% | ... AD58: =AD56/AD41 -> 15% | AF58: % Margen | AG58: =AG56/AG41 -> 10% | AH58: =AH56/AH41 -> 8% | AI58: =AI56/AI41 -> 8% | AJ58: =AJ56/AJ41 -> 15% | AK58: =AK56/AK41 -> 22% | AL58: =AL56/AL41 -> 19% | AM58: =AM56/AM41 -> 17% | AN58: =AN56/AN41 -> 24% | ... AS58: =AS56/AS41 -> 21% | AU58: % Margen | AV58: =AV56/AV41 -> (8%) | AW58: =AW56/AW41 -> 19% | AX58: =AX56/AX41 -> 10% | AY58: =AY56/AY41 -> 22% | AZ58: =AZ56/AZ41 -> 20% | BA58: =BA56/BA41 -> 17% | BB58: =BB56/BB41 -> 14% | BC58: =BC56/BC41 -> 20% | ... BH58: =BH56/BH41 -> 20%
B62: TROADER REAL 2024 | Q62: TROADER REAL 2025 | AF62: TROADER PRESUPUESTO 2026 | AU62: TROADER FORECAST 2026
AV64: 2 | AW64: 3 | AX64: 4 | AY64: 5 | AZ64: 6 | BA64: 7 | BB64: 8 | BC64: 9 | BD64: 10 | BE64: 11 | BF64: 12 | BG64: 13
B65: Real 2024 | C65: 45292 | D65: 45323 | E65: 45352 | F65: 45383 | G65: 45413 | H65: 45444 | I65: 45474 | J65: 45505 | K65: 45536 | L65: 45566 | M65: 45597 | N65: 45627 | O65: Total | Q65: Real 2025 | R65: 45658 | S65: 45689 | T65: 45717 | U65: 45748 | V65: 45778 | W65: 45809 | X65: 45839 | Y65: 45870 | Z65: 45901 | AA65: 45931 | AB65: 45962 | AC65: 45992 | AD65: Total | AF65: Presupuesto 2026 | AG65: 46023 | AH65: 46054 | AI65: 46082 | AJ65: 46113 | AK65: 46143 | AL65: 46174 | AM65: 46204 | AN65: 46235 | AO65: 46266 | AP65: 46296 | AQ65: 46327 | AR65: 46357 | AS65: Total | AU65: Forecast 2026 | AV65: 46023 | AW65: 46054 | AX65: 46082 | AY65: 46113 | AZ65: 46143 | BA65: 46174 | BB65: 46204 | BC65: 46235 | BD65: 46266 | BE65: 46296 | BF65: 46327 | BG65: 46357 | BH65: Total
B66: Ingresos Internos | C66: 21.909 | D66: 19.463537 | E66: 21.958422 | F66: 29.439877 | G66: 28.386778 | H66: 27.518845 | I66: 33.845138 | J66: 30.119618 | K66: 29.884239 | L66: 37.549446 | M66: 41.632821 | N66: 41.649628 | O66: =+SUM(C66:N66) -> 363.4 | Q66: Ingresos Internos | R66: 28.527082 | S66: 31.329683 | T66: 29.180258 | U66: 36.851586 | V66: 33.683232 | W66: 34.246841 | X66: 45.765097 | Y66: 36.999241 | Z66: 37.794968 | AA66: 17.388948 | AB66: 7.1092413 | AC66: 6.0777001 | AD66: =+SUM(R66:AC66) -> 345.0 | AF66: Ingresos Internos | AG66: 4.325464 | AH66: 3.76318 | AI66: 4.3525872 | AJ66: 4.0251388 | AK66: 4.0251388 | AL66: 4.6800357 | AM66: 4.2870975 | AN66: 4.2870975 | AO66: 5.0074842 | AP66: 4.4966646 | AQ66: 4.4966646 | AR66: 4.7071589 | AS66: =+SUM(AG66:AR66) -> 52.5 | AU66: Ingresos Internos | AV66: =VLOOKUP($AU66,#REF!,'Mkt United + Troader 26'!AV$64,0) -> #REF! | AW66: =VLOOKUP($AU66,#REF!,'Mkt United + Troader 26'!AW$64,0) -> #REF! | AX66: =VLOOKUP($AU66,#REF!,'Mkt United + Troader 26'!AX$64,0) -> #REF! | AY66: =VLOOKUP($AU66,#REF!,'Mkt United + Troader 26'!AY$64,0) -> #REF! | AZ66: 3.8251388 | BA66: 4.4800357 | BB66: 4.0870975 | BC66: 4.0870975 | BD66: 4.2 | BE66: 4.2966646 | BF66: 4.2966646 | BG66: 4.5071589 | BH66: =+SUM(AV66:BG66) -> #REF!
B67: Ingresos Externos | C67: 0 | D67: 0 | E67: 0 | F67: 0 | G67: 0 | H67: 0 | I67: 0 | J67: 0 | K67: 0 | L67: 0 | M67: 0 | N67: 0 | O67: =+SUM(C67:N67) -> - | Q67: Ingresos Externos | R67: 0 | S67: 0 | T67: 0 | U67: 0 | V67: 0 | W67: 0 | X67: 0 | Y67: 0 | Z67: 0 | AA67: 0 | AB67: 0 | AC67: 0 | AD67: =+SUM(R67:AC67) -> - | AF67: Ingresos Externos | AG67: 0 | AH67: 0 | AI67: 0 | AJ67: 0 | AK67: 0 | AL67: 0.9 | AM67: 0.9 | AN67: 0.9 | AO67: 0.9 | AP67: 0.9 | AQ67: 1.2 | AR67: 1 | AS67: =+SUM(AG67:AR67) -> 6.7 | AU67: Ingresos Externos | AV67: =VLOOKUP($AU67,#REF!,'Mkt United + Troader 26'!AV$64,0) -> #REF! | AW67: =VLOOKUP($AU67,#REF!,'Mkt United + Troader 26'!AW$64,0) -> #REF! | AX67: =VLOOKUP($AU67,#REF!,'Mkt United + Troader 26'!AX$64,0) -> #REF! | AY67: =VLOOKUP($AU67,#REF!,'Mkt United + Troader 26'!AY$64,0) -> #REF! | AZ67: 0 | BA67: 0 | BB67: 0 | BC67: 0 | BD67: 0 | BE67: 0.9 | BF67: 1.2 | BG67: 1 | BH67: =+SUM(AV67:BG67) -> #REF!
B68: Total Ingresos | C68: =C66+C67 -> 21.9 | D68: =D66+D67 -> 19.5 | E68: =E66+E67 -> 22.0 | F68: =F66+F67 -> 29.4 | G68: =G66+G67 -> 28.4 | H68: =H66+H67 -> 27.5 | I68: =I66+I67 -> 33.8 | J68: =J66+J67 -> 30.1 | ... O68: =O66+O67 -> 363.4 | Q68: Total Ingresos | R68: =R66+R67 -> 28.5 | S68: =S66+S67 -> 31.3 | T68: =T66+T67 -> 29.2 | U68: =U66+U67 -> 36.9 | V68: =V66+V67 -> 33.7 | W68: =W66+W67 -> 34.2 | X68: =X66+X67 -> 45.8 | Y68: =Y66+Y67 -> 37.0 | ... AD68: =AD66+AD67 -> 345.0 | AF68: Total Ingresos | AG68: =AG66+AG67 -> 4.3 | AH68: =AH66+AH67 -> 3.8 | AI68: =AI67+AI66 -> 4.4 | AJ68: =AJ67+AJ66 -> 4.0 | AK68: =AK67+AK66 -> 4.0 | AL68: =AL67+AL66 -> 5.6 | AM68: =AM67+AM66 -> 5.2 | AN68: =AN67+AN66 -> 5.2 | AO68: =AO67+AO66 -> 5.9 | AP68: =AP67+AP66 -> 5.4 | ... AR68: =AR67+AR66 -> 5.7 | AS68: =+SUM(AG68:AR68) -> 59.2 | AU68: Total Ingresos | AV68: =AV66+AV67 -> #REF! | AW68: =AW66+AW67 -> #REF! | AX68: =AX67+AX66 -> #REF! | AY68: =AY67+AY66 -> #REF! | AZ68: =AZ67+AZ66 -> 3.8 | BA68: =BA67+BA66 -> 4.5 | BB68: =BB67+BB66 -> 4.1 | BC68: =BC67+BC66 -> 4.1 | BD68: =BD67+BD66 -> 4.2 | BE68: =BE67+BE66 -> 5.2 | ... BG68: =BG67+BG66 -> 5.5 | BH68: =+SUM(AV68:BG68) -> #REF!
B69: Costo | C69: -18.058394 | D69: -15.039217 | E69: -16.876343 | F69: -22.922206 | G69: -22.460522 | H69: -21.98152 | I69: -27.070126 | J69: -24.134188 | K69: -22.607415 | L69: -29.051657 | M69: -33.857855 | N69: -32.21916 | O69: =+SUM(C69:N69) -> (286.3) | Q69: Costo | R69: -23.408366 | S69: -21.424154 | T69: -22.273865 | U69: -26.807143 | V69: -26.593165 | W69: -26.07119 | X69: -34.332588 | Y69: -28.256821 | Z69: -29.891004 | AA69: -10.654566 | AB69: -1.2136422 | AC69: -0.93626279 | AD69: =+SUM(R69:AC69) -> (251.9) | AF69: Costo | AG69: -0.75057405 | AH69: -1.3495945 | AI69: -1.2830558 | AJ69: -1.4004773 | AK69: -1.4004773 | AL69: -1.4004773 | AM69: -1.4004773 | AN69: -1.4004773 | AO69: -1.6632779 | AP69: -1.4004766 | AQ69: -1.5632779 | AR69: -1.5632779 | AS69: =+SUM(AG69:AR69) -> (16.6) | AU69: Costo | AV69: =VLOOKUP($AU69,#REF!,'Mkt United + Troader 26'!AV$64,0) -> #REF! | AW69: =VLOOKUP($AU69,#REF!,'Mkt United + Troader 26'!AW$64,0) -> #REF! | AX69: =VLOOKUP($AU69,#REF!,'Mkt United + Troader 26'!AX$64,0) -> #REF! | AY69: =VLOOKUP($AU69,#REF!,'Mkt United + Troader 26'!AY$64,0) -> #REF! | AZ69: -1 | BA69: -1 | BB69: -1 | BC69: -1 | BD69: -1 | BE69: -1 | BF69: -1 | BG69: -1 | BH69: =+SUM(AV69:BG69) -> #REF!
B70: Costo de nube | C70: 0 | D70: 0 | E70: 0 | F70: 0 | G70: 0 | H70: 0 | I70: 0 | J70: 0 | K70: 0 | L70: 0 | M70: 0 | N70: 0 | O70: =+SUM(C70:N70) -> - | Q70: Costo de nube | R70: -0.1747787 | S70: -0.16899334 | T70: -0.16676775 | U70: -0.17117037 | V70: -0.16558897 | W70: -0.161587 | X70: -0.14539197 | Y70: -0.15161362 | Z70: -0.14924677 | AA70: -0.045246287 | AB70: -0.043191252 | AC70: 0 | AD70: =+SUM(R70:AC70) -> (1.5) | AF70: Costo de nube | AG70: -0.098 | AH70: -0.098 | AI70: -0.098 | AJ70: -0.098 | AK70: -0.098 | AL70: -0.098 | AM70: -0.098 | AN70: -0.098 | AO70: -0.098 | AP70: -0.098 | AQ70: -0.098 | AR70: -0.098 | AS70: =+SUM(AG70:AR70) -> (1.2) | AU70: Costo de nube | AV70: =VLOOKUP($AU70,#REF!,'Mkt United + Troader 26'!AV$64,0) -> #REF! | AW70: =VLOOKUP($AU70,#REF!,'Mkt United + Troader 26'!AW$64,0) -> #REF! | AX70: =VLOOKUP($AU70,#REF!,'Mkt United + Troader 26'!AX$64,0) -> #REF! | AY70: =VLOOKUP($AU70,#REF!,'Mkt United + Troader 26'!AY$64,0) -> #REF! | AZ70: -0.098 | BA70: -0.098 | BB70: -0.098 | BC70: -0.098 | BD70: -0.098 | BE70: -0.098 | BF70: -0.098 | BG70: -0.098 | BH70: =+SUM(AV70:BG70) -> #REF!
B71: Desarrollo de software | C71: -0.32174997 | D71: -0.31692538 | E71: -0.32047686 | F71: -0.31523548 | G71: -0.35081466 | H71: -0.33091138 | I71: -0.31459455 | J71: -0.30550546 | K71: -0.28464315 | L71: -0.28479751 | M71: -0.28263346 | N71: -0.28263346 | O71: =+SUM(C71:N71) -> (3.7) | Q71: Desarrollo de software | R71: -0.32624056 | S71: -0.25700129 | T71: -0.26622401 | U71: -0.41797985 | V71: -0.61062941 | W71: -0.59239447 | X71: -0.59239447 | Y71: -0.62989447 | Z71: -0.58234308 | AA71: -0.68299348 | AB71: -0.59270931 | AC71: -0.5927093 | AD71: =+SUM(R71:AC71) -> (6.1) | AF71: Desarrollo de software | AG71: -0.92123325 | AH71: -0.18959371 | AI71: -0.18612818 | AJ71: -0.21132818 | AK71: -0.18612818 | AL71: -0.18612818 | AM71: -0.18612818 | AN71: -0.060149717 | AO71: -0.060149717 | AP71: -0.061987217 | AQ71: -0.060149717 | AR71: -0.060149717 | AS71: =+SUM(AG71:AR71) -> (2.4) | AU71: Desarrollo de software | AV71: =VLOOKUP($AU71,#REF!,'Mkt United + Troader 26'!AV$64,0) -> #REF! | AW71: =VLOOKUP($AU71,#REF!,'Mkt United + Troader 26'!AW$64,0) -> #REF! | AX71: =VLOOKUP($AU71,#REF!,'Mkt United + Troader 26'!AX$64,0) -> #REF! | AY71: =VLOOKUP($AU71,#REF!,'Mkt United + Troader 26'!AY$64,0) -> #REF! | AZ71: 0 | BA71: 0 | BB71: 0 | BC71: 0 | BD71: 0 | BE71: 0 | BF71: 0 | BG71: 0 | BH71: =+SUM(AV71:BG71) -> #REF!
B72: Costos Totales | C72: =SUM(C69:C71) -> (18.4) | D72: =SUM(D69:D71) -> (15.4) | E72: =SUM(E69:E71) -> (17.2) | F72: =SUM(F69:F71) -> (23.2) | G72: =SUM(G69:G71) -> (22.8) | H72: =SUM(H69:H71) -> (22.3) | I72: =SUM(I69:I71) -> (27.4) | J72: =SUM(J69:J71) -> (24.4) | ... O72: =SUM(O69:O71) -> (290.0) | Q72: Costos Totales | R72: =SUM(R69:R71) -> (23.9) | S72: =SUM(S69:S71) -> (21.9) | T72: =SUM(T69:T71) -> (22.7) | U72: =SUM(U69:U71) -> (27.4) | V72: =SUM(V69:V71) -> (27.4) | W72: =SUM(W69:W71) -> (26.8) | X72: =SUM(X69:X71) -> (35.1) | Y72: =SUM(Y69:Y71) -> (29.0) | ... AD72: =SUM(AD69:AD71) -> (259.5) | AF72: Costos Totales | AG72: =SUM(AG69:AG71) -> (1.8) | AH72: =SUM(AH69:AH71) -> (1.6) | AI72: =SUM(AI69:AI71) -> (1.6) | AJ72: =SUM(AJ69:AJ71) -> (1.7) | AK72: =SUM(AK69:AK71) -> (1.7) | AL72: =SUM(AL69:AL71) -> (1.7) | AM72: =SUM(AM69:AM71) -> (1.7) | AN72: =SUM(AN69:AN71) -> (1.6) | ... AS72: =SUM(AS69:AS71) -> (20.1) | AU72: Costos Totales | AV72: =SUM(AV69:AV71) -> #REF! | AW72: =SUM(AW69:AW71) -> #REF! | AX72: =SUM(AX69:AX71) -> #REF! | AY72: =SUM(AY69:AY71) -> #REF! | AZ72: =SUM(AZ69:AZ71) -> (1.1) | BA72: =SUM(BA69:BA71) -> (1.1) | BB72: =SUM(BB69:BB71) -> (1.1) | BC72: =SUM(BC69:BC71) -> (1.1) | ... BH72: =SUM(BH69:BH71) -> #REF!
B73: Contribución Bruta | C73: =C68+C72 -> 3.5 | D73: =D68+D72 -> 4.1 | E73: =E68+E72 -> 4.8 | F73: =F68+F72 -> 6.2 | G73: =G68+G72 -> 5.6 | H73: =H68+H72 -> 5.2 | I73: =I68+I72 -> 6.5 | J73: =J68+J72 -> 5.7 | ... O73: =O68+O72 -> 73.4 | Q73: Contribución Bruta | R73: =R68+R72 -> 4.6 | S73: =S68+S72 -> 9.5 | T73: =T68+T72 -> 6.5 | U73: =U68+U72 -> 9.5 | V73: =V68+V72 -> 6.3 | W73: =W68+W72 -> 7.4 | X73: =X68+X72 -> 10.7 | Y73: =Y68+Y72 -> 8.0 | ... AD73: =AD68+AD72 -> 85.4 | AF73: Contribución Bruta | AG73: =AG68+AG72 -> 2.6 | AH73: =AH68+AH72 -> 2.1 | AI73: =AI68+AI72 -> 2.8 | AJ73: =AJ68+AJ72 -> 2.3 | AK73: =AK68+AK72 -> 2.3 | AL73: =AL68+AL72 -> 3.9 | AM73: =AM68+AM72 -> 3.5 | AN73: =AN68+AN72 -> 3.6 | ... AR73: =AR68+AR72 -> 4.0 | AS73: =+SUM(AG73:AR73) -> 39.0 | AU73: Contribución Bruta | AV73: =AV68+AV72 -> #REF! | AW73: =AW68+AW72 -> #REF! | AX73: =AX68+AX72 -> #REF! | AY73: =AY68+AY72 -> #REF! | AZ73: =AZ68+AZ72 -> 2.7 | BA73: =BA68+BA72 -> 3.4 | BB73: =BB68+BB72 -> 3.0 | BC73: =BC68+BC72 -> 3.0 | ... BG73: =BG68+BG72 -> 4.4 | BH73: =+SUM(AV73:BG73) -> #REF!
B74: Personal | C74: -1.1957537 | D74: -1.0833716 | E74: -1.2478555 | F74: -1.1388973 | G74: -1.0947855 | H74: -1.3489493 | I74: -1.2520936 | J74: -1.2383704 | K74: -1.2443421 | L74: -1.0679293 | M74: -1.1342947 | N74: -1.4785892 | O74: =+SUM(C74:N74) -> (14.5) | Q74: Personal | R74: -1.6670683 | S74: -1.3814871 | T74: -1.4264058 | U74: -1.4809698 | V74: -1.4618985 | W74: -1.5572389 | X74: -1.4191173 | Y74: -1.4364998 | Z74: -1.4630881 | AA74: -2.6070892 | AB74: -0.83129895 | AC74: -0.82778752 | AD74: =+SUM(R74:AC74) -> (17.6) | AF74: Personal | AG74: -0.83734198 | AH74: -0.48961426 | AI74: -0.52555744 | AJ74: -0.4983726 | AK74: -0.4983726 | AL74: -0.4983726 | AM74: -0.4983726 | AN74: -0.4983726 | AO74: -0.4983726 | AP74: -0.4983726 | AQ74: -0.4983726 | AR74: -0.4983726 | AS74: =+SUM(AG74:AR74) -> (6.3) | AU74: Personal | AV74: =VLOOKUP($AU74,#REF!,'Mkt United + Troader 26'!AV$64,0) -> #REF! | AW74: =VLOOKUP($AU74,#REF!,'Mkt United + Troader 26'!AW$64,0) -> #REF! | AX74: =VLOOKUP($AU74,#REF!,'Mkt United + Troader 26'!AX$64,0) -> #REF! | AY74: =VLOOKUP($AU74,#REF!,'Mkt United + Troader 26'!AY$64,0) -> #REF! | AZ74: -0.4563726 | BA74: -0.4563726 | BB74: -0.3423726 | BC74: -0.3423726 | BD74: -0.3423726 | BE74: -0.3423726 | BF74: -0.3423726 | BG74: -0.3423726 | BH74: =+SUM(AV74:BG74) -> #REF!
B75: Gastos UX/UI | C75: -0.23677001 | D75: -0.23790664 | E75: -0.25191862 | F75: -0.25696809 | G75: -0.2334337 | H75: -0.23384185 | I75: -0.22914953 | J75: -0.22398448 | K75: -0.21396891 | L75: -0.12395692 | M75: -0.13334155 | N75: -0.1492277 | O75: =+SUM(C75:N75) -> (2.5) | Q75: Gastos UX/UI | R75: -0.28358194 | S75: -0.24433279 | T75: -0.25230833 | U75: -0.20018719 | V75: -0.29515963 | W75: -0.23247213 | X75: -0.234 | Y75: -0.257 | Z75: -0.19897243 | AA75: -0.212162 | AB75: -0.245268 | AC75: -0.233943 | AD75: =+SUM(R75:AC75) -> (2.9) | AF75: Gastos UX/UI | AG75: -0.23 | AH75: -0.23 | AI75: -0.23 | AJ75: -0.23 | AK75: -0.23 | AL75: -0.23 | AM75: -0.23 | AN75: -0.23 | AO75: -0.23 | AP75: -0.23 | AQ75: -0.23 | AR75: -0.23 | AS75: =+SUM(AG75:AR75) -> (2.8) | AU75: Gastos UX/UI | AV75: =VLOOKUP($AU75,#REF!,'Mkt United + Troader 26'!AV$64,0) -> #REF! | AW75: =VLOOKUP($AU75,#REF!,'Mkt United + Troader 26'!AW$64,0) -> #REF! | AX75: =VLOOKUP($AU75,#REF!,'Mkt United + Troader 26'!AX$64,0) -> #REF! | AY75: =VLOOKUP($AU75,#REF!,'Mkt United + Troader 26'!AY$64,0) -> #REF! | AZ75: 0 | BA75: 0 | BB75: 0 | BC75: 0 | BD75: 0 | BE75: 0 | BF75: 0 | BG75: 0 | BH75: =+SUM(AV75:BG75) -> #REF!
B76: Operación | C76: -0.50543082 | D76: -0.39031144 | E76: -0.58592582 | F76: -0.74147223 | G76: -0.51177546 | H76: -0.52738916 | I76: -0.80287636 | J76: -0.64473394 | K76: -0.93694095 | L76: -1.1432637 | M76: -1.6871243 | N76: -1.1432982 | O76: =+SUM(C76:N76) -> (9.6) | Q76: Operación | R76: -0.79876178 | S76: -0.91522922 | T76: -0.87143817 | U76: -1.1003383 | V76: -0.81097707 | W76: -1.1105972 | X76: -1.0234133 | Y76: -0.90236147 | Z76: -0.57870539 | AA76: -0.45135124 | AB76: -0.47877883 | AC76: -0.46819365 | AD76: =+SUM(R76:AC76) -> (9.5) | AF76: Operación | AG76: -0.03446125 | AH76: -0.09446125 | AI76: -0.06446125 | AJ76: -0.06446125 | AK76: -0.06446125 | AL76: -0.06446125 | AM76: -0.06446125 | AN76: -0.06446125 | AO76: -0.06446125 | AP76: -0.06446125 | AQ76: -0.06446125 | AR76: -0.06446125 | AS76: =+SUM(AG76:AR76) -> (0.8) | AU76: Operación | AV76: =VLOOKUP($AU76,#REF!,'Mkt United + Troader 26'!AV$64,0) -> #REF! | AW76: =VLOOKUP($AU76,#REF!,'Mkt United + Troader 26'!AW$64,0) -> #REF! | AX76: =VLOOKUP($AU76,#REF!,'Mkt United + Troader 26'!AX$64,0) -> #REF! | AY76: =VLOOKUP($AU76,#REF!,'Mkt United + Troader 26'!AY$64,0) -> #REF! | AZ76: -0.06446125 | BA76: -0.06446125 | BB76: -0.06446125 | BC76: -0.06446125 | BD76: -0.06446125 | BE76: -0.06446125 | BF76: -0.06446125 | BG76: -0.06446125 | BH76: =+SUM(AV76:BG76) -> #REF!
B77: Mantenimiento de software | C77: -0.29498808 | D77: -0.29498808 | E77: -0.33095909 | F77: -0.30688717 | G77: -0.29520966 | H77: -0.32093554 | I77: -0.31731624 | J77: -0.26571674 | K77: -0.32501371 | L77: -0.32571674 | M77: -0.32571674 | N77: -0.36292654 | O77: =+SUM(C77:N77) -> (3.8) | Q77: Mantenimiento de software | R77: -0.26245648 | S77: -0.2754743 | T77: -0.26811269 | U77: -0.26245648 | V77: -0.26245648 | W77: -0.15258689 | X77: -0.26245648 | Y77: -0.26689033 | Z77: -0.25069393 | AA77: -0.19307066 | AB77: -0.33949099 | AC77: -0.33949099 | AD77: =+SUM(R77:AC77) -> (3.1) | AF77: Mantenimiento de software | AG77: -0.23278715 | AH77: -0.10060613 | AI77: -0.19560613 | AJ77: -0.10060613 | AK77: -0.10060613 | AL77: -0.19560613 | AM77: -0.19560613 | AN77: -0.19560613 | AO77: -0.29060613 | AP77: -0.29060613 | AQ77: -0.19560613 | AR77: -0.29060613 | AS77: =+SUM(AG77:AR77) -> (2.4) | AU77: Mantenimiento de software | AV77: =VLOOKUP($AU77,#REF!,'Mkt United + Troader 26'!AV$64,0) -> #REF! | AW77: =VLOOKUP($AU77,#REF!,'Mkt United + Troader 26'!AW$64,0) -> #REF! | AX77: =VLOOKUP($AU77,#REF!,'Mkt United + Troader 26'!AX$64,0) -> #REF! | AY77: =VLOOKUP($AU77,#REF!,'Mkt United + Troader 26'!AY$64,0) -> #REF! | AZ77: -0.26821918 | BA77: -0.22668057 | BB77: -0.21652672 | BC77: -0.21671915 | BD77: -0.21671915 | BE77: -0.21855665 | BF77: -0.21671915 | BG77: -0.21671915 | BH77: =+SUM(AV77:BG77) -> #REF!
B78: Staff sistemas | C78: -0.21591546 | D78: -0.21055999 | E78: -0.23298485 | F78: -0.19714638 | G78: -0.17605651 | H78: -0.15143062 | I78: -0.1368007 | J78: -0.17351004 | K78: -0.13560624 | L78: -0.12285157 | M78: -0.1218417 | N78: -0.1218417 | O78: =+SUM(C78:N78) -> (2.0) | Q78: Staff sistemas | R78: -0.10995765 | S78: -0.15212687 | T78: -0.17337146 | U78: -0.19227151 | V78: -0.12264229 | W78: -0.26245648 | X78: -0.13381048 | Y78: -0.26245658 | Z78: -0.26245648 | AA78: -0.25860475 | AB78: -0.19958044 | AC78: -0.27781139 | AD78: =+SUM(R78:AC78) -> (2.4) | AF78: Staff sistemas | AG78: -0.12567112 | AH78: -0.096469389 | AI78: -0.096481511 | AJ78: -0.096481511 | AK78: -0.096481511 | AL78: -0.096481511 | AM78: -0.096481511 | AN78: -0.096481511 | AO78: -0.096481511 | AP78: -0.096481511 | AQ78: -0.096481511 | AR78: -0.096481511 | AS78: =+SUM(AG78:AR78) -> (1.2) | AU78: Staff sistemas | AV78: =VLOOKUP($AU78,#REF!,'Mkt United + Troader 26'!AV$64,0) -> #REF! | AW78: =VLOOKUP($AU78,#REF!,'Mkt United + Troader 26'!AW$64,0) -> #REF! | AX78: =VLOOKUP($AU78,#REF!,'Mkt United + Troader 26'!AX$64,0) -> #REF! | AY78: =VLOOKUP($AU78,#REF!,'Mkt United + Troader 26'!AY$64,0) -> #REF! | AZ78: -0.047099761 | BA78: -0.033558086 | BB78: -0.033547599 | BC78: -0.04880443 | BD78: -0.03636067 | BE78: -0.03636067 | BF78: -0.051066932 | BG78: -0.03636067 | BH78: =+SUM(AV78:BG78) -> #REF! | BI78: original
B79: Renta, Luz y Teléfono | C79: -0.25813331 | D79: -0.20956311 | E79: -0.20331204 | F79: -0.20991149 | G79: -0.21068381 | H79: -0.2149393 | I79: -0.21654286 | J79: -0.21988847 | K79: -0.22195493 | L79: -0.22505802 | M79: -0.22648902 | N79: -0.22702256 | O79: =+SUM(C79:N79) -> (2.6) | Q79: Renta, Luz y Teléfono | R79: -0.32718726 | S79: -0.26531365 | T79: -0.29491715 | U79: -0.23821539 | V79: -0.24979211 | W79: -0.24991961 | X79: -0.25539541 | Y79: -0.26054567 | Z79: -0.24777198 | AA79: -0.26890262 | AB79: -0.25398053 | AC79: -0.28546922 | AD79: =+SUM(R79:AC79) -> (3.2) | AF79: Renta, Luz y Teléfono | AG79: -0.12405386 | AH79: -0.12405386 | AI79: -0.12405386 | AJ79: -0.12405386 | AK79: -0.12405386 | AL79: -0.12405386 | AM79: -0.12405386 | AN79: -0.12405386 | AO79: -0.12405386 | AP79: -0.12405386 | AQ79: -0.12405386 | AR79: -0.12405386 | AS79: =+SUM(AG79:AR79) -> (1.5) | AU79: Renta, Luz y Teléfono | AV79: =VLOOKUP($AU79,#REF!,'Mkt United + Troader 26'!AV$64,0) -> #REF! | AW79: =VLOOKUP($AU79,#REF!,'Mkt United + Troader 26'!AW$64,0) -> #REF! | AX79: =VLOOKUP($AU79,#REF!,'Mkt United + Troader 26'!AX$64,0) -> #REF! | AY79: =VLOOKUP($AU79,#REF!,'Mkt United + Troader 26'!AY$64,0) -> #REF! | AZ79: =+[1]Gastos!G26 -> #ERROR! | BA79: =+[1]Gastos!H26 -> #ERROR! | BB79: =+[1]Gastos!I26 -> #ERROR! | BC79: =+[1]Gastos!J26 -> #ERROR! | BD79: =+[1]Gastos!K26 -> #ERROR! | BE79: =+[1]Gastos!L26 -> #ERROR! | BF79: =+[1]Gastos!M26 -> #ERROR! | BG79: =+[1]Gastos!N26 -> #ERROR! | BH79: =+SUM(AV79:BG79) -> #REF! | BI79: -1.5924209
B80: Gastos de despacho GS | C80: -0.07099123 | D80: -0.0812484 | E80: -0.06527152 | F80: -0.07462717 | G80: -0.0760559 | H80: -0.06686639 | I80: -0.06686639 | J80: -0.08116812 | K80: -0.08716613 | L80: -0.09171255 | M80: -0.08051564 | N80: -0.089636 | O80: =+SUM(C80:N80) -> (0.9) | Q80: Gastos de despacho GS | R80: -0.11797266 | S80: -0.13449559 | T80: -0.07047922 | U80: -0.09 | V80: -0.114095 | W80: -0.10453469 | X80: -0.10527637 | Y80: -0.10527638 | Z80: -0.10819668 | AA80: -0.12694863 | AB80: -0.10812357 | AC80: -0.10400332 | AD80: =+SUM(R80:AC80) -> (1.3) | AF80: Gastos de despacho GS | AG80: -0.090415525 | AH80: -0.091539046 | AI80: -0.094636718 | AJ80: -0.094104608 | AK80: -0.09466947 | AL80: -0.091018568 | AM80: -0.10108504 | AN80: -0.098087543 | AO80: -0.097714565 | AP80: -0.097714565 | AQ80: -0.097714565 | AR80: -0.097714565 | AS80: =+SUM(AG80:AR80) -> (1.1) | AU80: Gastos de despacho GS | AV80: =VLOOKUP($AU80,#REF!,'Mkt United + Troader 26'!AV$64,0) -> #REF! | AW80: =VLOOKUP($AU80,#REF!,'Mkt United + Troader 26'!AW$64,0) -> #REF! | AX80: =VLOOKUP($AU80,#REF!,'Mkt United + Troader 26'!AX$64,0) -> #REF! | AY80: =VLOOKUP($AU80,#REF!,'Mkt United + Troader 26'!AY$64,0) -> #REF! | AZ80: =+[1]Gastos!G27 -> #ERROR! | BA80: =+[1]Gastos!H27 -> #ERROR! | BB80: =+[1]Gastos!I27 -> #ERROR! | BC80: =+[1]Gastos!J27 -> #ERROR! | BD80: =+[1]Gastos!K27 -> #ERROR! | BE80: =+[1]Gastos!L27 -> #ERROR! | BF80: =+[1]Gastos!M27 -> #ERROR! | BG80: =+[1]Gastos!N27 -> #ERROR! | BH80: =+SUM(AV80:BG80) -> #REF! | BI80: -1.1651388
B81: Costo de Activo | C81: -0.000637 | D81: -0.014 | E81: -0.000614 | F81: -0.000601 | G81: -0.00060147 | H81: -0.00060347948 | I81: -0.00070347948 | J81: -0.000705 | K81: -0.000708 | L81: -0.000708 | M81: -0.000703 | N81: -0.000702 | O81: =+SUM(C81:N81) -> (0.0) | Q81: Costo de Activo | R81: -0.003556625 | S81: -0.003556625 | T81: -0.000643 | U81: -0.000644 | V81: -0.000643 | W81: -0.00067515 | X81: -0.000647 | Y81: -0.000648 | Z81: -0.000733 | AA81: -0.000726 | AB81: -0.00072135 | AC81: -0.000722 | AD81: =+SUM(R81:AC81) -> (0.0) | AF81: Costo de Activo | AG81: -0.0037344563 | AH81: -0.0037344563 | AI81: -0.00067515 | AJ81: -0.0006762 | AK81: -0.00067515 | AL81: -0.0007089075 | AM81: -0.00067935 | AN81: -0.0006804 | AO81: -0.00076965 | AP81: -0.00076965 | AQ81: -0.00076965 | AR81: -0.00076965 | AS81: =+SUM(AG81:AR81) -> (0.0) | AU81: Costo de Activo | AV81: =VLOOKUP($AU81,#REF!,'Mkt United + Troader 26'!AV$64,0) -> #REF! | AW81: =VLOOKUP($AU81,#REF!,'Mkt United + Troader 26'!AW$64,0) -> #REF! | AX81: =VLOOKUP($AU81,#REF!,'Mkt United + Troader 26'!AX$64,0) -> #REF! | AY81: =VLOOKUP($AU81,#REF!,'Mkt United + Troader 26'!AY$64,0) -> #REF! | AZ81: -0.00067515 | BA81: -0.0007089075 | BB81: -0.00067935 | BC81: -0.0006804 | BD81: -0.00076965 | BE81: -0.00076965 | BF81: -0.00076965 | BG81: -0.00076965 | BH81: =+SUM(AV81:BG81) -> #REF!
B82: Gastos Staff | C82: -1.011614 | D82: -1.008367 | E82: -1.086478 | F82: -1.134169 | G82: -1.213996 | H82: -1.22495 | I82: -1.339898 | J82: -1.1625516 | K82: -1.710564 | L82: -1.5904389 | M82: -1.5297635 | N82: -1.9910895 | O82: =+SUM(C82:N82) -> (16.0) | Q82: Gastos Staff | R82: -1.1349171 | S82: -1.1306756 | T82: -1.2191775 | U82: -1.332317 | V82: -1.4465648 | W82: -1.4452193 | X82: -1.4220953 | Y82: -1.419621 | Z82: -1.3080167 | AA82: -1.5306485 | AB82: -1.3959594 | AC82: -1.666509 | AD82: =+SUM(R82:AC82) -> (16.5) | AF82: Gastos Staff | AG82: -0.87228105 | AH82: -0.82761867 | AI82: -1.0541493 | AJ82: -1.0140271 | AK82: -1.0190666 | AL82: -1.1169442 | AM82: -1.0424764 | AN82: -1.0326597 | AO82: -1.0937012 | AP82: -1.0755674 | AQ82: -1.1248186 | AR82: -1.2247204 | AS82: =+SUM(AG82:AR82) -> (12.5) | AU82: Gastos Staff | AV82: =VLOOKUP($AU82,#REF!,'Mkt United + Troader 26'!AV$64,0) -> #REF! | AW82: =VLOOKUP($AU82,#REF!,'Mkt United + Troader 26'!AW$64,0) -> #REF! | AX82: =VLOOKUP($AU82,#REF!,'Mkt United + Troader 26'!AX$64,0) -> #REF! | AY82: =VLOOKUP($AU82,#REF!,'Mkt United + Troader 26'!AY$64,0) -> #REF! | AZ82: -1.0190666 | BA82: -1.1169442 | BB82: -1.0424764 | BC82: -1.0326597 | BD82: -1.0937012 | BE82: -1.0755674 | BF82: -1.1248186 | BG82: -1.2247204 | BH82: =+SUM(AV82:BG82) -> #REF!
B83: Total Gastos | C83: =SUM(C74:C82) -> (3.8) | D83: =SUM(D74:D82) -> (3.5) | E83: =SUM(E74:E82) -> (4.0) | F83: =SUM(F74:F82) -> (4.1) | G83: =SUM(G74:G82) -> (3.8) | H83: =SUM(H74:H82) -> (4.1) | I83: =SUM(I74:I82) -> (4.4) | J83: =SUM(J74:J82) -> (4.0) | ... O83: =SUM(O74:O82) -> (52.0) | Q83: Total Gastos | R83: =SUM(R74:R82) -> (4.7) | S83: =SUM(S74:S82) -> (4.5) | T83: =SUM(T74:T82) -> (4.6) | U83: =SUM(U74:U82) -> (4.9) | V83: =SUM(V74:V82) -> (4.8) | W83: =SUM(W74:W82) -> (5.1) | X83: =SUM(X74:X82) -> (4.9) | Y83: =SUM(Y74:Y82) -> (4.9) | ... AD83: =SUM(AD74:AD82) -> (56.5) | AF83: Total Gastos | AG83: =SUM(AG74:AG82) -> (2.6) | AH83: =SUM(AH74:AH82) -> (2.1) | AI83: =SUM(AI74:AI82) -> (2.4) | AJ83: =SUM(AJ74:AJ82) -> (2.2) | AK83: =SUM(AK74:AK82) -> (2.2) | AL83: =SUM(AL74:AL82) -> (2.4) | AM83: =SUM(AM74:AM82) -> (2.4) | AN83: =SUM(AN74:AN82) -> (2.3) | ... AS83: =SUM(AS74:AS82) -> (28.6) | AU83: Total Gastos | AV83: =SUM(AV74:AV82) -> #REF! | AW83: =SUM(AW74:AW82) -> #REF! | AX83: =SUM(AX74:AX82) -> #REF! | AY83: =SUM(AY74:AY82) -> #REF! | AZ83: =SUM(AZ74:AZ82) -> #ERROR! | BA83: =SUM(BA74:BA82) -> #ERROR! | BB83: =SUM(BB74:BB82) -> #ERROR! | BC83: =SUM(BC74:BC82) -> #ERROR! | ... BH83: =SUM(BH74:BH82) -> #REF!
B84: Contribución Neta | C84: =C73+C83 -> (0.3) | D84: =D73+D83 -> 0.6 | E84: =E73+E83 -> 0.8 | F84: =F73+F83 -> 2.1 | G84: =G73+G83 -> 1.8 | H84: =H73+H83 -> 1.1 | I84: =I73+I83 -> 2.1 | J84: =J73+J83 -> 1.7 | ... O84: =O73+O83 -> 21.3 | Q84: Contribución Neta | R84: =R73+R83 -> (0.1) | S84: =S73+S83 -> 5.0 | T84: =T73+T83 -> 1.9 | U84: =U73+U83 -> 4.6 | V84: =V73+V83 -> 1.5 | W84: =W73+W83 -> 2.3 | X84: =X73+X83 -> 5.8 | Y84: =Y73+Y83 -> 3.0 | ... AD84: =AD73+AD83 -> 28.9 | AF84: Contribución Neta | AG84: =AG73+AG83 -> 0.0 | AH84: =AH73+AH83 -> 0.1 | AI84: =AI73+AI83 -> 0.4 | AJ84: =AJ73+AJ83 -> 0.1 | AK84: =AK73+AK83 -> 0.1 | AL84: =AL73+AL83 -> 1.5 | AM84: =AM73+AM83 -> 1.1 | AN84: =AN73+AN83 -> 1.3 | ... AR84: =AR73+AR83 -> 1.4 | AS84: =+SUM(AG84:AR84) -> 10.4 | AU84: Contribución Neta | AV84: =AV73+AV83 -> #REF! | AW84: =AW73+AW83 -> #REF! | AX84: =AX73+AX83 -> #REF! | AY84: =AY73+AY83 -> #REF! | AZ84: =AZ73+AZ83 -> #ERROR! | BA84: =BA73+BA83 -> #ERROR! | BB84: =BB73+BB83 -> #ERROR! | BC84: =BC73+BC83 -> #ERROR! | ... BG84: =BG73+BG83 -> #ERROR! | BH84: =+SUM(AV84:BG84) -> #REF!
B86: % Margen | C86: =C84/C68 -> (1%) | D86: =D84/D68 -> 3% | E86: =E84/E68 -> 3% | F86: =F84/F68 -> 7% | G86: =G84/G68 -> 6% | H86: =H84/H68 -> 4% | I86: =I84/I68 -> 6% | J86: =J84/J68 -> 6% | ... O86: =O84/O68 -> 6% | Q86: % Margen | R86: =R84/R68 -> (0%) | S86: =S84/S68 -> 16% | T86: =T84/T68 -> 6% | U86: =U84/U68 -> 12% | V86: =V84/V68 -> 5% | W86: =W84/W68 -> 7% | X86: =X84/X68 -> 13% | Y86: =Y84/Y68 -> 8% | ... AD86: =AD84/AD68 -> 8% | AF86: % Margen | AG86: =AG84/AG68 -> 0% | AH86: =AH84/AH68 -> 2% | AI86: =AI84/AI68 -> 9% | AJ86: =AJ84/AJ68 -> 2% | AK86: =AK84/AK68 -> 3% | AL86: =AL84/AL68 -> 26% | AM86: =AM84/AM68 -> 22% | AN86: =AN84/AN68 -> 25% | ... AS86: =AS84/AS68 -> 17.7% | AU86: % Margen | AV86: =AV84/AV68 -> #REF! | AW86: =AW84/AW68 -> #REF! | AX86: =AX84/AX68 -> #REF! | AY86: =AY84/AY68 -> #REF! | AZ86: =AZ84/AZ68 -> #ERROR! | BA86: =BA84/BA68 -> #ERROR! | BB86: =BB84/BB68 -> #ERROR! | BC86: =BC84/BC68 -> #ERROR! | ... BH86: =BH84/BH68 -> #REF!

Sheet Staff 26
B1: GASTOS DE STAFF PRESUPUESTO 2026
R3: Real 2025 | T3: Plan 2026 | V3: Fcst 2026 | X3: Conceptos | Y3: Variaciones
Y4: Fcst 2026 vs Plan 2026 | AA4: Fcst 2026 vs Real 2025
B5: Proyección | C5: 46023 | D5: 46054 | E5: 46082 | F5: 46113 | G5: 46143 | H5: 46174 | I5: 46204 | J5: 46235 | K5: 46266 | L5: 46296 | M5: 46327 | N5: 46357 | O5: Total | R5: $ | S5: % | T5: $ | U5: % | V5: $ | W5: % | Y5: $ | Z5: % | AA5: $ | AB5: %
B6: Ingresos Internos | C6: 0 | D6: 0 | E6: 0 | F6: 0 | G6: 0 | H6: 0 | I6: 0 | J6: 0 | K6: 0 | L6: 0 | M6: 0 | N6: 0 | O6: =+SUM(C6:N6) -> - | S6: =IF((+IFERROR((R6/$R$8),0))<=-200%,"-200%",(+IFERROR((R6/$R$8),0))) -> 0% | T6: =VLOOKUP(X6,$B$27:$O$43,14,0) -> - | U6: =IF((+IFERROR((T6/$T$8),0))<=-200%,"-200%",(+IFERROR((T6/$T$8),0))) -> 0% | V6: =VLOOKUP(X6,$B$5:$O$23,14,0) -> - | W6: =IF((+IFERROR((V6/$V$8),0))<=-200%,"-200%",(+IFERROR((V6/$V$8),0))) -> 0% | X6: Ingresos Internos | Y6: =+V6-T6 -> - | Z6: =IF((IFERROR(IF(ABS(Y6/T6)>=9.99,IF(Y6>0,9.99,-9.99),Y6/ABS(T6)),IF(Y6=0,0,Y6/ABS(Y6))))<=-200%,"-200%",(IFERROR(IF(ABS(Y6/T6)>=9.99,IF(Y6>0,9.99,-9.99),Y6/ABS(T6)),IF(Y6=0,0,Y6/ABS(Y6))))) -> 0% | AA6: =V6-R6 -> - | AB6: =IF((IFERROR(IF(ABS(AA6/R6)>=9.99,IF(AA6>0,9.99,-9.99),AA6/ABS(R6)),IF(AA6=0,0,AA6/ABS(AA6))))<=-200%,"(200%)",(IFERROR(IF(ABS(AA6/R6)>=9.99,IF(AA6>0,9.99,-9.99),AA6/ABS(R6)),IF(AA6=0,0,AA6/ABS(AA6))))) -> 0%
B7: Ingresos Externos | C7: 0 | D7: 0 | E7: 0 | F7: 0 | G7: 0 | H7: 0 | I7: 0 | J7: 0 | K7: 0 | L7: 0 | M7: 0 | N7: 0 | O7: =+SUM(C7:N7) -> - | S7: =IF((+IFERROR((R7/$R$8),0))<=-200%,"-200%",(+IFERROR((R7/$R$8),0))) -> 0% | T7: =VLOOKUP(X7,$B$27:$O$43,14,0) -> - | U7: =IF((+IFERROR((T7/$T$8),0))<=-200%,"-200%",(+IFERROR((T7/$T$8),0))) -> 0% | V7: =VLOOKUP(X7,$B$5:$O$23,14,0) -> - | W7: =IF((+IFERROR((V7/$V$8),0))<=-200%,"-200%",(+IFERROR((V7/$V$8),0))) -> 0% | X7: Ingresos Externos | Y7: =+V7-T7 -> - | Z7: =IF((IFERROR(IF(ABS(Y7/T7)>=9.99,IF(Y7>0,9.99,-9.99),Y7/ABS(T7)),IF(Y7=0,0,Y7/ABS(Y7))))<=-200%,"-200%",(IFERROR(IF(ABS(Y7/T7)>=9.99,IF(Y7>0,9.99,-9.99),Y7/ABS(T7)),IF(Y7=0,0,Y7/ABS(Y7))))) -> 0% | AA7: =V7-R7 -> - | AB7: =IF((IFERROR(IF(ABS(AA7/R7)>=9.99,IF(AA7>0,9.99,-9.99),AA7/ABS(R7)),IF(AA7=0,0,AA7/ABS(AA7))))<=-200%,"(200%)",(IFERROR(IF(ABS(AA7/R7)>=9.99,IF(AA7>0,9.99,-9.99),AA7/ABS(R7)),IF(AA7=0,0,AA7/ABS(AA7))))) -> 0%
B8: Total Ingresos | C8: =C6+C7 -> - | D8: =D6+D7 -> - | E8: =E7+E6 -> - | F8: =F7+F6 -> - | G8: =G7+G6 -> - | H8: =H7+H6 -> - | I8: =I7+I6 -> - | J8: =J7+J6 -> - | K8: =K7+K6 -> - | L8: =L7+L6 -> - | ... O8: =O7+O6 -> - | R8: =SUM(R6:R7) -> - | S8: =IF((+IFERROR((R8/$R$8),0))<=-200%,"-200%",(+IFERROR((R8/$R$8),0))) -> 0% | T8: =SUM(T6:T7) -> - | U8: =IF((+IFERROR((T8/$T$8),0))<=-200%,"-200%",(+IFERROR((T8/$T$8),0))) -> 0% | V8: =SUM(V6:V7) -> - | W8: =IF((+IFERROR((V8/$V$8),0))<=-200%,"-200%",(+IFERROR((V8/$V$8),0))) -> 0% | X8: Total Ingresos | Y8: =+V8-T8 -> - | Z8: =IF((IFERROR(IF(ABS(Y8/T8)>=9.99,IF(Y8>0,9.99,-9.99),Y8/ABS(T8)),IF(Y8=0,0,Y8/ABS(Y8))))<=-200%,"-200%",(IFERROR(IF(ABS(Y8/T8)>=9.99,IF(Y8>0,9.99,-9.99),Y8/ABS(T8)),IF(Y8=0,0,Y8/ABS(Y8))))) -> 0% | AA8: =V8-R8 -> - | AB8: =IF((IFERROR(IF(ABS(AA8/R8)>=9.99,IF(AA8>0,9.99,-9.99),AA8/ABS(R8)),IF(AA8=0,0,AA8/ABS(AA8))))<=-200%,"(200%)",(IFERROR(IF(ABS(AA8/R8)>=9.99,IF(AA8>0,9.99,-9.99),AA8/ABS(R8)),IF(AA8=0,0,AA8/ABS(AA8))))) -> 0%
B9: Costo | O9: =+SUM(C9:N9) -> - | R9: 0 | S9: =IF((+IFERROR((R9/$R$8),0))<=-200%,"-200%",(+IFERROR((R9/$R$8),0))) -> 0% | T9: =VLOOKUP(X9,$B$27:$O$43,14,0) -> - | U9: =IF((+IFERROR((T9/$T$8),0))<=-200%,"-200%",(+IFERROR((T9/$T$8),0))) -> 0% | V9: =VLOOKUP(X9,$B$5:$O$23,14,0) -> - | W9: =IF((+IFERROR((V9/$V$8),0))<=-200%,"-200%",(+IFERROR((V9/$V$8),0))) -> 0% | X9: Costo | Y9: =+V9-T9 -> - | Z9: =IF((IFERROR(IF(ABS(Y9/T9)>=9.99,IF(Y9>0,9.99,-9.99),Y9/ABS(T9)),IF(Y9=0,0,Y9/ABS(Y9))))<=-200%,"-200%",(IFERROR(IF(ABS(Y9/T9)>=9.99,IF(Y9>0,9.99,-9.99),Y9/ABS(T9)),IF(Y9=0,0,Y9/ABS(Y9))))) -> 0% | AA9: =V9-R9 -> - | AB9: =IF((IFERROR(IF(ABS(AA9/R9)>=9.99,IF(AA9>0,9.99,-9.99),AA9/ABS(R9)),IF(AA9=0,0,AA9/ABS(AA9))))<=-200%,"(200%)",(IFERROR(IF(ABS(AA9/R9)>=9.99,IF(AA9>0,9.99,-9.99),AA9/ABS(R9)),IF(AA9=0,0,AA9/ABS(AA9))))) -> 0%
B10: Costo de Nube | C10: -0.03800104 | D10: -0.03925775 | E10: -0.04069563 | F10: -0.03383244 | G10: -0.035524062 | H10: -0.110702 | I10: -0.110702 | J10: -0.110702 | K10: -0.110702 | L10: -0.110702 | M10: -0.110702 | N10: -0.110702 | O10: =+SUM(C10:N10) -> (1.0) | R10: -0.46974699 | T10: =VLOOKUP(X10,$B$27:$O$43,14,0) -> #REF! | U10: =IF((+IFERROR((T10/$T$8),0))<=-200%,"-200%",(+IFERROR((T10/$T$8),0))) -> 0% | V10: =VLOOKUP(X10,$B$5:$O$23,14,0) -> (1.0) | W10: =IF((+IFERROR((V10/$V$8),0))<=-200%,"-200%",(+IFERROR((V10/$V$8),0))) -> 0% | X10: Costo de Nube | Y10: =+V10-T10 -> #REF! | Z10: =IF((IFERROR(IF(ABS(Y10/T10)>=9.99,IF(Y10>0,9.99,-9.99),Y10/ABS(T10)),IF(Y10=0,0,Y10/ABS(Y10))))<=-200%,"-200%",(IFERROR(IF(ABS(Y10/T10)>=9.99,IF(Y10>0,9.99,-9.99),Y10/ABS(T10)),IF(Y10=0,0,Y10/ABS(Y10))))) -> #REF! | AA10: =V10-R10 -> (0.5) | AB10: =IF((IFERROR(IF(ABS(AA10/R10)>=9.99,IF(AA10>0,9.99,-9.99),AA10/ABS(R10)),IF(AA10=0,0,AA10/ABS(AA10))))<=-200%,"(200%)",(IFERROR(IF(ABS(AA10/R10)>=9.99,IF(AA10>0,9.99,-9.99),AA10/ABS(R10)),IF(AA10=0,0,AA10/ABS(AA10))))) -> (105%)
B11: Desarrollo de Software | C11: -1.0866268 | D11: -0.51139064 | E11: -0.51904075 | F11: -0.44441161 | G11: -0.45121048 | H11: -0.46460095 | I11: -0.46460095 | J11: -0.77413105 | K11: -0.49173355 | L11: -0.49173355 | M11: -0.49173355 | N11: -0.49173355 | O11: =+SUM(C11:N11) -> (6.7) | R11: -4.3044185 | S11: =IF((+IFERROR((R11/$R$8),0))<=-200%,"-200%",(+IFERROR((R11/$R$8),0))) -> 0% | T11: =VLOOKUP(X11,$B$27:$O$43,14,0) -> #REF! | U11: =IF((+IFERROR((T11/$T$8),0))<=-200%,"-200%",(+IFERROR((T11/$T$8),0))) -> 0% | V11: =VLOOKUP(X11,$B$5:$O$23,14,0) -> (6.7) | W11: =IF((+IFERROR((V11/$V$8),0))<=-200%,"-200%",(+IFERROR((V11/$V$8),0))) -> 0% | X11: Desarrollo de Software | Y11: =+V11-T11 -> #REF! | Z11: =IF((IFERROR(IF(ABS(Y11/T11)>=9.99,IF(Y11>0,9.99,-9.99),Y11/ABS(T11)),IF(Y11=0,0,Y11/ABS(Y11))))<=-200%,"-200%",(IFERROR(IF(ABS(Y11/T11)>=9.99,IF(Y11>0,9.99,-9.99),Y11/ABS(T11)),IF(Y11=0,0,Y11/ABS(Y11))))) -> #REF! | AA11: =V11-R11 -> (2.4) | AB11: =IF((IFERROR(IF(ABS(AA11/R11)>=9.99,IF(AA11>0,9.99,-9.99),AA11/ABS(R11)),IF(AA11=0,0,AA11/ABS(AA11))))<=-200%,"(200%)",(IFERROR(IF(ABS(AA11/R11)>=9.99,IF(AA11>0,9.99,-9.99),AA11/ABS(R11)),IF(AA11=0,0,AA11/ABS(AA11))))) -> (55%)
B12: Costos Totales | C12: =SUM(C9:C11) -> (1.1) | D12: =SUM(D9:D11) -> (0.6) | E12: =SUM(E9:E11) -> (0.6) | F12: =SUM(F9:F11) -> (0.5) | G12: =SUM(G9:G11) -> (0.5) | H12: =SUM(H9:H11) -> (0.6) | I12: =SUM(I9:I11) -> (0.6) | J12: =SUM(J9:J11) -> (0.9) | ... O12: =SUM(O9:O11) -> (7.6) | R12: =SUM(R9:R11) -> (4.8) | S12: =IF((+IFERROR((R12/$R$8),0))<=-200%,"-200%",(+IFERROR((R12/$R$8),0))) -> 0% | T12: =SUM(T9:T11) -> #REF! | U12: =IF((+IFERROR((T12/$T$8),0))<=-200%,"-200%",(+IFERROR((T12/$T$8),0))) -> 0% | V12: =SUM(V9:V11) -> (7.6) | W12: =IF((+IFERROR((V12/$V$8),0))<=-200%,"-200%",(+IFERROR((V12/$V$8),0))) -> 0% | X12: Costos Totales | Y12: =+V12-T12 -> #REF! | Z12: =IF((IFERROR(IF(ABS(Y12/T12)>=9.99,IF(Y12>0,9.99,-9.99),Y12/ABS(T12)),IF(Y12=0,0,Y12/ABS(Y12))))<=-200%,"-200%",(IFERROR(IF(ABS(Y12/T12)>=9.99,IF(Y12>0,9.99,-9.99),Y12/ABS(T12)),IF(Y12=0,0,Y12/ABS(Y12))))) -> #REF! | AA12: =V12-R12 -> (2.9) | AB12: =IF((IFERROR(IF(ABS(AA12/R12)>=9.99,IF(AA12>0,9.99,-9.99),AA12/ABS(R12)),IF(AA12=0,0,AA12/ABS(AA12))))<=-200%,"(200%)",(IFERROR(IF(ABS(AA12/R12)>=9.99,IF(AA12>0,9.99,-9.99),AA12/ABS(R12)),IF(AA12=0,0,AA12/ABS(AA12))))) -> (60%)
B13: Contribución Bruta | C13: =C8+C12 -> (1.1) | D13: =D8+D12 -> (0.6) | E13: =E8+E12 -> (0.6) | F13: =F8+F12 -> (0.5) | G13: =G8+G12 -> (0.5) | H13: =H8+H12 -> (0.6) | I13: =I8+I12 -> (0.6) | J13: =J8+J12 -> (0.9) | ... O13: =O8+O12 -> (7.6) | R13: =R12+R8 -> (4.8) | S13: =IF((+IFERROR((R13/$R$8),0))<=-200%,"-200%",(+IFERROR((R13/$R$8),0))) -> 0% | T13: =T8+T12 -> #REF! | U13: =IF((+IFERROR((T13/$T$8),0))<=-200%,"-200%",(+IFERROR((T13/$T$8),0))) -> 0% | V13: =V8+V12 -> (7.6) | W13: =IF((+IFERROR((V13/$V$8),0))<=-200%,"-200%",(+IFERROR((V13/$V$8),0))) -> 0% | X13: Contribución Bruta | Y13: =+V13-T13 -> #REF! | Z13: =IF((IFERROR(IF(ABS(Y13/T13)>=9.99,IF(Y13>0,9.99,-9.99),Y13/ABS(T13)),IF(Y13=0,0,Y13/ABS(Y13))))<=-200%,"-200%",(IFERROR(IF(ABS(Y13/T13)>=9.99,IF(Y13>0,9.99,-9.99),Y13/ABS(T13)),IF(Y13=0,0,Y13/ABS(Y13))))) -> #REF! | AA13: =V13-R13 -> (2.9) | AB13: =IF((IFERROR(IF(ABS(AA13/R13)>=9.99,IF(AA13>0,9.99,-9.99),AA13/ABS(R13)),IF(AA13=0,0,AA13/ABS(AA13))))<=-200%,"(200%)",(IFERROR(IF(ABS(AA13/R13)>=9.99,IF(AA13>0,9.99,-9.99),AA13/ABS(R13)),IF(AA13=0,0,AA13/ABS(AA13))))) -> (60%)
B14: Personal | C14: -11.097364 | D14: -13.627559 | E14: -11.955164 | F14: -9.6196307 | G14: -10.158921 | H14: -12.49739 | I14: -12.49739 | J14: -12.49739 | K14: -12.49739 | L14: -12.49739 | M14: -12.49739 | N14: -12.49739 | O14: =+SUM(C14:N14) -> (143.9) | R14: -127.25071 | S14: =IF((+IFERROR((R14/$R$8),0))<=-200%,"-200%",(+IFERROR((R14/$R$8),0))) -> 0% | T14: =VLOOKUP(X14,$B$27:$O$43,14,0) -> #REF! | U14: =IF((+IFERROR((T14/$T$8),0))<=-200%,"-200%",(+IFERROR((T14/$T$8),0))) -> 0% | V14: =VLOOKUP(X14,$B$5:$O$23,14,0) -> (143.9) | W14: =IF((+IFERROR((V14/$V$8),0))<=-200%,"-200%",(+IFERROR((V14/$V$8),0))) -> 0% | X14: Personal | Y14: =+V14-T14 -> #REF! | Z14: =IF((IFERROR(IF(ABS(Y14/T14)>=9.99,IF(Y14>0,9.99,-9.99),Y14/ABS(T14)),IF(Y14=0,0,Y14/ABS(Y14))))<=-200%,"-200%",(IFERROR(IF(ABS(Y14/T14)>=9.99,IF(Y14>0,9.99,-9.99),Y14/ABS(T14)),IF(Y14=0,0,Y14/ABS(Y14))))) -> #REF! | AA14: =V14-R14 -> (16.7) | AB14: =IF((IFERROR(IF(ABS(AA14/R14)>=9.99,IF(AA14>0,9.99,-9.99),AA14/ABS(R14)),IF(AA14=0,0,AA14/ABS(AA14))))<=-200%,"(200%)",(IFERROR(IF(ABS(AA14/R14)>=9.99,IF(AA14>0,9.99,-9.99),AA14/ABS(R14)),IF(AA14=0,0,AA14/ABS(AA14))))) -> (13%)
B15: Gastos UX/UI | C15: 0 | D15: -0.045951535 | E15: -0.072039 | F15: -0.071962 | G15: -0.072075 | H15: 0 | I15: 0 | J15: 0 | K15: 0 | L15: 0 | M15: 0 | N15: 0 | O15: =+SUM(C15:N15) -> (0.3) | R15: 0 | S15: =IF((+IFERROR((R15/$R$8),0))<=-200%,"-200%",(+IFERROR((R15/$R$8),0))) -> 0% | T15: 0 | U15: =IF((+IFERROR((T15/$T$8),0))<=-200%,"-200%",(+IFERROR((T15/$T$8),0))) -> 0% | V15: =VLOOKUP(X15,$B$5:$O$23,14,0) -> (0.3) | W15: =IF((+IFERROR((V15/$V$8),0))<=-200%,"-200%",(+IFERROR((V15/$V$8),0))) -> 0% | X15: Gastos UX/UI | Y15: =+V15-T15 -> (0.3) | Z15: =IF((IFERROR(IF(ABS(Y15/T15)>=9.99,IF(Y15>0,9.99,-9.99),Y15/ABS(T15)),IF(Y15=0,0,Y15/ABS(Y15))))<=-200%,"-200%",(IFERROR(IF(ABS(Y15/T15)>=9.99,IF(Y15>0,9.99,-9.99),Y15/ABS(T15)),IF(Y15=0,0,Y15/ABS(Y15))))) -> (100%) | AA15: =V15-R15 -> (0.3) | AB15: =IF((IFERROR(IF(ABS(AA15/R15)>=9.99,IF(AA15>0,9.99,-9.99),AA15/ABS(R15)),IF(AA15=0,0,AA15/ABS(AA15))))<=-200%,"(200%)",(IFERROR(IF(ABS(AA15/R15)>=9.99,IF(AA15>0,9.99,-9.99),AA15/ABS(R15)),IF(AA15=0,0,AA15/ABS(AA15))))) -> (100%)
B16: Operación | C16: -0.25366797 | D16: -0.39990506 | E16: -0.64566096 | F16: -0.90213115 | G16: -0.60967111 | H16: -1.5312105 | I16: -1.7367489 | J16: -1.4559413 | K16: -2.1169912 | L16: -1.972087 | M16: -2.3656462 | N16: -2.3648613 | O16: =+SUM(C16:N16) -> (16.4) | R16: -21.078782 | S16: =IF((+IFERROR((R16/$R$8),0))<=-200%,"-200%",(+IFERROR((R16/$R$8),0))) -> 0% | T16: =VLOOKUP(X16,$B$27:$O$43,14,0) -> #ERROR! | U16: =IF((+IFERROR((T16/$T$8),0))<=-200%,"-200%",(+IFERROR((T16/$T$8),0))) -> 0% | V16: =VLOOKUP(X16,$B$5:$O$23,14,0) -> (16.4) | W16: =IF((+IFERROR((V16/$V$8),0))<=-200%,"-200%",(+IFERROR((V16/$V$8),0))) -> 0% | X16: Operación | Y16: =+V16-T16 -> #ERROR! | Z16: =IF((IFERROR(IF(ABS(Y16/T16)>=9.99,IF(Y16>0,9.99,-9.99),Y16/ABS(T16)),IF(Y16=0,0,Y16/ABS(Y16))))<=-200%,"-200%",(IFERROR(IF(ABS(Y16/T16)>=9.99,IF(Y16>0,9.99,-9.99),Y16/ABS(T16)),IF(Y16=0,0,Y16/ABS(Y16))))) -> #ERROR! | AA16: =V16-R16 -> 4.7 | AB16: =IF((IFERROR(IF(ABS(AA16/R16)>=9.99,IF(AA16>0,9.99,-9.99),AA16/ABS(R16)),IF(AA16=0,0,AA16/ABS(AA16))))<=-200%,"(200%)",(IFERROR(IF(ABS(AA16/R16)>=9.99,IF(AA16>0,9.99,-9.99),AA16/ABS(R16)),IF(AA16=0,0,AA16/ABS(AA16))))) -> 22%
B17: Mercadotecnia | C17: -0.16655682 | D17: -0.10469908 | E17: -0.09523818 | F17: -0.04254791 | G17: -0.15106272 | H17: -0.23461986 | I17: -0.26725576 | J17: -0.22266843 | K17: -0.32763156 | L17: -0.30462332 | M17: -0.36711361 | N17: -0.36698899 | O17: =+SUM(C17:N17) -> (2.7) | R17: -9.3710179 | S17: =IF((+IFERROR((R17/$R$8),0))<=-200%,"-200%",(+IFERROR((R17/$R$8),0))) -> 0% | T17: =VLOOKUP(X17,$B$27:$O$43,14,0) -> #ERROR! | U17: =IF((+IFERROR((T17/$T$8),0))<=-200%,"-200%",(+IFERROR((T17/$T$8),0))) -> 0% | V17: =VLOOKUP(X17,$B$5:$O$23,14,0) -> (2.7) | W17: =IF((+IFERROR((V17/$V$8),0))<=-200%,"-200%",(+IFERROR((V17/$V$8),0))) -> 0% | X17: Mercadotecnia | Y17: =+V17-T17 -> #ERROR! | Z17: =IF((IFERROR(IF(ABS(Y17/T17)>=9.99,IF(Y17>0,9.99,-9.99),Y17/ABS(T17)),IF(Y17=0,0,Y17/ABS(Y17))))<=-200%,"(200%)",(IFERROR(IF(ABS(Y17/T17)>=9.99,IF(Y17>0,9.99,-9.99),Y17/ABS(T17)),IF(Y17=0,0,Y17/ABS(Y17)))))*1 -> #ERROR! | AA17: =V17-R17 -> 6.7 | AB17: =IF((IFERROR(IF(ABS(AA17/R17)>=9.99,IF(AA17>0,9.99,-9.99),AA17/ABS(R17)),IF(AA17=0,0,AA17/ABS(AA17))))<=-200%,"(200%)",(IFERROR(IF(ABS(AA17/R17)>=9.99,IF(AA17>0,9.99,-9.99),AA17/ABS(R17)),IF(AA17=0,0,AA17/ABS(AA17)))))*1 -> 72%
B18: Mantenimiento de Software | C18: -0.38403069 | D18: -0.33417958 | E18: -0.30201417 | F18: -0.30087527 | G18: -0.29350685 | H18: -0.35773356 | I18: -0.27449777 | J18: -0.28376466 | K18: -0.28376466 | L18: -0.28376466 | M18: -0.28376466 | N18: -0.35688726 | O18: =+SUM(C18:N18) -> (3.7) | R18: -2.2726108 | T18: =VLOOKUP(X18,$B$27:$O$43,14,0) -> #ERROR! | U18: =IF((+IFERROR((T18/$T$8),0))<=-200%,"-200%",(+IFERROR((T18/$T$8),0))) -> 0% | V18: =VLOOKUP(X18,$B$5:$O$23,14,0) -> (3.7) | W18: =IF((+IFERROR((V18/$V$8),0))<=-200%,"-200%",(+IFERROR((V18/$V$8),0))) -> 0% | X18: Mantenimiento de Software | Y18: =+V18-T18 -> #ERROR! | Z18: =IF((IFERROR(IF(ABS(Y18/T18)>=9.99,IF(Y18>0,9.99,-9.99),Y18/ABS(T18)),IF(Y18=0,0,Y18/ABS(Y18))))<=-200%,"(200%)",(IFERROR(IF(ABS(Y18/T18)>=9.99,IF(Y18>0,9.99,-9.99),Y18/ABS(T18)),IF(Y18=0,0,Y18/ABS(Y18)))))*1 -> #ERROR! | AA18: =V18-R18 -> (1.5) | AB18: =IF((IFERROR(IF(ABS(AA18/R18)>=9.99,IF(AA18>0,9.99,-9.99),AA18/ABS(R18)),IF(AA18=0,0,AA18/ABS(AA18))))<=-200%,"(200%)",(IFERROR(IF(ABS(AA18/R18)>=9.99,IF(AA18>0,9.99,-9.99),AA18/ABS(R18)),IF(AA18=0,0,AA18/ABS(AA18)))))*1 -> (65%)
B19: Staff Sistemas | C19: -0.13038314 | D19: -0.11799216 | E19: -0.083847977 | F19: -0.091028269 | G19: -0.066616647 | H19: -0.098782486 | I19: -0.10642858 | J19: -0.11743462 | K19: -0.11743462 | L19: -0.11743462 | M19: -0.11743462 | N19: -0.11743462 | O19: =+SUM(C19:N19) -> (1.3) | R19: -1.0052735 | S19: =IF((+IFERROR((R19/$R$8),0))<=-200%,"-200%",(+IFERROR((R19/$R$8),0))) -> 0% | T19: =VLOOKUP(X19,$B$27:$O$43,14,0) -> #REF! | U19: =IF((+IFERROR((T19/$T$8),0))<=-200%,"-200%",(+IFERROR((T19/$T$8),0))) -> 0% | V19: =VLOOKUP(X19,$B$5:$O$23,14,0) -> (1.3) | W19: =IF((+IFERROR((V19/$V$8),0))<=-200%,"-200%",(+IFERROR((V19/$V$8),0))) -> 0% | X19: Staff Sistemas | Y19: =+V19-T19 -> #REF! | Z19: =IF((IFERROR(IF(ABS(Y19/T19)>=9.99,IF(Y19>0,9.99,-9.99),Y19/ABS(T19)),IF(Y19=0,0,Y19/ABS(Y19))))<=-200%,"-200%",(IFERROR(IF(ABS(Y19/T19)>=9.99,IF(Y19>0,9.99,-9.99),Y19/ABS(T19)),IF(Y19=0,0,Y19/ABS(Y19))))) -> #REF! | AA19: =V19-R19 -> (0.3) | AB19: =IF((IFERROR(IF(ABS(AA19/R19)>=9.99,IF(AA19>0,9.99,-9.99),AA19/ABS(R19)),IF(AA19=0,0,AA19/ABS(AA19))))<=-200%,"(200%)",(IFERROR(IF(ABS(AA19/R19)>=9.99,IF(AA19>0,9.99,-9.99),AA19/ABS(R19)),IF(AA19=0,0,AA19/ABS(AA19))))) -> (28%)
B20: Renta, Luz y Teléfono | C20: -1.5714989 | D20: -1.0945035 | E20: -0.99337409 | F20: -0.73369911 | G20: -0.83993116 | H20: -0.7671396 | I20: -0.7671396 | J20: -0.7671396 | K20: -0.7671396 | L20: -0.7671396 | M20: -0.7671396 | N20: -0.7671396 | O20: =+SUM(C20:N20) -> (10.6) | R20: -11.455213 | T20: =VLOOKUP(X20,$B$27:$O$43,14,0) -> #ERROR! | U20: =IF((+IFERROR((T20/$T$8),0))<=-200%,"-200%",(+IFERROR((T20/$T$8),0))) -> 0% | V20: =VLOOKUP(X20,$B$5:$O$23,14,0) -> (10.6) | W20: =IF((+IFERROR((V20/$V$8),0))<=-200%,"-200%",(+IFERROR((V20/$V$8),0))) -> 0% | X20: Renta, Luz y Teléfono | Y20: =+V20-T20 -> #ERROR! | Z20: =IF((IFERROR(IF(ABS(Y20/T20)>=9.99,IF(Y20>0,9.99,-9.99),Y20/ABS(T20)),IF(Y20=0,0,Y20/ABS(Y20))))<=-200%,"-200%",(IFERROR(IF(ABS(Y20/T20)>=9.99,IF(Y20>0,9.99,-9.99),Y20/ABS(T20)),IF(Y20=0,0,Y20/ABS(Y20))))) -> #ERROR! | AA20: =V20-R20 -> 0.9 | AB20: =IF((IFERROR(IF(ABS(AA20/R20)>=9.99,IF(AA20>0,9.99,-9.99),AA20/ABS(R20)),IF(AA20=0,0,AA20/ABS(AA20))))<=-200%,"(200%)",(IFERROR(IF(ABS(AA20/R20)>=9.99,IF(AA20>0,9.99,-9.99),AA20/ABS(R20)),IF(AA20=0,0,AA20/ABS(AA20))))) -> 7%
B21: Gastos de despacho GS | C21: -1.0672109 | D21: -1.0707356 | E21: -1.0573367 | F21: -1.0139929 | G21: -1.1775296 | H21: -0.94193539 | I21: -1.0729597 | J21: -0.89395362 | K21: -1.3153523 | L21: -1.2229804 | M21: -1.4738621 | N21: -1.4733617 | O21: =+SUM(C21:N21) -> (13.8) | R21: -13.657147 | S21: =IF((+IFERROR((R21/$R$8),0))<=-200%,"-200%",(+IFERROR((R21/$R$8),0))) -> 0% | T21: =VLOOKUP(X21,$B$27:$O$43,14,0) -> #ERROR! | U21: =IF((+IFERROR((T21/$T$8),0))<=-200%,"-200%",(+IFERROR((T21/$T$8),0))) -> 0% | V21: =VLOOKUP(X21,$B$5:$O$23,14,0) -> (13.8) | W21: =IF((+IFERROR((V21/$V$8),0))<=-200%,"-200%",(+IFERROR((V21/$V$8),0))) -> 0% | X21: Gastos de despacho GS | Y21: =+V21-T21 -> #ERROR! | Z21: =IF((IFERROR(IF(ABS(Y21/T21)>=9.99,IF(Y21>0,9.99,-9.99),Y21/ABS(T21)),IF(Y21=0,0,Y21/ABS(Y21))))<=-200%,"-200%",(IFERROR(IF(ABS(Y21/T21)>=9.99,IF(Y21>0,9.99,-9.99),Y21/ABS(T21)),IF(Y21=0,0,Y21/ABS(Y21))))) -> #ERROR! | AA21: =V21-R21 -> (0.1) | AB21: =IF((IFERROR(IF(ABS(AA21/R21)>=9.99,IF(AA21>0,9.99,-9.99),AA21/ABS(R21)),IF(AA21=0,0,AA21/ABS(AA21))))<=-200%,"(200%)",(IFERROR(IF(ABS(AA21/R21)>=9.99,IF(AA21>0,9.99,-9.99),AA21/ABS(R21)),IF(AA21=0,0,AA21/ABS(AA21))))) -> (1%)
B22: Costo de Activo | C22: -0.00164064 | D22: -0.00163264 | E22: -0.00142156 | F22: -0.00140756 | G22: -0.00141456 | H22: -0.0039817004 | I22: -0.0045355597 | J22: -0.0037788744 | K22: -0.005560189 | L22: -0.0051697193 | M22: -0.0062302333 | N22: -0.0062281183 | O22: =+SUM(C22:N22) -> (0.0) | R22: -0.050714465 | S22: =IF((+IFERROR((R22/$R$8),0))<=-200%,"-200%",(+IFERROR((R22/$R$8),0))) -> 0% | T22: =VLOOKUP(X22,$B$27:$O$43,14,0) -> #REF! | U22: =IF((+IFERROR((T22/$T$8),0))<=-200%,"-200%",(+IFERROR((T22/$T$8),0))) -> 0% | V22: =VLOOKUP(X22,$B$5:$O$23,14,0) -> (0.0) | W22: =IF((+IFERROR((V22/$V$8),0))<=-200%,"-200%",(+IFERROR((V22/$V$8),0))) -> 0% | X22: Costo de Activo | Y22: =+V22-T22 -> #REF! | Z22: =IF((IFERROR(IF(ABS(Y22/T22)>=9.99,IF(Y22>0,9.99,-9.99),Y22/ABS(T22)),IF(Y22=0,0,Y22/ABS(Y22))))<=-200%,"-200%",(IFERROR(IF(ABS(Y22/T22)>=9.99,IF(Y22>0,9.99,-9.99),Y22/ABS(T22)),IF(Y22=0,0,Y22/ABS(Y22))))) -> #REF! | AA22: =V22-R22 -> 0.0 | AB22: =IF((IFERROR(IF(ABS(AA22/R22)>=9.99,IF(AA22>0,9.99,-9.99),AA22/ABS(R22)),IF(AA22=0,0,AA22/ABS(AA22))))<=-200%,"(200%)",(IFERROR(IF(ABS(AA22/R22)>=9.99,IF(AA22>0,9.99,-9.99),AA22/ABS(R22)),IF(AA22=0,0,AA22/ABS(AA22))))) -> 15%
B23: Total Gastos | C23: =SUM(C14:C22) -> (14.7) | D23: =SUM(D14:D22) -> (16.8) | E23: =SUM(E14:E22) -> (15.2) | F23: =SUM(F14:F22) -> (12.8) | G23: =SUM(G14:G22) -> (13.4) | H23: =SUM(H14:H22) -> (16.4) | I23: =SUM(I14:I22) -> (16.7) | J23: =SUM(J14:J22) -> (16.2) | ... O23: =SUM(O14:O22) -> (192.7) | R23: =+SUM(R14:R22) -> (186.1) | S23: =IF((+IFERROR((R23/$R$8),0))<=-200%,"-200%",(+IFERROR((R23/$R$8),0))) -> 0% | T23: =+SUM(T14:T22) -> #REF! | U23: =IF((+IFERROR((T23/$T$8),0))<=-200%,"-200%",(+IFERROR((T23/$T$8),0))) -> 0% | V23: =+SUM(V14:V22) -> (192.7) | W23: =IF((+IFERROR((V23/$V$8),0))<=-200%,"-200%",(+IFERROR((V23/$V$8),0))) -> 0% | X23: Costo de Activo | Y23: =+V23-T23 -> #REF! | Z23: =IF((IFERROR(IF(ABS(Y23/T23)>=9.99,IF(Y23>0,9.99,-9.99),Y23/ABS(T23)),IF(Y23=0,0,Y23/ABS(Y23))))<=-200%,"-200%",(IFERROR(IF(ABS(Y23/T23)>=9.99,IF(Y23>0,9.99,-9.99),Y23/ABS(T23)),IF(Y23=0,0,Y23/ABS(Y23))))) -> #REF! | AA23: =V23-R23 -> (6.5) | AB23: =IF((IFERROR(IF(ABS(AA23/R23)>=9.99,IF(AA23>0,9.99,-9.99),AA23/ABS(R23)),IF(AA23=0,0,AA23/ABS(AA23))))<=-200%,"(200%)",(IFERROR(IF(ABS(AA23/R23)>=9.99,IF(AA23>0,9.99,-9.99),AA23/ABS(R23)),IF(AA23=0,0,AA23/ABS(AA23))))) -> (3%)
B24: Contribución Neta $ | C24: =+C13+C23 -> (15.8) | D24: =+D13+D23 -> (17.3) | E24: =+E13+E23 -> (15.8) | F24: =+F13+F23 -> (13.3) | G24: =+G13+G23 -> (13.9) | H24: =+H13+H23 -> (17.0) | I24: =+I13+I23 -> (17.3) | J24: =+J13+J23 -> (17.1) | ... O24: =+O13+O23 -> (200.3) | R24: =+R23+R13 -> (190.9) | S24: =IF((+IFERROR((R24/$R$8),0))<=-200%,"-200%",(+IFERROR((R24/$R$8),0))) -> 0% | T24: =T13+T23 -> #REF! | U24: =IF((+IFERROR((T24/$T$8),0))<=-200%,"-200%",(+IFERROR((T24/$T$8),0))) -> 0% | V24: =V13+V23 -> (200.3) | W24: =IF((+IFERROR((V24/$V$8),0))<=-200%,"-200%",(+IFERROR((V24/$V$8),0))) -> 0% | X24: Contribución Neta | Y24: =+V24-T24 -> #REF! | Z24: =IF((IFERROR(IF(ABS(Y24/T24)>=9.99,IF(Y24>0,9.99,-9.99),Y24/ABS(T24)),IF(Y24=0,0,Y24/ABS(Y24))))<=-200%,"-200%",(IFERROR(IF(ABS(Y24/T24)>=9.99,IF(Y24>0,9.99,-9.99),Y24/ABS(T24)),IF(Y24=0,0,Y24/ABS(Y24))))) -> #REF! | AA24: =V24-R24 -> (9.4) | AB24: =IF((IFERROR(IF(ABS(AA24/R24)>=9.99,IF(AA24>0,9.99,-9.99),AA24/ABS(R24)),IF(AA24=0,0,AA24/ABS(AA24))))<=-200%,"(200%)",(IFERROR(IF(ABS(AA24/R24)>=9.99,IF(AA24>0,9.99,-9.99),AA24/ABS(R24)),IF(AA24=0,0,AA24/ABS(AA24))))) -> (5%)
B27: Presupuesto 2026 | C27: 46023 | D27: 46054 | E27: 46082 | F27: 46113 | G27: 46143 | H27: 46174 | I27: 46204 | J27: 46235 | K27: 46266 | L27: 46296 | M27: 46327 | N27: 46357 | O27: Total
B28: Ingresos Internos | C28: 0 | D28: 0 | E28: 0 | F28: 0 | G28: 0 | H28: 0 | I28: 0 | J28: 0 | K28: 0 | L28: 0 | M28: 0 | N28: 0 | O28: =+SUM(C28:N28) -> -
B29: Ingresos Externos | C29: 0 | D29: 0 | E29: 0 | F29: 0 | G29: 0 | H29: 0 | I29: 0 | J29: 0 | K29: 0 | L29: 0 | M29: 0 | N29: 0 | O29: =+SUM(C29:N29) -> -
B30: Total Ingresos | C30: =C28+C29 -> - | D30: =D28+D29 -> - | E30: =E29+E28 -> - | F30: =F29+F28 -> - | G30: =G29+G28 -> - | H30: =H29+H28 -> - | I30: =I29+I28 -> - | J30: =J29+J28 -> - | K30: =K29+K28 -> - | L30: =L29+L28 -> - | ... O30: =O29+O28 -> -
B31: Costo | O31: =+SUM(C31:N31) -> -
B32: Costo de Nube | C32: =+'[2]Dispersión Gto de Staff'!C48 -> #REF! | D32: =+'[2]Dispersión Gto de Staff'!D48 -> #REF! | E32: =+'[2]Dispersión Gto de Staff'!E48 -> #REF! | F32: =+'[2]Dispersión Gto de Staff'!F48 -> #REF! | G32: =+'[2]Dispersión Gto de Staff'!G48 -> #REF! | H32: =+'[2]Dispersión Gto de Staff'!H48 -> #REF! | I32: =+'[2]Dispersión Gto de Staff'!I48 -> #REF! | J32: =+'[2]Dispersión Gto de Staff'!J48 -> #REF! | ... N32: =+'[2]Dispersión Gto de Staff'!N48 -> #REF! | O32: =+SUM(C32:N32) -> #REF!
B33: Desarrollo de Software | C33: =+'[2]Dispersión Gto de Staff'!C49 -> #REF! | D33: =+'[2]Dispersión Gto de Staff'!D49 -> #REF! | E33: =+'[2]Dispersión Gto de Staff'!E49 -> #REF! | F33: =+'[2]Dispersión Gto de Staff'!F49 -> #REF! | G33: =+'[2]Dispersión Gto de Staff'!G49 -> #REF! | H33: =+'[2]Dispersión Gto de Staff'!H49 -> #REF! | I33: =+'[2]Dispersión Gto de Staff'!I49 -> #REF! | J33: =+'[2]Dispersión Gto de Staff'!J49 -> #REF! | ... N33: =+'[2]Dispersión Gto de Staff'!N49 -> #REF! | O33: =+SUM(C33:N33) -> #REF!
B34: Costos Totales | C34: =SUM(C31:C33) -> #REF! | D34: =SUM(D31:D33) -> #REF! | E34: =SUM(E31:E33) -> #REF! | F34: =SUM(F31:F33) -> #REF! | G34: =SUM(G31:G33) -> #REF! | H34: =SUM(H31:H33) -> #REF! | I34: =SUM(I31:I33) -> #REF! | J34: =SUM(J31:J33) -> #REF! | ... O34: =SUM(O31:O33) -> #REF!
B35: Contribución Bruta | C35: =C30+C34 -> #REF! | D35: =D30+D34 -> #REF! | E35: =E30+E34 -> #REF! | F35: =F30+F34 -> #REF! | G35: =G30+G34 -> #REF! | H35: =H30+H34 -> #REF! | I35: =I30+I34 -> #REF! | J35: =J30+J34 -> #REF! | ... O35: =O30+O34 -> #REF!
B36: Personal | C36: =+'[3]Final Staff Consolidado'!R27+'[3]Final Staff Consolidado'!R49 -> #REF! | D36: =+'[3]Final Staff Consolidado'!S27+'[3]Final Staff Consolidado'!S49 -> #REF! | E36: =+'[3]Final Staff Consolidado'!T27+'[3]Final Staff Consolidado'!T49 -> #REF! | F36: =+'[3]Final Staff Consolidado'!U27+'[3]Final Staff Consolidado'!U49 -> #REF! | G36: =+'[3]Final Staff Consolidado'!V27+'[3]Final Staff Consolidado'!V49 -> #REF! | H36: =+'[3]Final Staff Consolidado'!W27+'[3]Final Staff Consolidado'!W49 -> #REF! | I36: =+'[3]Final Staff Consolidado'!X27+'[3]Final Staff Consolidado'!X49 -> #REF! | J36: =+'[3]Final Staff Consolidado'!Y27+'[3]Final Staff Consolidado'!Y49 -> #REF! | ... N36: =+'[3]Final Staff Consolidado'!AC27+'[3]Final Staff Consolidado'!AC49 -> #REF! | O36: =+SUM(C36:N36) -> #REF!
B37: Operación | C37: ='[2]Dispersión Gto de Staff'!C46+[4]ND!C23+[5]Hoja1!S97 -> #ERROR! | D37: ='[2]Dispersión Gto de Staff'!D46+[4]ND!D23+[5]Hoja1!T97 -> #ERROR! | E37: ='[2]Dispersión Gto de Staff'!E46+[4]ND!E23+[5]Hoja1!U97 -> #ERROR! | F37: ='[2]Dispersión Gto de Staff'!F46+[4]ND!F23+[5]Hoja1!V97 -> #ERROR! | G37: ='[2]Dispersión Gto de Staff'!G46+[4]ND!G23+[5]Hoja1!W97 -> #ERROR! | H37: ='[2]Dispersión Gto de Staff'!H46+[4]ND!H23+[5]Hoja1!X97 -> #ERROR! | I37: ='[2]Dispersión Gto de Staff'!I46+[4]ND!I23+[5]Hoja1!Y97 -> #ERROR! | J37: ='[2]Dispersión Gto de Staff'!J46+[4]ND!J23+[5]Hoja1!Z97 -> #ERROR! | ... N37: ='[2]Dispersión Gto de Staff'!N46+[4]ND!N23+[5]Hoja1!AD97 -> #ERROR! | O37: =+SUM(C37:N37) -> #ERROR!
B38: Mercadotecnia | C38: ='[2]Dispersión Gto de Staff'!C47+[4]ND!C24 -> #ERROR! | D38: ='[2]Dispersión Gto de Staff'!D47+[4]ND!D24 -> #ERROR! | E38: ='[2]Dispersión Gto de Staff'!E47+[4]ND!E24 -> #ERROR! | F38: ='[2]Dispersión Gto de Staff'!F47+[4]ND!F24 -> #ERROR! | G38: ='[2]Dispersión Gto de Staff'!G47+[4]ND!G24 -> #ERROR! | H38: ='[2]Dispersión Gto de Staff'!H47+[4]ND!H24 -> #ERROR! | I38: ='[2]Dispersión Gto de Staff'!I47+[4]ND!I24 -> #ERROR! | J38: ='[2]Dispersión Gto de Staff'!J47+[4]ND!J24 -> #ERROR! | ... N38: ='[2]Dispersión Gto de Staff'!N47+[4]ND!N24 -> #ERROR! | O38: =+SUM(C38:N38) -> #ERROR!
B39: Mantenimiento de Software | C39: =+'[2]Dispersión Gto de Staff'!C50+[6]FDS!B106 -> #ERROR! | D39: =+'[2]Dispersión Gto de Staff'!D50+[6]FDS!C106 -> #ERROR! | E39: =+'[2]Dispersión Gto de Staff'!E50+[6]FDS!D106 -> #ERROR! | F39: =+'[2]Dispersión Gto de Staff'!F50+[6]FDS!E106 -> #ERROR! | G39: =+'[2]Dispersión Gto de Staff'!G50+[6]FDS!F106 -> #ERROR! | H39: =+'[2]Dispersión Gto de Staff'!H50+[6]FDS!G106 -> #ERROR! | I39: =+'[2]Dispersión Gto de Staff'!I50+[6]FDS!H106 -> #ERROR! | J39: =+'[2]Dispersión Gto de Staff'!J50+[6]FDS!I106 -> #ERROR! | ... N39: =+'[2]Dispersión Gto de Staff'!N50+[6]FDS!M106 -> #ERROR! | O39: =+SUM(C39:N39) -> #ERROR!
B40: Staff Sistemas | C40: =+'[2]Dispersión Gto de Staff'!C51 -> #REF! | D40: =+'[2]Dispersión Gto de Staff'!D51 -> #REF! | E40: =+'[2]Dispersión Gto de Staff'!E51 -> #REF! | F40: =+'[2]Dispersión Gto de Staff'!F51 -> #REF! | G40: =+'[2]Dispersión Gto de Staff'!G51 -> #REF! | H40: =+'[2]Dispersión Gto de Staff'!H51 -> #REF! | I40: =+'[2]Dispersión Gto de Staff'!I51 -> #REF! | J40: =+'[2]Dispersión Gto de Staff'!J51 -> #REF! | ... N40: =+'[2]Dispersión Gto de Staff'!N51 -> #REF! | O40: =+SUM(C40:N40) -> #REF!
